Workbook
Name _04_7065: #REF!
Name Code: #REF!
Name Code6: #REF!
Name DATA: #REF!
Name Focus: #REF!
Name PN: #REF!
Name PN_Description: #REF!
Name PT_EndRow: COUNTA(#REF!)+PT_StartRow-3
Name PT_EndRow: COUNTA(#REF!)+PT_StartRow-3
Name PT_StartRow: ROW(INDEX(#REF!,MATCH("*",#REF!,0),1))+1
Name ชื่อสาขา: #REF!
Name ชื่อสินค้า: #REF!
Name ยอดขาย: #REF!

Sheet EXC.VAT-ไม่รวม VAT Thomas
A1: Commission & Outlet Rebate Calculation Form
A2: Outlet :
A3: BDE : | D3: Types & Sub Types :
A4: Period : | D4: Area :
A5: Supervisor : | D5: Agent :
G6: ACTUAL OFF TAKE | J6: TOTAL ACTUAL OFF TAKE VALUE
A7: Principle | B7: Category | C7: Brand | D7: Product | E7: Size | F7: Packing | G7: Price INC.VAT | H7: Price EXC.VAT | I7: Vol. Btls. | J7: Total Price Inc.VAT | K7: Total Price Exc.VAT | L7: Rebate % | M7: Rebate Value
A8: TEG | B8: Single Malt Scotch | C8: The Macallan | D8: The Macallan Sherry Oak 12YO | E8: 700ml | F8: 12 | G8: =H8*1.07 -> 0 | J8: =G8*I8 -> 0 | K8: =H8*I8 -> 0 | M8: =K8*L8 -> 0
A9: TEG | B9: Single Malt Scotch | C9: The Macallan | D9: The Macallan Triple Cask 12YO | E9: 700ml | F9: 12 | G9: =H9*1.07 -> 0 | J9: =G9*I9 -> 0 | K9: =H9*I9 -> 0 | M9: =K9*L9 -> 0
A10: TEG | B10: Single Malt Scotch | C10: The Macallan | D10: The Macallan Double Cask 12YO | E10: 700ml | F10: 12 | G10: =H10*1.07 -> 0 | J10: =G10*I10 -> 0 | K10: =H10*I10 -> 0 | M10: =K10*L10 -> 0
A11: TEG | B11: Single Malt Scotch | C11: The Macallan | D11: The Macallan Double Cask 15YO | E11: 700ml | F11: 6 | G11: =H11*1.07 -> 0 | J11: =G11*I11 -> 0 | K11: =H11*I11 -> 0 | M11: =K11*L11 -> 0
A12: TEG | B12: Single Malt Scotch | C12: The Macallan | D12: The Macallan Triple Cask 15YO | E12: 700ml | F12: 6 | G12: =H12*1.07 -> 0 | J12: =G12*I12 -> 0 | K12: =H12*I12 -> 0 | M12: =K12*L12 -> 0
A13: TEG | B13: Single Malt Scotch | C13: The Macallan | D13: The Macalan Double Cask 18YO | E13: 700ml | F13: 6 | G13: =H13*1.07 -> 0 | J13: =G13*I13 -> 0 | K13: =H13*I13 -> 0 | M13: =K13*L13 -> 0
A14: TEG | B14: Single Malt Scotch | C14: The Macallan | D14: The Macallan Sherry Oak 18YO | E14: 700ml | F14: 6 | G14: =H14*1.07 -> 0 | J14: =G14*I14 -> 0 | K14: =H14*I14 -> 0 | M14: =K14*L14 -> 0
A15: TEG | B15: Single Malt Scotch | C15: The Macallan | D15: The Macallan Sherry Oak 25YO | E15: 700ml | F15: 3 | G15: =H15*1.07 -> 0 | J15: =G15*I15 -> 0 | K15: =H15*I15 -> 0 | M15: =K15*L15 -> 0
A16: TEG | B16: Single Malt Scotch | C16: The Macallan | D16: The Macallan Harmony Collection | E16: 700ml | F16: 6 | G16: =H16*1.07 -> 0 | J16: =G16*I16 -> 0 | K16: =H16*I16 -> 0 | M16: =K16*L16 -> 0
A17: TEG | B17: Single Malt Scotch | C17: The Macallan | D17: The Macallan Rare Cask | E17: 700ml | F17: 3 | G17: =H17*1.07 -> 0 | J17: =G17*I17 -> 0 | K17: =H17*I17 -> 0 | M17: =K17*L17 -> 0
A18: TEG | B18: Single Malt Scotch | C18: The Macallan | D18: The Macallan Reflexion | E18: 700ml | F18: 2 | G18: =H18*1.07 -> 0 | J18: =G18*I18 -> 0 | K18: =H18*I18 -> 0 | M18: =K18*L18 -> 0
A19: TEG | B19: Single Malt Scotch | C19: The Macallan | D19: The Macallan Classic Cut Whisky | E19: 700ml | F19: 12 | G19: =H19*1.07 -> 0 | J19: =G19*I19 -> 0 | K19: =H19*I19 -> 0 | M19: =K19*L19 -> 0
... A59: Campari | B59: American Whiskey | C59: Wild Turkey | D59: Russell's Reserve 10YO | E59: 750ml | F59: 6 | G59: =H59*1.07 -> 0 | J59: =G59*I59 -> 0 | K59: =H59*I59 -> 0 | M59: =K59*L59 -> 0
A60: Campari | B60: American Whiskey | C60: Wild Turkey | D60: Wild Turkey Forgiven | E60: 750ml | G60: =H60*1.07 -> 0 | J60: =G60*I60 -> 0 | K60: =H60*I60 -> 0 | M60: =K60*L60 -> 0
A61: Campari | B61: American Whiskey | C61: Wild Turkey | D61: Wild Turkey Masters 17YO | E61: 750ml | F61: 6 | G61: =H61*1.07 -> 0 | J61: =G61*I61 -> 0 | K61: =H61*I61 -> 0 | M61: =K61*L61 -> 0
A62: Campari | B62: American Whiskey | C62: Wild Turkey | D62: Wild Turkey American Honey 35.5% | E62: 750ml | F62: 12 | G62: =H62*1.07 -> 0 | J62: =G62*I62 -> 0 | K62: =H62*I62 -> 0 | M62: =K62*L62 -> 0
A63: Independent | B63: Japanese Whiskey | C63: Kyoto | D63: Kyoto Whisky Aka Obi | E63: 700ml | F63: 12 | G63: =H63*1.07 -> 0 | J63: =G63*I63 -> 0 | K63: =H63*I63 -> 0 | M63: =K63*L63 -> 0
A64: Independent | B64: Japanese Whiskey | C64: Kyoto | D64: Kyoto Whisky Murasaki-Obi | E64: 700ml | F64: 12 | G64: =H64*1.07 -> 0 | J64: =G64*I64 -> 0 | K64: =H64*I64 -> 0 | M64: =K64*L64 -> 0
A65: Independent | B65: Japanese Whiskey | C65: Kyoto | D65: Kyoto Whisky Kuro-Obi | E65: 700ml | F65: 12 | G65: =H65*1.07 -> 0 | J65: =G65*I65 -> 0 | K65: =H65*I65 -> 0 | M65: =K65*L65 -> 0
A66: Campari | B66: Cachaca | C66: Sagatiba | D66: Sagatiba Cachaca | E66: 700ml | F66: 6 | G66: =H66*1.07 -> 0 | J66: =G66*I66 -> 0 | K66: =H66*I66 -> 0 | M66: =K66*L66 -> 0
A67: Campari | B67: RUM | C67: Appleton | D67: Appleton White Jamaican | E67: 750ml | F67: 12 | G67: =H67*1.07 -> 0 | J67: =G67*I67 -> 0 | K67: =H67*I67 -> 0 | M67: =K67*L67 -> 0
A68: Campari | B68: RUM | C68: Appleton | D68: Appleton Special Dark Jamaican | E68: 750ml | F68: 12 | G68: =H68*1.07 -> 0 | J68: =G68*I68 -> 0 | K68: =H68*I68 -> 0 | M68: =K68*L68 -> 0
A69: Campari | B69: RUM | C69: Appleton | D69: Appleton VX Jamaican | E69: 750ml | G69: =H69*1.07 -> 0 | J69: =G69*I69 -> 0 | K69: =H69*I69 -> 0 | M69: =K69*L69 -> 0
A70: Campari | B70: RUM | C70: Appleton | D70: Appleton Estate Reserve Jamaican | E70: 750ml | F70: 12 | G70: =H70*1.07 -> 0 | J70: =G70*I70 -> 0 | K70: =H70*I70 -> 0 | M70: =K70*L70 -> 0
A71: Campari | B71: RUM | C71: Appleton | D71: Appleton Estate Signature Jamaican Blend | E71: 750ml | F71: 12 | G71: =H71*1.07 -> 0 | J71: =G71*I71 -> 0 | K71: =H71*I71 -> 0 | M71: =K71*L71 -> 0
A72: Campari | B72: RUM | C72: Appleton | D72: Appleton Estate 12YO Rare Cask | E72: 750ml | F72: 12 | G72: =H72*1.07 -> 0 | J72: =G72*I72 -> 0 | K72: =H72*I72 -> 0 | M72: =K72*L72 -> 0
A73: Campari | B73: RUM | C73: Appleton | D73: Appleton Estate 21YO Jamaican | E73: 750ml | F73: 6 | G73: =H73*1.07 -> 0 | J73: =G73*I73 -> 0 | K73: =H73*I73 -> 0 | M73: =K73*L73 -> 0
A74: Campari | B74: RUM | C74: Appleton | D74: Appleton Estate 30YO Jamaican | E74: 750ml | F74: 6 | G74: =H74*1.07 -> 0 | J74: =G74*I74 -> 0 | K74: =H74*I74 -> 0 | M74: =K74*L74 -> 0
A75: Campari | B75: RUM | C75: Kingston | D75: Kingston 62 Jamaica Gold Rum | E75: 750ml | F75: 12 | G75: =H75*1.07 -> 0 | J75: =G75*I75 -> 0 | K75: =H75*I75 -> 0 | M75: =K75*L75 -> 0
A76: RC | B76: RUM | C76: Mt Gay | D76: Mt Gay Eclipse Barbados | E76: 700ml | F76: 6 | G76: =H76*1.07 -> 0 | J76: =G76*I76 -> 0 | K76: =H76*I76 -> 0 | M76: =K76*L76 -> 0
A77: RC | B77: RUM | C77: Mt Gay | D77: Mt Gay Black Barrel Barbados | E77: 700ml | F77: 6 | G77: =H77*1.07 -> 0 | J77: =G77*I77 -> 0 | K77: =H77*I77 -> 0 | M77: =K77*L77 -> 0
A78: RC | B78: RUM | C78: Mt Gay | D78: Mt Gay XO Barbados | E78: 700ml | F78: 6 | G78: =H78*1.07 -> 0 | J78: =G78*I78 -> 0 | K78: =H78*I78 -> 0 | M78: =K78*L78 -> 0
A79: TEG | B79: RUM | C79: Brugal | D79: Brugal Blanco Supremo White Rum | E79: 700ml | F79: 12 | G79: =H79*1.07 -> 0 | J79: =G79*I79 -> 0 | K79: =H79*I79 -> 0 | M79: =K79*L79 -> 0
A80: TEG | B80: RUM | C80: Brugal | D80: Brugal Anejo Superior Rum | E80: 700ml | F80: 6 | G80: =H80*1.07 -> 0 | J80: =G80*I80 -> 0 | K80: =H80*I80 -> 0 | M80: =K80*L80 -> 0
A81: TEG | B81: RUM | C81: Brugal | D81: Brugal 1888 Dominican | E81: 700ml | F81: 6 | G81: =H81*1.07 -> 0 | J81: =G81*I81 -> 0 | K81: =H81*I81 -> 0 | M81: =K81*L81 -> 0
... A138: Independent | B138: Mezcal | C138: Clase Azul | D138: Clase Azul Durango | E138: 750ml | F138: 3 | G138: =H138*1.07 -> 0 | J138: =G138*I138 -> 0 | K138: =H138*I138 -> 0 | M138: =K138*L138 -> 0
A139: Proximo | B139: Tequila | C139: 1800 | D139: 1800 Tequila Silver | E139: 750ml | F139: 12 | G139: =H139*1.07 -> 0 | J139: =G139*I139 -> 0 | K139: =H139*I139 -> 0 | M139: =K139*L139 -> 0
A140: Proximo | B140: Tequila | C140: 1800 | D140: 1800 Tequila Reposado | E140: 750ml | F140: 12 | G140: =H140*1.07 -> 0 | J140: =G140*I140 -> 0 | K140: =H140*I140 -> 0 | M140: =K140*L140 -> 0
A141: Proximo | B141: Tequila | C141: 1800 | D141: 1800 Tequila Coconut | E141: 750ml | F141: 12 | G141: =H141*1.07 -> 0 | J141: =G141*I141 -> 0 | K141: =H141*I141 -> 0 | M141: =K141*L141 -> 0
A142: Proximo | B142: Tequila | C142: 1800 | D142: 1800 Tequila Anejo | E142: 750ml | F142: 6 | G142: =H142*1.07 -> 0 | J142: =G142*I142 -> 0 | K142: =H142*I142 -> 0 | M142: =K142*L142 -> 0
A143: Proximo | B143: Tequila | C143: Jose Cuervo | D143: Jose Cuervo Reserva De La Familia | E143: 750ml | F143: 3 | G143: =H143*1.07 -> 0 | J143: =G143*I143 -> 0 | K143: =H143*I143 -> 0 | M143: =K143*L143 -> 0
A144: Proximo | B144: Tequila | C144: Jose Cuervo | D144: Jose Cuervo Platino | E144: 700ml | F144: 6 | G144: =H144*1.07 -> 0 | J144: =G144*I144 -> 0 | K144: =H144*I144 -> 0 | M144: =K144*L144 -> 0
A145: Proximo | B145: Tequila | C145: Jose Cuervo | D145: Jose Cuervo Tradicional Reposado | E145: 700ml | F145: 6 | G145: =H145*1.07 -> 0 | J145: =G145*I145 -> 0 | K145: =H145*I145 -> 0 | M145: =K145*L145 -> 0
A146: Proximo | B146: Tequila | C146: Jose Cuervo | D146: Jose Cuervo Tradicional Silver | E146: 700ml | F146: 6 | G146: =H146*1.07 -> 0 | J146: =G146*I146 -> 0 | K146: =H146*I146 -> 0 | M146: =K146*L146 -> 0
A147: Proximo | B147: Tequila | C147: Jose Cuervo | D147: Jose Cuervo Especial Reposdo | E147: 700ml | F147: 12 | G147: =H147*1.07 -> 0 | J147: =G147*I147 -> 0 | K147: =H147*I147 -> 0 | M147: =K147*L147 -> 0
A148: Proximo | B148: Tequila | C148: Jose Cuervo | D148: Jose Cuervo Especial Silver | E148: 700ml | F148: 12 | G148: =H148*1.07 -> 0 | J148: =G148*I148 -> 0 | K148: =H148*I148 -> 0 | M148: =K148*L148 -> 0
A149: Campari | B149: Tequila | C149: Espolon Tequila | D149: Espolon Tequila Reposado 40% | E149: 750ml | F149: 6 | G149: =H149*1.07 -> 0 | J149: =G149*I149 -> 0 | K149: =H149*I149 -> 0 | M149: =K149*L149 -> 0
A150: Campari | B150: Tequila | C150: Espolon Tequila | D150: Espolon Tequila Blanco 40% | E150: 750ml | F150: 6 | G150: =H150*1.07 -> 0 | J150: =G150*I150 -> 0 | K150: =H150*I150 -> 0 | M150: =K150*L150 -> 0
A151: Independent | B151: Tequila | C151: Clase Azul | D151: Clase Azul Plata Tequila | E151: 750ml | F151: 6 | G151: =H151*1.07 -> 0 | J151: =G151*I151 -> 0 | K151: =H151*I151 -> 0 | M151: =K151*L151 -> 0
A152: Independent | B152: Tequila | C152: Clase Azul | D152: Clase Azul Reposado Tequila | E152: 750ml | F152: 6 | G152: =H152*1.07 -> 0 | J152: =G152*I152 -> 0 | K152: =H152*I152 -> 0 | M152: =K152*L152 -> 0
A153: Independent | B153: Tequila | C153: Clase Azul | D153: Clase Azul Gold Tequila | E153: 750ml | F153: 3 | G153: =H153*1.07 -> 0 | J153: =G153*I153 -> 0 | K153: =H153*I153 -> 0 | M153: =K153*L153 -> 0
A154: Independent | B154: Tequila | C154: Clase Azul | D154: Clase Azul Anejo Tequila | E154: 750ml | F154: 3 | G154: =H154*1.07 -> 0 | J154: =G154*I154 -> 0 | K154: =H154*I154 -> 0 | M154: =K154*L154 -> 0
... A188: Campari | B188: Vermouth | C188: Cinzano | D188: Cinzano 1757 Vermouth Rosso | E188: 1000ml | F188: 6 | G188: =H188*1.07 -> 0 | J188: =G188*I188 -> 0 | K188: =H188*I188 -> 0 | M188: =K188*L188 -> 0
A189: Campari | B189: Vermouth | C189: Cinzano | D189: Cinzano 1757 Vermouth Bianco | G189: =H189*1.07 -> 0 | J189: =G189*I189 -> 0 | K189: =H189*I189 -> 0 | M189: =K189*L189 -> 0
A190: Campari | B190: Vermouth | C190: Cinzano | D190: Cinzano 1757 Vermouth Extra Dry | E190: 1000ml | F190: 6 | G190: =H190*1.07 -> 0 | J190: =G190*I190 -> 0 | K190: =H190*I190 -> 0 | M190: =K190*L190 -> 0
A191: Campari | B191: Sparkling | C191: Cinzano | D191: Cinzano Prosecco | E191: 750ml | F191: 6 | G191: =H191*1.07 -> 0 | J191: =G191*I191 -> 0 | K191: =H191*I191 -> 0 | M191: =K191*L191 -> 0
A192: Campari | B192: Sparkling | C192: Cinzano | D192: Cinzano Pinot Chardonnay | E192: 750ml | F192: 6 | G192: =H192*1.07 -> 0 | J192: =G192*I192 -> 0 | K192: =H192*I192 -> 0 | M192: =K192*L192 -> 0
A193: Campari | B193: Sparkling | C193: Cinzano | D193: Gran Cinzano Dolce | E193: 750ml | F193: 6 | G193: =H193*1.07 -> 0 | J193: =G193*I193 -> 0 | K193: =H193*I193 -> 0 | M193: =K193*L193 -> 0
A194: Campari | B194: Sparkling | C194: Cinzano | D194: Cinzano Asti Sparkling Wine | E194: 750ml | F194: 6 | G194: =H194*1.07 -> 0 | J194: =G194*I194 -> 0 | K194: =H194*I194 -> 0 | M194: =K194*L194 -> 0
A195: Campari | B195: Sparkling | C195: Cinzano | D195: Cinzano Rose Edition Sparkling Wine | E195: 750ml | F195: 6 | G195: =H195*1.07 -> 0 | J195: =G195*I195 -> 0 | K195: =H195*I195 -> 0 | M195: =K195*L195 -> 0
A196: Campari | B196: Sparkling | C196: Cinzano | D196: Cinzano To Spritz Dry Sparkling Wine | E196: 750ml | F196: 6 | G196: =H196*1.07 -> 0 | J196: =G196*I196 -> 0 | K196: =H196*I196 -> 0 | M196: =K196*L196 -> 0
A197: Independent | B197: Champagne | C197: Pommery | D197: Champagne Pommery Brut Royal | E197: 750ml | F197: 6 | G197: =H197*1.07 -> 0 | J197: =G197*I197 -> 0 | K197: =H197*I197 -> 0 | M197: =K197*L197 -> 0
A198: Independent | B198: Champagne | C198: Pommery | D198: Champagne Pommery Brut Rose Royal | E198: 750ml | F198: 6 | G198: =H198*1.07 -> 0 | J198: =G198*I198 -> 0 | K198: =H198*I198 -> 0 | M198: =K198*L198 -> 0
A199: Independent | B199: Champagne | C199: Pommery | D199: Champagne Pommery Royal Blue Sky | E199: 750ml | F199: 6 | G199: =H199*1.07 -> 0 | J199: =G199*I199 -> 0 | K199: =H199*I199 -> 0 | M199: =K199*L199 -> 0
A200: Independent | B200: Champagne | C200: Pommery | D200: Champagne Pommery Cuvee Louise 2004 | E200: 750ml | F200: 6 | G200: =H200*1.07 -> 0 | J200: =G200*I200 -> 0 | K200: =H200*I200 -> 0 | M200: =K200*L200 -> 0
A201: Independent | B201: Premium Fillers | C201: Thomas Henry | D201: Thomas Henry Tonic Water | E201: 200ml | F201: 24 | G201: =H201*1.07 -> 0 | J201: =G201*I201 -> 0 | K201: =H201*I201 -> 0 | M201: =K201*L201 -> 0
... A208: Independent | B208: Cider | C208: Rekorderlig | D208: Rekorderlig Wild Berries Bottle | E208: 330ml | F208: 24 | G208: =H208*1.07 -> 0 | J208: =G208*I208 -> 0 | K208: =H208*I208 -> 0 | M208: =K208*L208 -> 0
G209: =H209*1.07 -> 0 | J209: =G209*I209 -> 0 | K209: =H209*I209 -> 0 | M209: =K209*L209 -> 0
I210: =SUM(I8:I209) -> 0 | J210: =SUM(J8:J209) -> 0 | K210: =SUM(K8:K209) -> 0 | M210: =SUM(M8:M209) -> 0

Sheet INC.VAT-รวม VAT Thomas
A1: Commission & Outlet Rebate Calculation Form
A2: Outlet :
A3: BDE : | D3: Types & Sub Types :
A4: Period : | D4: Area :
A5: Supervisor : | D5: Agent :
G6: ACTUAL OFF TAKE | J6: TOTAL ACTUAL OFF TAKE VALUE
A7: Principle | B7: Category | C7: Brand | D7: Product | E7: Size | F7: Packing | G7: Price INC.VAT | H7: Price EXC.VAT | I7: Vol. Btls. | J7: Total Price Inc.VAT | K7: Total Price Exc.VAT | L7: Rebate % | M7: Rebate Value
A8: TEG | B8: Single Malt Scotch | C8: The Macallan | D8: The Macallan Sherry Oak 12YO | E8: 700ml | F8: 12 | H8: =G8/1.07 -> 0 | J8: =G8*I8 -> 0 | K8: =H8*I8 -> 0 | M8: =K8*L8 -> 0
A9: TEG | B9: Single Malt Scotch | C9: The Macallan | D9: The Macallan Triple Cask 12YO | E9: 700ml | F9: 12 | H9: =G9/1.07 -> 0 | J9: =G9*I9 -> 0 | K9: =H9*I9 -> 0 | M9: =K9*L9 -> 0
A10: TEG | B10: Single Malt Scotch | C10: The Macallan | D10: The Macallan Double Cask 12YO | E10: 700ml | F10: 12 | H10: =G10/1.07 -> 0 | J10: =G10*I10 -> 0 | K10: =H10*I10 -> 0 | M10: =K10*L10 -> 0
A11: TEG | B11: Single Malt Scotch | C11: The Macallan | D11: The Macallan Double Cask 15YO | E11: 700ml | F11: 6 | H11: =G11/1.07 -> 0 | J11: =G11*I11 -> 0 | K11: =H11*I11 -> 0 | M11: =K11*L11 -> 0
A12: TEG | B12: Single Malt Scotch | C12: The Macallan | D12: The Macallan Triple Cask 15YO | E12: 700ml | F12: 6 | H12: =G12/1.07 -> 0 | J12: =G12*I12 -> 0 | K12: =H12*I12 -> 0 | M12: =K12*L12 -> 0
A13: TEG | B13: Single Malt Scotch | C13: The Macallan | D13: The Macalan Double Cask 18YO | E13: 700ml | F13: 6 | H13: =G13/1.07 -> 0 | J13: =G13*I13 -> 0 | K13: =H13*I13 -> 0 | M13: =K13*L13 -> 0
A14: TEG | B14: Single Malt Scotch | C14: The Macallan | D14: The Macallan Sherry Oak 18YO | E14: 700ml | F14: 6 | H14: =G14/1.07 -> 0 | J14: =G14*I14 -> 0 | K14: =H14*I14 -> 0 | M14: =K14*L14 -> 0
A15: TEG | B15: Single Malt Scotch | C15: The Macallan | D15: The Macallan Sherry Oak 25YO | E15: 700ml | F15: 3 | H15: =G15/1.07 -> 0 | J15: =G15*I15 -> 0 | K15: =H15*I15 -> 0 | M15: =K15*L15 -> 0
A16: TEG | B16: Single Malt Scotch | C16: The Macallan | D16: The Macallan Harmony Collection | E16: 700ml | F16: 6 | H16: =G16/1.07 -> 0 | J16: =G16*I16 -> 0 | K16: =H16*I16 -> 0 | M16: =K16*L16 -> 0
A17: TEG | B17: Single Malt Scotch | C17: The Macallan | D17: The Macallan Rare Cask | E17: 700ml | F17: 3 | H17: =G17/1.07 -> 0 | J17: =G17*I17 -> 0 | K17: =H17*I17 -> 0 | M17: =K17*L17 -> 0
A18: TEG | B18: Single Malt Scotch | C18: The Macallan | D18: The Macallan Reflexion | E18: 700ml | F18: 2 | H18: =G18/1.07 -> 0 | J18: =G18*I18 -> 0 | K18: =H18*I18 -> 0 | M18: =K18*L18 -> 0
A19: TEG | B19: Single Malt Scotch | C19: The Macallan | D19: The Macallan Classic Cut Whisky | E19: 700ml | F19: 12 | H19: =G19/1.07 -> 0 | J19: =G19*I19 -> 0 | K19: =H19*I19 -> 0 | M19: =K19*L19 -> 0
... A59: Campari | B59: American Whiskey | C59: Wild Turkey | D59: Russell's Reserve 10YO | E59: 750ml | F59: 6 | H59: =G59/1.07 -> 0 | J59: =G59*I59 -> 0 | K59: =H59*I59 -> 0 | M59: =K59*L59 -> 0
A60: Campari | B60: American Whiskey | C60: Wild Turkey | D60: Wild Turkey Forgiven | E60: 750ml | H60: =G60/1.07 -> 0 | J60: =G60*I60 -> 0 | K60: =H60*I60 -> 0 | M60: =K60*L60 -> 0
A61: Campari | B61: American Whiskey | C61: Wild Turkey | D61: Wild Turkey Masters 17YO | E61: 750ml | F61: 6 | H61: =G61/1.07 -> 0 | J61: =G61*I61 -> 0 | K61: =H61*I61 -> 0 | M61: =K61*L61 -> 0
A62: Campari | B62: American Whiskey | C62: Wild Turkey | D62: Wild Turkey American Honey 35.5% | E62: 750ml | F62: 12 | H62: =G62/1.07 -> 0 | J62: =G62*I62 -> 0 | K62: =H62*I62 -> 0 | M62: =K62*L62 -> 0
A63: Independent | B63: Japanese Whiskey | C63: Kyoto | D63: Kyoto Whisky Aka Obi | E63: 700ml | F63: 12 | H63: =G63/1.07 -> 0 | J63: =G63*I63 -> 0 | K63: =H63*I63 -> 0 | M63: =K63*L63 -> 0
A64: Independent | B64: Japanese Whiskey | C64: Kyoto | D64: Kyoto Whisky Murasaki-Obi | E64: 700ml | F64: 12 | H64: =G64/1.07 -> 0 | J64: =G64*I64 -> 0 | K64: =H64*I64 -> 0 | M64: =K64*L64 -> 0
A65: Independent | B65: Japanese Whiskey | C65: Kyoto | D65: Kyoto Whisky Kuro-Obi | E65: 700ml | F65: 12 | H65: =G65/1.07 -> 0 | J65: =G65*I65 -> 0 | K65: =H65*I65 -> 0 | M65: =K65*L65 -> 0
A66: Campari | B66: Cachaca | C66: Sagatiba | D66: Sagatiba Cachaca | E66: 700ml | F66: 6 | H66: =G66/1.07 -> 0 | J66: =G66*I66 -> 0 | K66: =H66*I66 -> 0 | M66: =K66*L66 -> 0
A67: Campari | B67: RUM | C67: Appleton | D67: Appleton White Jamaican | E67: 750ml | F67: 12 | H67: =G67/1.07 -> 0 | J67: =G67*I67 -> 0 | K67: =H67*I67 -> 0 | M67: =K67*L67 -> 0
A68: Campari | B68: RUM | C68: Appleton | D68: Appleton Special Dark Jamaican | E68: 750ml | F68: 12 | H68: =G68/1.07 -> 0 | J68: =G68*I68 -> 0 | K68: =H68*I68 -> 0 | M68: =K68*L68 -> 0
A69: Campari | B69: RUM | C69: Appleton | D69: Appleton VX Jamaican | E69: 750ml | H69: =G69/1.07 -> 0 | J69: =G69*I69 -> 0 | K69: =H69*I69 -> 0 | M69: =K69*L69 -> 0
A70: Campari | B70: RUM | C70: Appleton | D70: Appleton Estate Reserve Jamaican | E70: 750ml | F70: 12 | H70: =G70/1.07 -> 0 | J70: =G70*I70 -> 0 | K70: =H70*I70 -> 0 | M70: =K70*L70 -> 0
A71: Campari | B71: RUM | C71: Appleton | D71: Appleton Estate Signature Jamaican Blend | E71: 750ml | F71: 12 | H71: =G71/1.07 -> 0 | J71: =G71*I71 -> 0 | K71: =H71*I71 -> 0 | M71: =K71*L71 -> 0
A72: Campari | B72: RUM | C72: Appleton | D72: Appleton Estate 12YO Rare Cask | E72: 750ml | F72: 12 | H72: =G72/1.07 -> 0 | J72: =G72*I72 -> 0 | K72: =H72*I72 -> 0 | M72: =K72*L72 -> 0
A73: Campari | B73: RUM | C73: Appleton | D73: Appleton Estate 21YO Jamaican | E73: 750ml | F73: 6 | H73: =G73/1.07 -> 0 | J73: =G73*I73 -> 0 | K73: =H73*I73 -> 0 | M73: =K73*L73 -> 0
A74: Campari | B74: RUM | C74: Appleton | D74: Appleton Estate 30YO Jamaican | E74: 750ml | F74: 6 | H74: =G74/1.07 -> 0 | J74: =G74*I74 -> 0 | K74: =H74*I74 -> 0 | M74: =K74*L74 -> 0
A75: Campari | B75: RUM | C75: Kingston | D75: Kingston 62 Jamaica Gold Rum | E75: 750ml | F75: 12 | H75: =G75/1.07 -> 0 | J75: =G75*I75 -> 0 | K75: =H75*I75 -> 0 | M75: =K75*L75 -> 0
A76: RC | B76: RUM | C76: Mt Gay | D76: Mt Gay Eclipse Barbados | E76: 700ml | F76: 6 | H76: =G76/1.07 -> 0 | J76: =G76*I76 -> 0 | K76: =H76*I76 -> 0 | M76: =K76*L76 -> 0
A77: RC | B77: RUM | C77: Mt Gay | D77: Mt Gay Black Barrel Barbados | E77: 700ml | F77: 6 | H77: =G77/1.07 -> 0 | J77: =G77*I77 -> 0 | K77: =H77*I77 -> 0 | M77: =K77*L77 -> 0
A78: RC | B78: RUM | C78: Mt Gay | D78: Mt Gay XO Barbados | E78: 700ml | F78: 6 | H78: =G78/1.07 -> 0 | J78: =G78*I78 -> 0 | K78: =H78*I78 -> 0 | M78: =K78*L78 -> 0
A79: TEG | B79: RUM | C79: Brugal | D79: Brugal Blanco Supremo White Rum | E79: 700ml | F79: 12 | H79: =G79/1.07 -> 0 | J79: =G79*I79 -> 0 | K79: =H79*I79 -> 0 | M79: =K79*L79 -> 0
A80: TEG | B80: RUM | C80: Brugal | D80: Brugal Anejo Superior Rum | E80: 700ml | F80: 6 | H80: =G80/1.07 -> 0 | J80: =G80*I80 -> 0 | K80: =H80*I80 -> 0 | M80: =K80*L80 -> 0
A81: TEG | B81: RUM | C81: Brugal | D81: Brugal 1888 Dominican | E81: 700ml | F81: 6 | H81: =G81/1.07 -> 0 | J81: =G81*I81 -> 0 | K81: =H81*I81 -> 0 | M81: =K81*L81 -> 0
... A138: Independent | B138: Mezcal | C138: Clase Azul | D138: Clase Azul Durango | E138: 750ml | F138: 3 | H138: =G138/1.07 -> 0 | J138: =G138*I138 -> 0 | K138: =H138*I138 -> 0 | M138: =K138*L138 -> 0
A139: Proximo | B139: Tequila | C139: 1800 | D139: 1800 Tequila Silver | E139: 750ml | F139: 12 | H139: =G139/1.07 -> 0 | J139: =G139*I139 -> 0 | K139: =H139*I139 -> 0 | M139: =K139*L139 -> 0
A140: Proximo | B140: Tequila | C140: 1800 | D140: 1800 Tequila Reposado | E140: 750ml | F140: 12 | H140: =G140/1.07 -> 0 | J140: =G140*I140 -> 0 | K140: =H140*I140 -> 0 | M140: =K140*L140 -> 0
A141: Proximo | B141: Tequila | C141: 1800 | D141: 1800 Tequila Coconut | E141: 750ml | F141: 12 | H141: =G141/1.07 -> 0 | J141: =G141*I141 -> 0 | K141: =H141*I141 -> 0 | M141: =K141*L141 -> 0
A142: Proximo | B142: Tequila | C142: 1800 | D142: 1800 Tequila Anejo | E142: 750ml | F142: 6 | H142: =G142/1.07 -> 0 | J142: =G142*I142 -> 0 | K142: =H142*I142 -> 0 | M142: =K142*L142 -> 0
A143: Proximo | B143: Tequila | C143: Jose Cuervo | D143: Jose Cuervo Reserva De La Familia | E143: 750ml | F143: 3 | H143: =G143/1.07 -> 0 | J143: =G143*I143 -> 0 | K143: =H143*I143 -> 0 | M143: =K143*L143 -> 0
A144: Proximo | B144: Tequila | C144: Jose Cuervo | D144: Jose Cuervo Platino | E144: 700ml | F144: 6 | H144: =G144/1.07 -> 0 | J144: =G144*I144 -> 0 | K144: =H144*I144 -> 0 | M144: =K144*L144 -> 0
A145: Proximo | B145: Tequila | C145: Jose Cuervo | D145: Jose Cuervo Tradicional Reposado | E145: 700ml | F145: 6 | H145: =G145/1.07 -> 0 | J145: =G145*I145 -> 0 | K145: =H145*I145 -> 0 | M145: =K145*L145 -> 0
A146: Proximo | B146: Tequila | C146: Jose Cuervo | D146: Jose Cuervo Tradicional Silver | E146: 700ml | F146: 6 | H146: =G146/1.07 -> 0 | J146: =G146*I146 -> 0 | K146: =H146*I146 -> 0 | M146: =K146*L146 -> 0
A147: Proximo | B147: Tequila | C147: Jose Cuervo | D147: Jose Cuervo Especial Reposdo | E147: 700ml | F147: 12 | H147: =G147/1.07 -> 0 | J147: =G147*I147 -> 0 | K147: =H147*I147 -> 0 | M147: =K147*L147 -> 0
A148: Proximo | B148: Tequila | C148: Jose Cuervo | D148: Jose Cuervo Especial Silver | E148: 700ml | F148: 12 | H148: =G148/1.07 -> 0 | J148: =G148*I148 -> 0 | K148: =H148*I148 -> 0 | M148: =K148*L148 -> 0
A149: Campari | B149: Tequila | C149: Espolon Tequila | D149: Espolon Tequila Reposado 40% | E149: 750ml | F149: 6 | H149: =G149/1.07 -> 0 | J149: =G149*I149 -> 0 | K149: =H149*I149 -> 0 | M149: =K149*L149 -> 0
A150: Campari | B150: Tequila | C150: Espolon Tequila | D150: Espolon Tequila Blanco 40% | E150: 750ml | F150: 6 | H150: =G150/1.07 -> 0 | J150: =G150*I150 -> 0 | K150: =H150*I150 -> 0 | M150: =K150*L150 -> 0
A151: Independent | B151: Tequila | C151: Clase Azul | D151: Clase Azul Plata Tequila | E151: 750ml | F151: 6 | H151: =G151/1.07 -> 0 | J151: =G151*I151 -> 0 | K151: =H151*I151 -> 0 | M151: =K151*L151 -> 0
A152: Independent | B152: Tequila | C152: Clase Azul | D152: Clase Azul Reposado Tequila | E152: 750ml | F152: 6 | H152: =G152/1.07 -> 0 | J152: =G152*I152 -> 0 | K152: =H152*I152 -> 0 | M152: =K152*L152 -> 0
A153: Independent | B153: Tequila | C153: Clase Azul | D153: Clase Azul Gold Tequila | E153: 750ml | F153: 3 | H153: =G153/1.07 -> 0 | J153: =G153*I153 -> 0 | K153: =H153*I153 -> 0 | M153: =K153*L153 -> 0
A154: Independent | B154: Tequila | C154: Clase Azul | D154: Clase Azul Anejo Tequila | E154: 750ml | F154: 3 | H154: =G154/1.07 -> 0 | J154: =G154*I154 -> 0 | K154: =H154*I154 -> 0 | M154: =K154*L154 -> 0
... A188: Campari | B188: Vermouth | C188: Cinzano | D188: Cinzano 1757 Vermouth Rosso | E188: 1000ml | F188: 6 | H188: =G188/1.07 -> 0 | J188: =G188*I188 -> 0 | K188: =H188*I188 -> 0 | M188: =K188*L188 -> 0
A189: Campari | B189: Vermouth | C189: Cinzano | D189: Cinzano 1757 Vermouth Bianco | H189: =G189/1.07 -> 0 | J189: =G189*I189 -> 0 | K189: =H189*I189 -> 0 | M189: =K189*L189 -> 0
A190: Campari | B190: Vermouth | C190: Cinzano | D190: Cinzano 1757 Vermouth Extra Dry | E190: 1000ml | F190: 6 | H190: =G190/1.07 -> 0 | J190: =G190*I190 -> 0 | K190: =H190*I190 -> 0 | M190: =K190*L190 -> 0
A191: Campari | B191: Sparkling | C191: Cinzano | D191: Cinzano Prosecco | E191: 750ml | F191: 6 | H191: =G191/1.07 -> 0 | J191: =G191*I191 -> 0 | K191: =H191*I191 -> 0 | M191: =K191*L191 -> 0
A192: Campari | B192: Sparkling | C192: Cinzano | D192: Cinzano Pinot Chardonnay | E192: 750ml | F192: 6 | H192: =G192/1.07 -> 0 | J192: =G192*I192 -> 0 | K192: =H192*I192 -> 0 | M192: =K192*L192 -> 0
A193: Campari | B193: Sparkling | C193: Cinzano | D193: Gran Cinzano Dolce | E193: 750ml | F193: 6 | H193: =G193/1.07 -> 0 | J193: =G193*I193 -> 0 | K193: =H193*I193 -> 0 | M193: =K193*L193 -> 0
A194: Campari | B194: Sparkling | C194: Cinzano | D194: Cinzano Asti Sparkling Wine | E194: 750ml | F194: 6 | H194: =G194/1.07 -> 0 | J194: =G194*I194 -> 0 | K194: =H194*I194 -> 0 | M194: =K194*L194 -> 0
A195: Campari | B195: Sparkling | C195: Cinzano | D195: Cinzano Rose Edition Sparkling Wine | E195: 750ml | F195: 6 | H195: =G195/1.07 -> 0 | J195: =G195*I195 -> 0 | K195: =H195*I195 -> 0 | M195: =K195*L195 -> 0
A196: Campari | B196: Sparkling | C196: Cinzano | D196: Cinzano To Spritz Dry Sparkling Wine | E196: 750ml | F196: 6 | H196: =G196/1.07 -> 0 | J196: =G196*I196 -> 0 | K196: =H196*I196 -> 0 | M196: =K196*L196 -> 0
A197: Independent | B197: Champagne | C197: Pommery | D197: Champagne Pommery Brut Royal | E197: 750ml | F197: 6 | H197: =G197/1.07 -> 0 | J197: =G197*I197 -> 0 | K197: =H197*I197 -> 0 | M197: =K197*L197 -> 0
A198: Independent | B198: Champagne | C198: Pommery | D198: Champagne Pommery Brut Rose Royal | E198: 750ml | F198: 6 | H198: =G198/1.07 -> 0 | J198: =G198*I198 -> 0 | K198: =H198*I198 -> 0 | M198: =K198*L198 -> 0
A199: Independent | B199: Champagne | C199: Pommery | D199: Champagne Pommery Royal Blue Sky | E199: 750ml | F199: 6 | H199: =G199/1.07 -> 0 | J199: =G199*I199 -> 0 | K199: =H199*I199 -> 0 | M199: =K199*L199 -> 0
A200: Independent | B200: Champagne | C200: Pommery | D200: Champagne Pommery Cuvee Louise 2004 | E200: 750ml | F200: 6 | H200: =G200/1.07 -> 0 | J200: =G200*I200 -> 0 | K200: =H200*I200 -> 0 | M200: =K200*L200 -> 0
A201: Independent | B201: Premium Fillers | C201: Thomas Henry | D201: Thomas Henry Tonic Water | E201: 200ml | F201: 24 | H201: =G201/1.07 -> 0 | J201: =G201*I201 -> 0 | K201: =H201*I201 -> 0 | M201: =K201*L201 -> 0
... A208: Independent | B208: Cider | C208: Rekorderlig | D208: Rekorderlig Wild Berries Bottle | E208: 330ml | F208: 24 | H208: =G208/1.07 -> 0 | J208: =G208*I208 -> 0 | K208: =H208*I208 -> 0 | M208: =K208*L208 -> 0
H209: =G209/1.07 -> 0 | J209: =G209*I209 -> 0 | K209: =H209*I209 -> 0 | M209: =K209*L209 -> 0
I210: =SUM(I8:I209) -> 0 | J210: =SUM(J8:J209) -> 0 | K210: =SUM(K8:K209) -> 0 | M210: =SUM(M8:M209) -> 0

Sheet INDEX
A1: Input data in yellow cell | G1: Instruction how to use this file | U1: DO NOT DELETE
B3: Outlet Name: | C3: Outlet Name | H3: Step 1.1 | I3: Go to "INDEX" tab. Input outlet data
I4: information about that outlet the outlet name, contract period, and other info are mapped to link with all the monthly sheet
B5: Legal Name: | C5: Outlet Company Limited | V5: Start Month | W5: End Month | Y5: Principle | AA5: Item | AB5: Description | AC5: Code | AD5: Pack | AE5: Size | AF5: Price Update 1 Aug 26 (Direct Ex.VAT
C6: (Please input in English. Go to website DBD to check Enghlish name) | V6: 45292 | W6: 46053 | Y6: ALL | AA6: 1 | AB6: SKYY VODKA ICE BUCKET | AC6: 00-3LICE-BUCKET00
B7: BDE: | C7: Name of BDE | V7: 45323 | W7: 46081 | Y7: TEG | AA7: 2 | AB7: แก้ว APEROL | AC7: 00-GLASS-APEROL00
V8: 45352 | W8: 46112 | Y8: RC | AA8: 3 | AB8: แก้ว CINZANO | AC8: 00-GLASS-CINZANO0
B9: Area: | C9: Area | V9: 45383 | W9: 46142 | Y9: Campari | AA9: 4 | AB9: BOLS SILVER TOP GIN | AC9: 01-SPGIN-07003727 | AD9: 6 | AE9: 700 | AF9: 462
V10: 45413 | W10: 46173 | Y10: Proximo | AA10: 5 | AB10: BOLS GENEVER | AC10: 01-SPGIN-07008005 | AD10: 6 | AE10: 700 | AF10: 2500
B11: Agent: | C11: Agent name | V11: 45444 | W11: 46203 | Y11: Independent | AA11: 6 | AB11: BOLS BROWN CREAM LIQUEUR | AC11: 01-SPLIQ-07002551 | AD11: 6 | AE11: 700 | AF11: 730
V12: 45474 | W12: 46234 | Y12: Lucas Bols | AA12: 7 | AB12: BOLS ELDERFLOWER | AC12: 01-SPLIQ-07002897 | AD12: 6 | AE12: 700 | AF12: 730
B13: Manager: | C13: Manager Name | V13: 45505 | W13: 46265 | AA13: 8 | AB13: BOLS TRIPLE SEC | AC13: 01-SPLIQ-07002941 | AD13: 6 | AE13: 700 | AF13: 730
V14: 45536 | W14: 46295 | AA14: 9 | AB14: BOLS AMARETTO | AC14: 01-SPLIQ-07006625 | AD14: 6 | AE14: 700 | AF14: 730
B15: Contract Start | C15: 46023 | V15: 45566 | W15: 46326 | AA15: 10 | AB15: BOLS APRICOT BRANDY | AC15: 01-SPLIQ-07006632 | AD15: 6 | AE15: 700 | AF15: 730
V16: 45597 | W16: 46356 | AA16: 11 | AB16: BOLS BLUE CURACAO | AC16: 01-SPLIQ-07006656 | AD16: 6 | AE16: 700 | AF16: 730
B17: Contract End | C17: 46387 | H17: Step 1.2 | I17: Go to "Mapping" tab. Input %Rebate for each SKU | V17: 45627 | W17: 46387 | AA17: 12 | AB17: BOLS CHERRY BRANDY | AC17: 01-SPLIQ-07006663 | AD17: 6 | AE17: 700 | AF17: 730
I18: The Rebate% will reflect in all monthly sheet | V18: 45658 | W18: 46418 | AA18: 13 | AB18: BOLS BANANA | AC18: 01-SPLIQ-07006694 | AD18: 6 | AE18: 700 | AF18: 730
B19: Contract Period | C19: =_xlfn.CONCAT(TEXT(C15, "dd mmm yy"), " - ", TEXT(C17, "dd mmm yy")) -> 01 Jan 26 - 31 Dec 26 | V19: 45689 | W19: 46446 | AA19: 14 | AB19: BOLS CREME DE CASSIS | AC19: 01-SPLIQ-07006700 | AD19: 6 | AE19: 700 | AF19: 730
V20: 45717 | W20: 46477 | AA20: 15 | AB20: BOLS CACAO BROWN | AC20: 01-SPLIQ-07006717 | AD20: 6 | AE20: 700 | AF20: 730
B21: Contract Type | C21: Marketing Contract & Yearly Contract | V21: 45748 | W21: 46507 | AA21: 16 | AB21: BOLS CACAO WHITE | AC21: 01-SPLIQ-07006724 | AD21: 6 | AE21: 700 | AF21: 730
V22: 45778 | W22: 46538 | AA22: 17 | AB22: BOLS DRY ORANGE | AC22: 01-SPLIQ-07006731 | AD22: 6 | AE22: 700 | AF22: 730
V23: 45809 | W23: 46568 | AA23: 18 | AB23: BOLS LYCHEE | AC23: 01-SPLIQ-07006786 | AD23: 6 | AE23: 700 | AF23: 730
V24: 45839 | W24: 46599 | AA24: 19 | AB24: BOLS MELON | AC24: 01-SPLIQ-07006809 | AD24: 6 | AE24: 700 | AF24: 730
V25: 45870 | W25: 46630 | AA25: 20 | AB25: BOLS PEACH | AC25: 01-SPLIQ-07006830 | AD25: 6 | AE25: 700 | AF25: 730
V26: 45901 | W26: 46660 | AA26: 21 | AB26: BOLS STRAWBERRY | AC26: 01-SPLIQ-07006885 | AD26: 6 | AE26: 700 | AF26: 730
V27: 45931 | W27: 46691 | AA27: 22 | AB27: BOLS SOUR APPLE | AC27: 01-SPLIQ-07009334 | AD27: 6 | AE27: 700 | AF27: 730
H28: Step 2. | I28: Go to each month tab. There are 3 things to input here | V28: 45962 | W28: 46721 | AA28: 23 | AB28: BOLS PEPPERMINT GREEN | AC28: 01-SPLIQ-07009408 | AD28: 6 | AE28: 700 | AF28: 730
H29: 1. Select the wholesaler based on each skus/invoices | M29: - Total rebate for all principle will show on top right summary | V29: 45992 | W29: 46752 | AA29: 24 | AB29: BOLS VODKA 700 ML. | AC29: 01-SPVOD-07000328 | AD29: 12 | AE29: 700
H30: 2. Input price per bottle : input only 1 column (J or K), which is either with or without VAT | M30: - Selected principle in the dropdown list to see each principle summary | V30: 46023 | W30: 46783 | AA30: 25 | AB30: BOLS VODKA 37.50% | AC30: 01-SPVOD-07008530 | AD30: 6 | AE30: 700 | AF30: 576
H31: 3. Input volume bottles for each skus | V31: 46054 | W31: 46812 | AA31: 26 | AB31: BOLS VODKA 1.0 LITER | AC31: 01-SPVOD-10000311 | AD31: 6 | AE31: 1000
H32: Please note that the wholesaler list is from company's data base. If the customer purchase directly with Alchemy, please select direct sales | V32: 46082 | W32: 46843 | AA32: 27 | AB32: BOLS VODKA 37.5% 1L | AC32: 01-SPVOD-10008547 | AD32: 6 | AE32: 1000 | AF32: 690
H33: For outlets that has an official summary or purchase from the outlet's system and cannot specify the wholesaler, please selet "Outlet Summary" | V33: 46113 | W33: 46873 | AA33: 28 | AB33: GALLIANO ESPRESSO LIQUEUR | AC33: 02-SPLIQ-05001661 | AD33: 6 | AE33: 500 | AF33: 1100
V34: 46143 | W34: 46904 | AA34: 29 | AB34: GALLIANO VANILLA (500 ML) | AC34: 02-SPLIQ-05009501 | AD34: 6 | AE34: 500 | AF34: 1100
V35: 46174 | W35: 46934 | AA35: 30 | AB35: GALLIANO VANILLA | AC35: 02-SPLIQ-07009594 | AD35: 6 | AE35: 700 | AF35: 1520
V36: 46204 | W36: 46965 | AA36: 31 | AB36: HENKES GIN | AC36: 03-SPGIN-07504125 | AD36: 6 | AE36: 750 | AF36: 770
V37: 46235 | W37: 46996 | AA37: 32 | AB37: THE MACALLAN M BLACK SCOTCH WHISKY (2023) | AC37: 04-23MBL-07000168 | AD37: 1 | AE37: 700
V38: 46266 | W38: 47026 | AA38: 33 | AB38: THE MACALLAN M COPPER SCOTCH WHISKY (2023) | AC38: 04-23MCO-07000175 | AD38: 1 | AE38: 700
V39: 46296 | W39: 47057 | AA39: 34 | AB39: THE MACALLAN M SCOTCH WHISKY (2023) | AC39: 04-23MDC-07000151 | AD39: 1 | AE39: 700
V40: 46327 | W40: 47087 | AA40: 35 | AB40: THE MACALLAN A NIGHT ON EARTH SCOTCH WHISKY Y23 | AC40: 04-23WHI-07001806 | AD40: 6 | AE40: 700 | AF40: 7100
V41: 46357 | W41: 47118 | AA41: 36 | AB41: THE MACALLAN HARMONY AMBER MEADOW WHISKY | AC41: 04-23WHI-07002322 | AD41: 12 | AE41: 700 | AF41: 12000
W42: 47149 | AA42: 37 | AB42: THE MACALLAN HARMONY VIBRANT OAK WHISKY | AC42: 04-24HMN-07002650 | AD42: 6 | AE42: 700 | AF42: 9700
W43: 47177 | AA43: 38 | AB43: THE MACALLAN A NIGHT ON EARTH IN JEREZ WHISKY Y2 | AC43: 04-24NOE-07002766 | AD43: 6 | AE43: 700
W44: 47208 | AA44: 39 | AB44: THE MACALLAN HARMONY PHOENIX HONEY WHISKY (2025) | AC44: 04-25HMN-07002971 | AD44: 6 | AE44: 700 | AF44: 9700
W45: 47238 | AA45: 40 | AB45: THE MACALLAN A NIGHT ON EARTH FIRST LIGHT WHISKY | AC45: 04-25NOE-07003381 | AD45: 6 | AE45: 700 | AF45: 7190
W46: 47269 | AA46: 41 | AB46: THE MACALLAN DOUBLE CASK 30 YEARS OLD WHISKY | AC46: 04-SPWHI-07000311 | AD46: 3 | AE46: 700 | AF46: 250200
W47: 47299 | AA47: 42 | AB47: THE MACALLAN HARMONY COLLECTION | AC47: 04-SPWHI-07000557 | AD47: 6 | AE47: 700 | AF47: 11810
W48: 47330 | AA48: 43 | AB48: THE MACALLAN TRIPLE CASK MATURED 12 Y.O. | AC48: 04-SPWHI-07000796 | AD48: 12 | AE48: 700
W49: 47361 | AA49: 44 | AB49: THE MACALLAN A NIGHT ON EARTH SCOTCH WHISKY Y22 | AC49: 04-SPWHI-07001080 | AD49: 6 | AE49: 700 | AF49: 7100
W50: 47391 | AA50: 45 | AB50: THE MACALLAN A NIGHT ON EARTH SCOTCH WHISKY | AC50: 04-SPWHI-07001155 | AD50: 6 | AE50: 700
W51: 47422 | AA51: 46 | AB51: THE MACALLAN CLASSIC CUT WHISKY | AC51: 04-SPWHI-07001162 | AD51: 12 | AE51: 700 | AF51: 7890
W52: 47452 | AA52: 47 | AB52: THE MACALLAN HARMONY COLLECTION INTENSE ARABICA | AC52: 04-SPWHI-07001226 | AD52: 6 | AE52: 700 | AF52: 12000
W53: 47483 | AA53: 48 | AB53: THE MACALLAN ART IS THE FLOWER WHISKY | AC53: 04-SPWHI-07001622 | AD53: 4 | AE53: 700 | AF53: 44900
AA54: 49 | AB54: THE MACALLAN CLASSIC CUT 2022 WHISKY | AC54: 04-SPWHI-07001872 | AD54: 12 | AE54: 700
H55: Step 3. | I55: To view summary of the outlet performance in this year and wholesale summary please see sheet "SUMMARY" and "WHOLESALE" | AA55: 50 | AB55: THE MACALLAN EDITION NO 1 WHISKY | AC55: 04-SPWHI-07002668 | AD55: 1 | AE55: 700
AA56: 51 | AB56: THE MACALLAN EDITION NO 2 WHISKY | AC56: 04-SPWHI-07002910 | AD56: 1 | AE56: 700
AA57: 52 | AB57: THE MACALLAN TIME SPACE MASTERY WHISKY | AC57: 04-SPWHI-07002919 | AD57: 1 | AE57: 700 | AF57: 68700
AA58: 53 | AB58: THE MACALLAN DOUBLE CASK 12 YEARS OLD | AC58: 04-SPWHI-07003009 | AD58: 12 | AE58: 700 | AF58: 4600
AA59: 54 | AB59: THE MACALLAN FOLIO 8 SCOTCH WHISKY | AC59: 04-SPWHI-07003299 | AD59: 1 | AE59: 700 | AF59: 35700
AA60: 55 | AB60: THE MACALLAN M SCOTCH WHISKY | AC60: 04-SPWHI-07003372 | AD60: 1 | AE60: 700
AA61: 56 | AB61: THE MACALLAN EDITION NO.3 | AC61: 04-SPWHI-07004105 | AD61: 12 | AE61: 700
AA62: 57 | AB62: THE MACALLAN EDITION NO.4 | AC62: 04-SPWHI-07005591 | AD62: 12 | AE62: 700
AA63: 58 | AB63: THE MACALLAN 25 YEARS OLD | AC63: 04-SPWHI-07006031 | AD63: 3 | AE63: 700 | AF63: 123000
AA64: 59 | AB64: THE MACALLAN SHERRY OAK 30 YEARS OLD WHISKY | AC64: 04-SPWHI-07006048 | AD64: 3 | AE64: 700 | AF64: 287200
AA65: 60 | AB65: THE MACALLAN 18 Y.O. | AC65: 04-SPWHI-07007126 | AD65: 6 | AE65: 700
AA66: 61 | AB66: THE MACALLAN SHERRY OAK CASK 12 Y.O. | AC66: 04-SPWHI-07007491 | AD66: 12 | AE66: 700 | AF66: 5150
AA67: 62 | AB67: THE MACALLAN DOUBLE CASK 15 YEARS OLD | AC67: 04-SPWHI-07007700 | AD67: 6 | AE67: 700 | AF67: 8600
AA68: 63 | AB68: THE MACALLAN RARE CASK WHISKY (2023) | AC68: 04-SPWHI-07007984 | AD68: 3 | AE68: 700 | AF68: 24350
AA69: 64 | AB69: THE MACALLAN EDITION NO.5 | AC69: 04-SPWHI-07008059 | AD69: 12 | AE69: 700
AA70: 65 | AB70: THE MACALLAN DOUBLE CASK 18 YEARS OLD | AC70: 04-SPWHI-07009254 | AD70: 6 | AE70: 700 | AF70: 19950
AA71: 66 | AB71: THE MACALLAN EDITION NO.6 | AC71: 04-SPWHI-07009285 | AD71: 12 | AE71: 700
AA72: 67 | AB72: THE MACALLAN SHERRY OAK CASK 18 Y.O. | AC72: 04-SPWHI-07017065 | AD72: 6 | AE72: 700 | AF72: 22160
AA73: 68 | AB73: THE MACALLAN EDITION GIFT SET | AC73: 04-SPWHI-4200GSET | AD73: 1 | AE73: 4200
AA74: 69 | AB74: THE FAMOUS GROUSE BLENDED SW 700 ML. | AC74: 06-SPWHI-07000096 | AD74: 12 | AE74: 700 | AF74: 779
AA75: 70 | AB75: THE FAMOUS GROUSE SHERRY CASK SCOTCH WHISKY | AC75: 06-SPWHI-07000649 | AD75: 6 | AE75: 700 | AF75: 1150
AA76: 71 | AB76: THE FAMOUS GROUSE SMOKY BLACK SCOTCH WHISKY | AC76: 06-SPWHI-07002675 | AD76: 6 | AE76: 700 | AF76: 1150
AA77: 72 | AB77: NAKED GROUSE BLENDED MALT SW | AC77: 06-SPWHI-07004082 | AD77: 6 | AE77: 700
AA78: 73 | AB78: NAKED MALT BLENDED MALT SCOTCH WHISKY | AC78: 06-SPWHI-07014082 | AD78: 6 | AE78: 700 | AF78: 1730
AA79: 74 | AB79: THE FAMOUS GROUSE BLENDED SW 1.0 LITER | AC79: 06-SPWHI-10001091 | AD79: 12 | AE79: 1000 | AF79: 1040
AA80: 75 | AB80: BRUGAL BLANCO SUPREMO RUM | AC80: 07-SPRUM-07000534 | AD80: 12 | AE80: 700 | AF80: 830
AA81: 76 | AB81: BRUGAL ANEJO SUPERIOR RUM | AC81: 07-SPRUM-07001468 | AD81: 6 | AE81: 700
AA82: 77 | AB82: BRUGAL 1888 RUM | AC82: 07-SPRUM-07002960 | AD82: 6 | AE82: 700 | AF82: 2990
AA83: 78 | AB83: PASSOA LIQUEUR | AC83: 09-SPLIQ-07001757 | AD83: 6 | AE83: 700 | AF83: 870
AA84: 79 | AB84: VACCARI SAMBUCA | AC84: 09-SPLIQ-07009136 | AD84: 6 | AE84: 700
AA85: 80 | AB85: HIGHLAND PARK 15 YEARS OLD SCOTCH WHISKY | AC85: 11-SPWHI-07000489 | AD85: 6 | AE85: 700 | AF85: 6930
AA86: 81 | AB86: HIGHLAND PARK 12 YEAR OLD | AC86: 11-SPWHI-07000996 | AD86: 6 | AE86: 700 | AF86: 3930
AA87: 82 | AB87: HIGHLAND PARK 10 YEARS OLD SCOTCH WHISKEY | AC87: 11-SPWHI-07003795 | AD87: 6 | AE87: 700 | AF87: 2595
AA88: 83 | AB88: HIGHLAND PARK 18 YEAR OLD | AC88: 11-SPWHI-07005191 | AD88: 6 | AE88: 700 | AF88: 10500
AA89: 84 | AB89: HIGHLAND PARK VALKNUT | AC89: 11-SPWHI-07006123 | AD89: 6 | AE89: 700
AA90: 85 | AB90: HIGHLAND PARK VALFATHER SCOTCH WHISKY | AC90: 11-SPWHI-07008264 | AD90: 6 | AE90: 700 | AF90: 5480
AA91: 86 | AB91: THE GLENROTHES VINTAGE RESERVE 12 Y.O. | AC91: 12-SPWHI-07000235 | AD91: 6 | AE91: 700
AA92: 87 | AB92: THE GLENROTHES 12 YEARS OLD | AC92: 12-SPWHI-07005935 | AD92: 6 | AE92: 700 | AF92: 3930
AA93: 88 | AB93: THE GLENROTHES WHISKY MAKER'S CUT | AC93: 12-SPWHI-07005942 | AD93: 6 | AE93: 700 | AF93: 6200
AA94: 89 | AB94: THE GLENROTHES 18 YEARS OLD | AC94: 12-SPWHI-07005959 | AD94: 6 | AE94: 700 | AF94: 9080
AA95: 90 | AB95: THE GLENROTHES 25 YEARS OLD | AC95: 12-SPWHI-07005966 | AD95: 4 | AE95: 700 | AF95: 41100
H96: Step 4. | I96: Go to "Payment Form" tab. Input data (price per bt, volume and %rebate) in column J to O | AA96: 91 | AB96: NO.3 LONDON DRY GIN | AC96: 13-SPGIN-07006017 | AD96: 6 | AE96: 700
I97: 3.1 Select Cheque date and don't forget to change the claim period | AA97: 92 | AB97: NO.3 LONDON DRY ORGANIC GIN | AC97: 13-SPGIN-07007377 | AD97: 6 | AE97: 700 | AF97: 2860
I98: 3.2 Tick check box to choose rebate period, rebate value will auto-generated | AA98: 93 | AB98: LICOR 43 | AC98: 15-SPLIQ-07000154 | AD98: 6 | AE98: 700
I99: 3.3 Select Local Generation or Brand Owner Investment | AA99: 94 | AB99: FOUR PILLARS BARREL AGED GIN | AC99: 16-SPGIN-07000157 | AD99: 6 | AE99: 700
AA100: 95 | AB100: FOUR PILLARS RARE DRY GIN | AC100: 16-SPGIN-07000194 | AD100: 6 | AE100: 700 | AF100: 1730
AA101: 96 | AB101: FOUR PILLARS BLOODY SHIRAZ GIN | AC101: 16-SPGIN-07000256 | AD101: 6 | AE101: 700 | AF101: 2010
...

Sheet FOC FORM
Q1: Original-Accounting
G2: Alchemy Wines and Spirits (Thailand) Co., Ltd.
A5: FOC FORM
A6: SHOP NAME : | D6: =INDEX!C3 -> Outlet Name | O6: DATE: | P6: 46023
A7: Company/Personal Name : | F7: =INDEX!C5 -> Outlet Company Limited | N7: =IF(F7="","Required","") | O7: Bring out by:- | R7: =IF(O9="","Required","") | U7: https://datawarehouse.dbd.go.th/index
A9: ที่อยู่จัดส่ง : | O9: =INDEX!C7 -> Name of BDE
O10: Type of Investment:
P11: =IF(AND(P12="",P13=""),"Required","")
A12: Delivery Date : | N12: =IF(C12="","Required","") -> Required | P12: x | Q12: Local Generation
A13: Time : | C13: From | D13: 0.47916667 | I13: To | J13: 0.47916667 | N13: =IF(OR(D13="",J13=""),"Required","") | Q13: Brand Owner Investment
A14: ผู้ติดต่อ : | C14: ภาษาไทยเท่านั้น | I14: TEL:
A17: NO. | B17: INVENTORY ID. | G17: NAME | O17: QUANTITY | Q17: UNIT
A18: 1 | B18: 324 | C18: =_xlfn.XLOOKUP(G18,MAPPING!G:G,MAPPING!B:B,"",) -> 01-SPVOD-07008530 | G18: Bols Vodka 700ml | O18: =IF('REBATE TO FOC CALC'!K34="", "", 'REBATE TO FOC CALC'!K34) | Q18: =IF(G18="","-","Bottle") -> Bottle
A19: 2 | C19: =_xlfn.XLOOKUP(G19,MAPPING!G:G,MAPPING!B:B,"",) | G19: =IF('REBATE TO FOC CALC'!E35="", "", 'REBATE TO FOC CALC'!E35) | O19: =IF('REBATE TO FOC CALC'!K35="", "", 'REBATE TO FOC CALC'!K35) | Q19: =IF(G19="","-","Bottle") -> -
A20: 3 | C20: =_xlfn.XLOOKUP(G20,MAPPING!G:G,MAPPING!B:B,"",) | G20: =IF('REBATE TO FOC CALC'!E36="", "", 'REBATE TO FOC CALC'!E36) | O20: =IF('REBATE TO FOC CALC'!K36="", "", 'REBATE TO FOC CALC'!K36) | Q20: =IF(G20="","-","Bottle") -> -
A21: 4 | C21: =_xlfn.XLOOKUP(G21,MAPPING!G:G,MAPPING!B:B,"",) | G21: =IF('REBATE TO FOC CALC'!E37="", "", 'REBATE TO FOC CALC'!E37) | O21: =IF('REBATE TO FOC CALC'!K37="", "", 'REBATE TO FOC CALC'!K37) | Q21: =IF(G21="","-","Bottle") -> -
A22: 5 | C22: =_xlfn.XLOOKUP(G22,MAPPING!G:G,MAPPING!B:B,"",) | G22: =IF('REBATE TO FOC CALC'!E38="", "", 'REBATE TO FOC CALC'!E38) | O22: =IF('REBATE TO FOC CALC'!K38="", "", 'REBATE TO FOC CALC'!K38) | Q22: =IF(G22="","-","Bottle") -> -
A23: 6 | C23: =_xlfn.XLOOKUP(G23,MAPPING!G:G,MAPPING!B:B,"",) | G23: =IF('REBATE TO FOC CALC'!E39="", "", 'REBATE TO FOC CALC'!E39) | O23: =IF('REBATE TO FOC CALC'!K39="", "", 'REBATE TO FOC CALC'!K39) | Q23: =IF(G23="","-","Bottle") -> -
A24: 7 | C24: =_xlfn.XLOOKUP(G24,MAPPING!G:G,MAPPING!B:B,"",) | G24: =IF('REBATE TO FOC CALC'!E40="", "", 'REBATE TO FOC CALC'!E40) | O24: =IF('REBATE TO FOC CALC'!K40="", "", 'REBATE TO FOC CALC'!K40) | Q24: =IF(G24="","-","Bottle") -> -
A25: 8 | C25: =_xlfn.XLOOKUP(G25,MAPPING!G:G,MAPPING!B:B,"",) | G25: =IF('REBATE TO FOC CALC'!E41="", "", 'REBATE TO FOC CALC'!E41) | O25: =IF('REBATE TO FOC CALC'!K41="", "", 'REBATE TO FOC CALC'!K41) | Q25: =IF(G25="","-","Bottle") -> -
A26: 9 | C26: =_xlfn.XLOOKUP(G26,MAPPING!G:G,MAPPING!B:B,"",) | G26: =IF('REBATE TO FOC CALC'!E42="", "", 'REBATE TO FOC CALC'!E42) | O26: =IF('REBATE TO FOC CALC'!K42="", "", 'REBATE TO FOC CALC'!K42) | Q26: =IF(G26="","-","Bottle") -> -
A27: 10 | C27: =_xlfn.XLOOKUP(G27,MAPPING!G:G,MAPPING!B:B,"",) | G27: =IF('REBATE TO FOC CALC'!E43="", "", 'REBATE TO FOC CALC'!E43) | O27: =IF('REBATE TO FOC CALC'!K43="", "", 'REBATE TO FOC CALC'!K43) | Q27: =IF(G27="","-","Bottle") -> -
A28: 11 | C28: =_xlfn.XLOOKUP(G28,MAPPING!G:G,MAPPING!B:B,"",) | G28: =IF('REBATE TO FOC CALC'!E44="", "", 'REBATE TO FOC CALC'!E44) | O28: =IF('REBATE TO FOC CALC'!K44="", "", 'REBATE TO FOC CALC'!K44) | Q28: =IF(G28="","-","Bottle") -> -
A29: 12 | C29: =_xlfn.XLOOKUP(G29,MAPPING!G:G,MAPPING!B:B,"",) | G29: =IF('REBATE TO FOC CALC'!E45="", "", 'REBATE TO FOC CALC'!E45) | O29: =IF('REBATE TO FOC CALC'!K45="", "", 'REBATE TO FOC CALC'!K45) | Q29: =IF(G29="","-","Bottle") -> -
C30: =_xlfn.XLOOKUP(G30,MAPPING!G:G,MAPPING!B:B,"",) | G30: =IF('REBATE TO FOC CALC'!E46="", "", 'REBATE TO FOC CALC'!E46) | O30: =IF('REBATE TO FOC CALC'!K46="", "", 'REBATE TO FOC CALC'!K46)
A31: Detail Of Use : | L31: TOTAL | O31: =SUM(O18:P30) -> 0
A32: Contract Period: | C32: =INDEX!C19 -> 01 Jan 26 - 31 Dec 26
A33: Claim Period:
A34: Promotion:
A35: Reason
A41: Department
A43: Purpose
A44: FALSE | B44: Tasting & Training (06) | G44: FALSE | H44: Sponsorship (08) | K44: FALSE | L44: Event (09) | N44: FALSE | O44: Rebate (11) | Q44: FALSE | R44: PR / Media (12)
A46: FALSE | B46: Borrow | G46: FALSE | H46: Consignment
A49: Requested by | D49: Pay Off By | I49: Mgr.Approved | O49: Marketing Manager
A52: Date ….... / …..... / …..... | D52: Date …….. / ….….. / …….. | I52: Date …….. / ….….. / …….. | O52: Date …….. / ….….. / ……..
A54: =INDEX!C7 -> Name of BDE | D54: (….........................................) | I54: (….........................................) | O54: (….........................................)
A56: ผู้ส่งสินค้า (Delivered by) | I56: ผู้รับสินค้า (For Customer Received by)
A58: …..................................................................................ลงนาม(Please sign here) | I58: …..................................................................................ลงนาม(Please sign here)
A59: ( ) | I59: ( )
A60: วันที่ (Date)............/.........../............. | I60: วันที่ (Date)............/.........../.............

Sheet CASH REBATE
D7: Request for Rebate Payment
F9: Cheque Date : | G9: X | H9: Payment on 15th.
H10: (Submit document 10 days in advance, cut off on 5th)
H11: Payment on 30th.
H12: (Submit document 10 days in advance, cut off on 20th)
F13: Amount (THB) : | H13: =J36 -> 0
F14: Outlet Name : | H14: =INDEX!C3 -> Outlet Name
F15: Vendor Name : | H15: =INDEX!C5 -> Outlet Company Limited
E18: Contract Period : | G18: =INDEX!C19 -> 01 Jan 26 - 31 Dec 26
E20: Claim Period : | G20: {=IF(COUNTIF(P22:Q32,TRUE)=0,"",TEXT(MIN(IF(P22:P32=TRUE,E22:E32),IF(Q22:Q32=TRUE,I22:I32)),"mmm yy")&IF(COUNTIF(P22:Q32,TRUE)=1,""," - "&TEXT(MAX(IF(P22:P32=TRUE,E22:E32),IF(Q22:Q32=TRUE,I22:I32)),"mmm yy")))}
E22: 46023 | F22: =IF(P22=TRUE,'01'!$T$3,0) -> 0 | I22: 46204 | J22: =IF(Q22=TRUE,'07'!$T$3,0) -> 0 | P22: FALSE | Q22: FALSE
E24: 46054 | F24: =IF(P24=TRUE,'02'!$T$3,0) -> 0 | I24: 46235 | J24: =IF(Q24=TRUE,'08'!$T$3,0) -> 0 | P24: FALSE | Q24: FALSE
E26: 46082 | F26: =IF(P26=TRUE,'03'!$T$3,0) -> 0 | I26: 46266 | J26: =IF(Q26=TRUE,'09'!$T$3,0) -> 0 | P26: FALSE | Q26: FALSE
E28: 46113 | F28: =IF(P28=TRUE,'04'!$T$3,0) -> 0 | I28: 46296 | J28: =IF(Q28=TRUE,'10'!$T$3,0) -> 0 | P28: FALSE | Q28: FALSE
E30: 46143 | F30: =IF(P30=TRUE,'05'!$T$3,0) -> 0 | I30: 46327 | J30: =IF(Q30=TRUE,'11'!$T$3,0) -> 0 | P30: FALSE | Q30: FALSE
E32: 46174 | F32: =IF(P32=TRUE,'06'!$T$3,0) -> 0 | I32: 46357 | J32: =IF(Q32=TRUE,'12'!$T$3,0) -> 0 | P32: FALSE | Q32: FALSE
H36: TOTAL | J36: =SUM(F22:F32,J22:J32) -> 0
F39: BRAND OWNER INVESTMENT | I39: X | J39: LOCAL GENERATION COSTS
F40: (Need Marketing approval)
G42: Bank acc or Promptpay number : | H42: 111-1-11111-1
G44: Bank acc / Promptpay name : | H44: English Name Co., Ltd.
F46: Email : | H46: For sending payment advice (will send to requester email if not specify)
F50: Requested By | I50: Verified By
F52: …..... /…..... / …..... | I52: …..... /…..... / ….....

Sheet REBATE TO FOC CALC
C4: REBATE TO FOC CALCULATION SHEET
C6: Outlet Name: | E6: =INDEX!C3 -> Outlet Name | I6: Area: | J6: =INDEX!C9 -> Area
C7: Legal Name: | E7: =INDEX!C5 -> Outlet Company Limited | I7: BDE: | J7: =INDEX!C7 -> Name of BDE
C8: Type of Contract | E8: =INDEX!C21 -> Marketing Contract & Yearly Contract
C9: Contract Period: | E9: =INDEX!C19 -> 01 Jan 26 - 31 Dec 26
E11: Contract Period : | G11: =INDEX!C19 -> 01 Jan 26 - 31 Dec 26
E13: Claim Period : | G13: {=IF(COUNTIF(C15:C25,TRUE)+COUNTIF(I15:I25,TRUE)=0,"",TEXT(MIN(IF(C15:C25=TRUE,D15:D25),IF(I15:I25=TRUE,J15:J25)),"mmm yy")&IF(COUNTIF(C15:C25,TRUE)+COUNTIF(I15:I25,TRUE)=1,""," - "&TEXT(MAX(IF(C15:C25=TRUE,D15:D25),IF(I15:I25=TRUE,J15:J25)),"mmm yy")))}
P14: DO NOT DELETE
C15: FALSE | D15: 46023 | F15: =IF(C15=TRUE,'01'!$T$3,0) -> 0 | I15: FALSE | J15: 46204 | L15: =IF(I15=TRUE,'07'!$T$3,0) -> 0
P16: FALSE | Q16: FALSE
C17: FALSE | D17: 46054 | F17: =IF(C17=TRUE,'02'!$T$3,0) -> 0 | I17: FALSE | J17: 46235 | L17: =IF(I17=TRUE,'08'!$T$3,0) -> 0
P18: FALSE | Q18: FALSE
C19: FALSE | D19: 46082 | F19: =IF(C19=TRUE,'03'!$T$3,0) -> 0 | I19: FALSE | J19: 46266 | L19: =IF(I19=TRUE,'09'!$T$3,0) -> 0
P20: FALSE | Q20: FALSE
C21: FALSE | D21: 46113 | F21: =IF(C21=TRUE,'04'!$T$3,0) -> 0 | I21: FALSE | J21: 46296 | L21: =IF(I21=TRUE,'10'!$T$3,0) -> 0
C23: FALSE | D23: 46143 | F23: =IF(C23=TRUE,'05'!$T$3,0) -> 0 | I23: FALSE | J23: 46327 | L23: =IF(I23=TRUE,'11'!$T$3,0) -> 0 | P23: FALSE | Q23: FALSE
C25: FALSE | D25: 46174 | F25: =IF(C25=TRUE,'06'!$T$3,0) -> 0 | I25: FALSE | J25: 46357 | L25: =IF(I25=TRUE,'12'!$T$3,0) -> 0 | P25: FALSE | Q25: FALSE
I27: CLAIMABLE VALUE | L27: =SUM(F15:F25,L15:L25) -> 0 | P27: FALSE | Q27: FALSE
D30: FOC VALUE CALCULATION
J32: INPUT PRICE/BTL HERE
C33: INVENTORY ID. | E33: PRODUCT | H33: SIZE | J33: UNIT PRICE | K33: BTL | L33: VALUE (THB)
C34: =_xlfn.XLOOKUP(E34,MAPPING!G:G,MAPPING!B:B,"",) -> 0 | H34: =_xlfn.XLOOKUP(E34,MAPPING!G:G,MAPPING!H:H,"",) -> 0 | J34: =_xlfn.XLOOKUP(C34,MAPPING!B:B,MAPPING!M:M,"",) | L34: =IFERROR(K34*J34,"")
C35: =_xlfn.XLOOKUP(E35,MAPPING!G:G,MAPPING!B:B,"",) -> 0 | H35: =_xlfn.XLOOKUP(E35,MAPPING!G:G,MAPPING!H:H,"",) -> 0 | J35: =_xlfn.XLOOKUP(C35,MAPPING!B:B,MAPPING!M:M,"",) | L35: =IFERROR(K35*J35,"")
C36: =_xlfn.XLOOKUP(E36,MAPPING!G:G,MAPPING!B:B,"",) -> 0 | H36: =_xlfn.XLOOKUP(E36,MAPPING!G:G,MAPPING!H:H,"",) -> 0 | J36: =_xlfn.XLOOKUP(C36,MAPPING!B:B,MAPPING!M:M,"",) | L36: =IFERROR(K36*J36,"")
C37: =_xlfn.XLOOKUP(E37,MAPPING!G:G,MAPPING!B:B,"",) -> 0 | H37: =_xlfn.XLOOKUP(E37,MAPPING!G:G,MAPPING!H:H,"",) -> 0 | J37: =_xlfn.XLOOKUP(C37,MAPPING!B:B,MAPPING!M:M,"",) | L37: =IFERROR(K37*J37,"")
C38: =_xlfn.XLOOKUP(E38,MAPPING!G:G,MAPPING!B:B,"",) -> 0 | H38: =_xlfn.XLOOKUP(E38,MAPPING!G:G,MAPPING!H:H,"",) -> 0 | J38: =_xlfn.XLOOKUP(C38,MAPPING!B:B,MAPPING!M:M,"",) | L38: =IFERROR(K38*J38,"")
C39: =_xlfn.XLOOKUP(E39,MAPPING!G:G,MAPPING!B:B,"",) -> 0 | H39: =_xlfn.XLOOKUP(E39,MAPPING!G:G,MAPPING!H:H,"",) -> 0 | J39: =_xlfn.XLOOKUP(C39,MAPPING!B:B,MAPPING!M:M,"",) | L39: =IFERROR(K39*J39,"")
C40: =_xlfn.XLOOKUP(E40,MAPPING!G:G,MAPPING!B:B,"",) -> 0 | H40: =_xlfn.XLOOKUP(E40,MAPPING!G:G,MAPPING!H:H,"",) -> 0 | J40: =_xlfn.XLOOKUP(C40,MAPPING!B:B,MAPPING!M:M,"",) | L40: =IFERROR(K40*J40,"")
C41: =_xlfn.XLOOKUP(E41,MAPPING!G:G,MAPPING!B:B,"",) -> 0 | H41: =_xlfn.XLOOKUP(E41,MAPPING!G:G,MAPPING!H:H,"",) -> 0 | J41: =_xlfn.XLOOKUP(C41,MAPPING!B:B,MAPPING!M:M,"",) | L41: =IFERROR(K41*J41,"")
C42: =_xlfn.XLOOKUP(E42,MAPPING!G:G,MAPPING!B:B,"",) -> 0 | H42: =_xlfn.XLOOKUP(E42,MAPPING!G:G,MAPPING!H:H,"",) -> 0 | J42: =_xlfn.XLOOKUP(C42,MAPPING!B:B,MAPPING!M:M,"",) | L42: =IFERROR(K42*J42,"")
C43: =_xlfn.XLOOKUP(E43,MAPPING!G:G,MAPPING!B:B,"",) -> 0 | H43: =_xlfn.XLOOKUP(E43,MAPPING!G:G,MAPPING!H:H,"",) -> 0 | J43: =_xlfn.XLOOKUP(C43,MAPPING!B:B,MAPPING!M:M,"",) | L43: =IFERROR(K43*J43,"")
C44: =_xlfn.XLOOKUP(E44,MAPPING!G:G,MAPPING!B:B,"",) -> 0 | H44: =_xlfn.XLOOKUP(E44,MAPPING!G:G,MAPPING!H:H,"",) -> 0 | J44: =_xlfn.XLOOKUP(C44,MAPPING!B:B,MAPPING!M:M,"",) | L44: =IFERROR(K44*J44,"")
C45: =_xlfn.XLOOKUP(E45,MAPPING!G:G,MAPPING!B:B,"",) -> 0 | H45: =_xlfn.XLOOKUP(E45,MAPPING!G:G,MAPPING!H:H,"",) -> 0 | J45: =_xlfn.XLOOKUP(C45,MAPPING!B:B,MAPPING!M:M,"",) | L45: =IFERROR(K45*J45,"")
... C48: =_xlfn.XLOOKUP(E48,MAPPING!G:G,MAPPING!B:B,"",) -> 0 | H48: =_xlfn.XLOOKUP(E48,MAPPING!G:G,MAPPING!H:H,"",) -> 0 | J48: =_xlfn.XLOOKUP(C48,MAPPING!B:B,MAPPING!M:M,"",) | L48: =IFERROR(K48*J48,"")
C49: TOTAL | K49: =SUM(K34:K48) -> 0 | L49: =SUM(L34:L48) -> 0
I51: CLAIMABLE VALUE | L51: =L27 -> 0
I52: ACTUAL CLAIM | L52: =L49 -> 0
I53: DIFFERENCE | L53: =L51-L52 -> 0

Sheet WHOLESALE
B1: Outlet Rebate Calculation Form
B2: Outlet Name: | C2: =IF(INDEX!C3="","",INDEX!C3) -> Outlet Name | E2: Area: | F2: =IF(INDEX!C9="","",INDEX!C9) -> Area
B4: Legal Name: | C4: =IF(INDEX!C5="","",INDEX!C5) -> Outlet Company Limited | E4: Agent: | F4: =IF(INDEX!C11="","",INDEX!C11) -> Agent name
B6: BDE: | C6: =IF(INDEX!C7="","",INDEX!C7) -> Name of BDE | E6: Supervisor: | F6: =IF(INDEX!C13="","",INDEX!C13) -> Manager Name
B10: *To Add other wholesaler, please type in the last line | D10: =SUBTOTAL(9, D12:D59) -> 0 | E10: =SUBTOTAL(9, E12:E59) -> 0 | F10: =SUBTOTAL(9, F12:F59) -> 0
B11: Region | C11: WHOLESALER | D11: Volume BTLS | E11: Value INC VAT | F11: Value EX VAT | K11: Sheet | L11: Code | M11: Principle | N11: Category | O11: Brand | P11: Brand Code | Q11: Product | R11: Size | S11: Packing | T11: Wholesaler | U11: Price Inc. VAT | V11: Price Ex. VAT | W11: x | X11: Vol. (Btls.) | Y11: x | Z11: Rebate (%) | AA11: x | AB11: Total Price Inc. VAT | AC11: Total Price ex. VAT | AD11: Total Rebate
B12: BANGKOK | C12: Asia Liqour | D12: =IF(SUMIF($T:$T, C12, $X:$X)=0, "", SUMIF($T:$T, C12, $X:$X)) | E12: =IF(SUMIF($T:$T, C12, $U:$U)=0, "", SUMIF($T:$T, C12, $U:$U)) | F12: =IF(SUMIF($T:$T, C12, $V:$V)=0, "", SUMIF($T:$T, C12, $V:$V)) | K12: 1 | L12: {='01'!B13:T365} -> 04-SPWHI-07007491 | M12: TEG | N12: Single Malt Scotch | O12: The Macallan | P12: MAC | Q12: The Macallan Sherry Oak 12YO | R12: 700ml | S12: 12 | T12: 0 | U12: 0 | V12: 0 | W12: 0 | X12: 0 | Y12: 0 | Z12: 0 | AA12: 0 | AB12: 0 | AC12: 0 | AD12: 0
B13: BANGKOK | C13: Boozia | D13: =IF(SUMIF($T:$T, C13, $X:$X)=0, "", SUMIF($T:$T, C13, $X:$X)) | E13: =IF(SUMIF($T:$T, C13, $U:$U)=0, "", SUMIF($T:$T, C13, $U:$U)) | F13: =IF(SUMIF($T:$T, C13, $V:$V)=0, "", SUMIF($T:$T, C13, $V:$V)) | K13: 1 | L13: 04-SPWHI-07017065 | M13: TEG | N13: Single Malt Scotch | O13: The Macallan | P13: MAC | Q13: The Macallan Sherry Oak 18YO | R13: 700ml | S13: 6 | T13: 0 | U13: 0 | V13: 0 | W13: 0 | X13: 0 | Y13: 0 | Z13: 0 | AA13: 0 | AB13: 0 | AC13: 0 | AD13: 0
B14: BANGKOK | C14: Cherry Kansura | D14: =IF(SUMIF($T:$T, C14, $X:$X)=0, "", SUMIF($T:$T, C14, $X:$X)) | E14: =IF(SUMIF($T:$T, C14, $U:$U)=0, "", SUMIF($T:$T, C14, $U:$U)) | F14: =IF(SUMIF($T:$T, C14, $V:$V)=0, "", SUMIF($T:$T, C14, $V:$V)) | K14: 1 | L14: 04-SPWHI-07006031 | M14: TEG | N14: Single Malt Scotch | O14: The Macallan | P14: MAC | Q14: The Macallan Sherry Oak 25YO | R14: 700ml | S14: 3 | T14: 0 | U14: 0 | V14: 0 | W14: 0 | X14: 0 | Y14: 0 | Z14: 0 | AA14: 0 | AB14: 0 | AC14: 0 | AD14: 0
B15: BANGKOK | C15: Charoenchai | D15: =IF(SUMIF($T:$T, C15, $X:$X)=0, "", SUMIF($T:$T, C15, $X:$X)) | E15: =IF(SUMIF($T:$T, C15, $U:$U)=0, "", SUMIF($T:$T, C15, $U:$U)) | F15: =IF(SUMIF($T:$T, C15, $V:$V)=0, "", SUMIF($T:$T, C15, $V:$V)) | K15: 1 | L15: 04-SPWHI-07006048 | M15: TEG | N15: Single Malt Scotch | O15: The Macallan | P15: MAC | Q15: The Macallan Sherry Oak 30YO | R15: 700ml | S15: 3 | T15: 0 | U15: 0 | V15: 0 | W15: 0 | X15: 0 | Y15: 0 | Z15: 0 | AA15: 0 | AB15: 0 | AC15: 0 | AD15: 0
B16: BANGKOK | C16: CN Liqueur | D16: =IF(SUMIF($T:$T, C16, $X:$X)=0, "", SUMIF($T:$T, C16, $X:$X)) | E16: =IF(SUMIF($T:$T, C16, $U:$U)=0, "", SUMIF($T:$T, C16, $U:$U)) | F16: =IF(SUMIF($T:$T, C16, $V:$V)=0, "", SUMIF($T:$T, C16, $V:$V)) | K16: 1 | L16: 04-SPWHI-07003009 | M16: TEG | N16: Single Malt Scotch | O16: The Macallan | P16: MAC | Q16: The Macallan Double Cask 12YO | R16: 700ml | S16: 12 | T16: 0 | U16: 0 | V16: 0 | W16: 0 | X16: 0 | Y16: 0 | Z16: 0 | AA16: 0 | AB16: 0 | AC16: 0 | AD16: 0
B17: BANGKOK | C17: Direct Alchemy | D17: =IF(SUMIF($T:$T, C17, $X:$X)=0, "", SUMIF($T:$T, C17, $X:$X)) | E17: =IF(SUMIF($T:$T, C17, $U:$U)=0, "", SUMIF($T:$T, C17, $U:$U)) | F17: =IF(SUMIF($T:$T, C17, $V:$V)=0, "", SUMIF($T:$T, C17, $V:$V)) | K17: 1 | L17: 04-SPWHI-07007700 | M17: TEG | N17: Single Malt Scotch | O17: The Macallan | P17: MAC | Q17: The Macallan Double Cask 15YO | R17: 700ml | S17: 6 | T17: 0 | U17: 0 | V17: 0 | W17: 0 | X17: 0 | Y17: 0 | Z17: 0 | AA17: 0 | AB17: 0 | AC17: 0 | AD17: 0
B18: BANGKOK | C18: Den Udom | D18: =IF(SUMIF($T:$T, C18, $X:$X)=0, "", SUMIF($T:$T, C18, $X:$X)) | E18: =IF(SUMIF($T:$T, C18, $U:$U)=0, "", SUMIF($T:$T, C18, $U:$U)) | F18: =IF(SUMIF($T:$T, C18, $V:$V)=0, "", SUMIF($T:$T, C18, $V:$V)) | K18: 1 | L18: 04-SPWHI-07009254 | M18: TEG | N18: Single Malt Scotch | O18: The Macallan | P18: MAC | Q18: The Macallan Double Cask 18YO | R18: 700ml | S18: 6 | T18: 0 | U18: 0 | V18: 0 | W18: 0 | X18: 0 | Y18: 0 | Z18: 0 | AA18: 0 | AB18: 0 | AC18: 0 | AD18: 0
B19: BANGKOK | C19: Happy Goods | D19: =IF(SUMIF($T:$T, C19, $X:$X)=0, "", SUMIF($T:$T, C19, $X:$X)) | E19: =IF(SUMIF($T:$T, C19, $U:$U)=0, "", SUMIF($T:$T, C19, $U:$U)) | F19: =IF(SUMIF($T:$T, C19, $V:$V)=0, "", SUMIF($T:$T, C19, $V:$V)) | K19: 1 | L19: 04-SPWHI-07000311 | M19: TEG | N19: Single Malt Scotch | O19: The Macallan | P19: MAC | Q19: The Macallan Double Cask 30YO | R19: 700ml | S19: 3 | T19: 0 | U19: 0 | V19: 0 | W19: 0 | X19: 0 | Y19: 0 | Z19: 0 | AA19: 0 | AB19: 0 | AC19: 0 | AD19: 0
B20: BANGKOK | C20: Happy Spirit | D20: =IF(SUMIF($T:$T, C20, $X:$X)=0, "", SUMIF($T:$T, C20, $X:$X)) | E20: =IF(SUMIF($T:$T, C20, $U:$U)=0, "", SUMIF($T:$T, C20, $U:$U)) | F20: =IF(SUMIF($T:$T, C20, $V:$V)=0, "", SUMIF($T:$T, C20, $V:$V)) | K20: 1 | L20: 04-SPWHI-07000796 | M20: TEG | N20: Single Malt Scotch | O20: The Macallan | P20: MAC | Q20: The Macallan Triple Cask 12YO | R20: 700ml | S20: 12 | T20: 0 | U20: 0 | V20: 0 | W20: 0 | X20: 0 | Y20: 0 | Z20: 0 | AA20: 0 | AB20: 0 | AC20: 0 | AD20: 0
B21: BANGKOK | C21: King Store | D21: =IF(SUMIF($T:$T, C21, $X:$X)=0, "", SUMIF($T:$T, C21, $X:$X)) | E21: =IF(SUMIF($T:$T, C21, $U:$U)=0, "", SUMIF($T:$T, C21, $U:$U)) | F21: =IF(SUMIF($T:$T, C21, $V:$V)=0, "", SUMIF($T:$T, C21, $V:$V)) | K21: 1 | L21: 04-24HMN-07002650 | M21: TEG | N21: Single Malt Scotch | O21: The Macallan | P21: MAC | Q21: The Macallan Harmony Vibrant Oak | R21: 700ml | S21: 6 | T21: 0 | U21: 0 | V21: 0 | W21: 0 | X21: 0 | Y21: 0 | Z21: 0 | AA21: 0 | AB21: 0 | AC21: 0 | AD21: 0
B22: BANGKOK | C22: Mongkol Liquor | D22: =IF(SUMIF($T:$T, C22, $X:$X)=0, "", SUMIF($T:$T, C22, $X:$X)) | E22: =IF(SUMIF($T:$T, C22, $U:$U)=0, "", SUMIF($T:$T, C22, $U:$U)) | F22: =IF(SUMIF($T:$T, C22, $V:$V)=0, "", SUMIF($T:$T, C22, $V:$V)) | K22: 1 | L22: 04-23WHI-07002322 | M22: TEG | N22: Single Malt Scotch | O22: The Macallan | P22: MAC | Q22: The Macallan Harmony Collection Amber Meadow | R22: 700ml | S22: 12 | T22: 0 | U22: 0 | V22: 0 | W22: 0 | X22: 0 | Y22: 0 | Z22: 0 | AA22: 0 | AB22: 0 | AC22: 0 | AD22: 0
B23: BANGKOK | C23: Mercantile | D23: =IF(SUMIF($T:$T, C23, $X:$X)=0, "", SUMIF($T:$T, C23, $X:$X)) | E23: =IF(SUMIF($T:$T, C23, $U:$U)=0, "", SUMIF($T:$T, C23, $U:$U)) | F23: =IF(SUMIF($T:$T, C23, $V:$V)=0, "", SUMIF($T:$T, C23, $V:$V)) | K23: 1 | L23: 04-SPWHI-07000557 | M23: TEG | N23: Single Malt Scotch | O23: The Macallan | P23: MAC | Q23: The Macallan Harmony Collection | R23: 700ml | S23: 6 | T23: 0 | U23: 0 | V23: 0 | W23: 0 | X23: 0 | Y23: 0 | Z23: 0 | AA23: 0 | AB23: 0 | AC23: 0 | AD23: 0
B24: BANGKOK | C24: P.B. Liqueur | D24: =IF(SUMIF($T:$T, C24, $X:$X)=0, "", SUMIF($T:$T, C24, $X:$X)) | E24: =IF(SUMIF($T:$T, C24, $U:$U)=0, "", SUMIF($T:$T, C24, $U:$U)) | F24: =IF(SUMIF($T:$T, C24, $V:$V)=0, "", SUMIF($T:$T, C24, $V:$V)) | K24: 1 | L24: 04-SPWHI-07001226 | M24: TEG | N24: Single Malt Scotch | O24: The Macallan | P24: MAC | Q24: The Macallan Harmony Collection Intense Arabica | R24: 700ml | S24: 6 | T24: 0 | U24: 0 | V24: 0 | W24: 0 | X24: 0 | Y24: 0 | Z24: 0 | AA24: 0 | AB24: 0 | AC24: 0 | AD24: 0
... B73: SOUTH | C73: Trung Suratip | D73: =IF(SUMIF($T:$T, C73, $X:$X)=0, "", SUMIF($T:$T, C73, $X:$X)) | E73: =IF(SUMIF($T:$T, C73, $U:$U)=0, "", SUMIF($T:$T, C73, $U:$U)) | F73: =IF(SUMIF($T:$T, C73, $V:$V)=0, "", SUMIF($T:$T, C73, $V:$V)) | K73: 1 | L73: 23-SPWHI-07000197 | M73: Proximo | N73: Irish Whiskey | O73: Bushmills | P73: BUM | Q73: Bushmills Single Malt 12YO | R73: 700ml | S73: 6 | T73: 0 | U73: 0 | V73: 0 | W73: 0 | X73: 0 | Y73: 0 | Z73: 0 | AA73: 0 | AB73: 0 | AC73: 0 | AD73: 0
K74: 1 | L74: 23-SPWHI-07005022 | M74: Proximo | N74: Irish Whiskey | O74: Bushmills | P74: BUM | Q74: Bushmills Single Malt 16YO | R74: 700ml | S74: 6 | T74: 0 | U74: 0 | V74: 0 | W74: 0 | X74: 0 | Y74: 0 | Z74: 0 | AA74: 0 | AB74: 0 | AC74: 0 | AD74: 0
K75: 1 | L75: 23-SPWHI-07008268 | M75: Proximo | N75: Irish Whiskey | O75: Bushmills | P75: BUM | Q75: Bushmills Single Malt 21YO | R75: 700ml | S75: 6 | T75: 0 | U75: 0 | V75: 0 | W75: 0 | X75: 0 | Y75: 0 | Z75: 0 | AA75: 0 | AB75: 0 | AC75: 0 | AD75: 0
K76: 1 | L76: 47-SPWHI-07000010 | M76: Proximo | N76: Irish Whiskey | O76: The Sexton | P76: TST | Q76: Sexton Single Malt | R76: 700ml | S76: 6 | T76: 0 | U76: 0 | V76: 0 | W76: 0 | X76: 0 | Y76: 0 | Z76: 0 | AA76: 0 | AB76: 0 | AC76: 0 | AD76: 0
K77: 1 | L77: 37-SPWHI-07003251 | M77: Campari | N77: American Whiskey | O77: Wild Turkey | P77: WTK | Q77: Wild Turkey Aged 8 YO | R77: 700ml | S77: 12 | T77: 0 | U77: 0 | V77: 0 | W77: 0 | X77: 0 | Y77: 0 | Z77: 0 | AA77: 0 | AB77: 0 | AC77: 0 | AD77: 0
K78: 1 | L78: 37-SPWHI-07507508 | M78: Campari | N78: American Whiskey | O78: Wild Turkey | P78: WTK | Q78: Wild Turkey 101 Bourbon | R78: 750ml | S78: 12 | T78: 0 | U78: 0 | V78: 0 | W78: 0 | X78: 0 | Y78: 0 | Z78: 0 | AA78: 0 | AB78: 0 | AC78: 0 | AD78: 0
K79: 1 | L79: 37-SPWHI-07507503 | M79: Campari | N79: American Whiskey | O79: Wild Turkey | P79: WTK | Q79: Wild Turkey Bourbon 750ml | R79: 750ml | S79: 12 | T79: 0 | U79: 0 | V79: 0 | W79: 0 | X79: 0 | Y79: 0 | Z79: 0 | AA79: 0 | AB79: 0 | AC79: 0 | AD79: 0
K80: 1 | L80: 37-SPWHI-10001006 | M80: Campari | N80: American Whiskey | O80: Wild Turkey | P80: WTK | Q80: Wild Turkey Bourbon 1L | R80: 1000ml | S80: 12 | T80: 0 | U80: 0 | V80: 0 | W80: 0 | X80: 0 | Y80: 0 | Z80: 0 | AA80: 0 | AB80: 0 | AC80: 0 | AD80: 0
K81: 1 | L81: 37-SPWHI-07007019 | M81: Campari | N81: American Whiskey | O81: Wild Turkey | P81: WTK | Q81: Wild Turkey Rye 40.5% 700ml | R81: 700ml | S81: 6 | T81: 0 | U81: 0 | V81: 0 | W81: 0 | X81: 0 | Y81: 0 | Z81: 0 | AA81: 0 | AB81: 0 | AC81: 0 | AD81: 0
K82: 1 | L82: 37-SPWHI-07500229 | M82: Campari | N82: American Whiskey | O82: Wild Turkey | P82: WTK | Q82: Wild Turkey Rare Breed Bourbon 54.1% | R82: 750ml | S82: 6 | T82: 0 | U82: 0 | V82: 0 | W82: 0 | X82: 0 | Y82: 0 | Z82: 0 | AA82: 0 | AB82: 0 | AC82: 0 | AD82: 0
K83: 1 | L83: 37-SPWHI-07003268 | M83: Campari | N83: American Whiskey | O83: Wild Turkey | P83: WTK | Q83: Wild Turkey Aged 12 Years GB | R83: 700ml | S83: 6 | T83: 0 | U83: 0 | V83: 0 | W83: 0 | X83: 0 | Y83: 0 | Z83: 0 | AA83: 0 | AB83: 0 | AC83: 0 | AD83: 0
K84: 1 | L84: 37-SPLIQ-07507506 | M84: Campari | N84: American Whiskey | O84: Wild Turkey | P84: WTK | Q84: Wild Turkey American Honey 35.5% | R84: 750ml | S84: 12 | T84: 0 | U84: 0 | V84: 0 | W84: 0 | X84: 0 | Y84: 0 | Z84: 0 | AA84: 0 | AB84: 0 | AC84: 0 | AD84: 0
K85: 1 | L85: 37-WTWHI-07507507 | M85: Campari | N85: American Whiskey | O85: Wild Turkey | P85: WTK | Q85: Wild Turkey Kentucky Spirit Single Barrel | R85: 750ml | S85: 6 | T85: 0 | U85: 0 | V85: 0 | W85: 0 | X85: 0 | Y85: 0 | Z85: 0 | AA85: 0 | AB85: 0 | AC85: 0 | AD85: 0
... K336: 1 | L336: 29-SPGIN-07006351 | M336: Remy Cointreau | N336: Gin | O336: Botanist | P336: BOT | Q336: The Botanist Islay Dry Gin (Gift Box) | R336: 700ml | S336: 4 | T336: 0 | U336: 0 | V336: 0 | W336: 0 | X336: 0 | Y336: 0 | Z336: 0 | AA336: 0 | AB336: 0 | AC336: 0 | AD336: 0
K337: 1 | L337: 31-SPMIX-1450PACK | M337: Campari | N337: Liqueur | O337: Aperol/Cinzano | Q337: Aperol + Cinzano Prosecco | R337: 1450ml | S337: 3 | T337: 0 | U337: 0 | V337: 0 | W337: 0 | X337: 0 | Y337: 0 | Z337: 0 | AA337: 0 | AB337: 0 | AC337: 0 | AD337: 0
K338: 1 | L338: 31-SPPAC-07000575 | M338: Campari | N338: Liqueur | O338: Aperol | P338: APR | Q338: Aperol Glass Set | R338: 700ml | S338: 5 | T338: 0 | U338: 0 | V338: 0 | W338: 0 | X338: 0 | Y338: 0 | Z338: 0 | AA338: 0 | AB338: 0 | AC338: 0 | AD338: 0
K339: 1 | L339: 32-06LIQ-05001051 | M339: Campari | N339: Liqueur | O339: Campari | P339: CAM | Q339: Campari Negroni Liqueur | R339: 500ml | S339: 6 | T339: 0 | U339: 0 | V339: 0 | W339: 0 | X339: 0 | Y339: 0 | Z339: 0 | AA339: 0 | AB339: 0 | AC339: 0 | AD339: 0
K340: 1 | L340: 32-06LIQ-07501402 | M340: Campari | N340: Liqueur | O340: Campari | P340: CAM | Q340: Campari Bitter 750 ml | R340: 750ml | S340: 6 | T340: 0 | U340: 0 | V340: 0 | W340: 0 | X340: 0 | Y340: 0 | Z340: 0 | AA340: 0 | AB340: 0 | AC340: 0 | AD340: 0
K341: 1 | L341: 32-SPPAC-07509002 | M341: Campari | N341: Liqueur | O341: Campari | P341: CAM | Q341: Campari Negroni Set | R341: 2250ml | S341: 4 | T341: 0 | U341: 0 | V341: 0 | W341: 0 | X341: 0 | Y341: 0 | Z341: 0 | AA341: 0 | AB341: 0 | AC341: 0 | AD341: 0
K342: 1 | L342: 33-SPGIN-07502000 | M342: Campari | N342: Gin | O342: Bulldog | P342: BUL | Q342: Bulldog London Dry Gin 750 ml | R342: 750ml | S342: 6 | T342: 0 | U342: 0 | V342: 0 | W342: 0 | X342: 0 | Y342: 0 | Z342: 0 | AA342: 0 | AB342: 0 | AC342: 0 | AD342: 0
K343: 1 | L343: 33-SPPAC-07506102 | M343: Campari | N343: Gin | O343: Bulldog | P343: BUL | Q343: Bulldog Gin Glass Set | R343: 750ml | S343: 6 | T343: 0 | U343: 0 | V343: 0 | W343: 0 | X343: 0 | Y343: 0 | Z343: 0 | AA343: 0 | AB343: 0 | AC343: 0 | AD343: 0
K344: 1 | L344: 34-12VOD-01808261 | M344: Campari | N344: Vodka | O344: Skyy | P344: SKY | Q344: Skyy Vodka 180 ml (P12) | R344: 180ml | S344: 12 | T344: 0 | U344: 0 | V344: 0 | W344: 0 | X344: 0 | Y344: 0 | Z344: 0 | AA344: 0 | AB344: 0 | AC344: 0 | AD344: 0
K345: 1 | L345: 34-SPVOD-07007004 | M345: Campari | N345: Vodka | O345: Skyy | P345: SKY | Q345: Skyy Vodka | R345: 700ml | S345: 12 | T345: 0 | U345: 0 | V345: 0 | W345: 0 | X345: 0 | Y345: 0 | Z345: 0 | AA345: 0 | AB345: 0 | AC345: 0 | AD345: 0
K346: 1 | L346: 37-SPWHI-07002834 | M346: Campari | N346: Whisky | O346: Wild Turkey | P346: WTK | Q346: Wild Turkey Rye Whiskey 700ml | R346: 700ml | S346: 12 | T346: 0 | U346: 0 | V346: 0 | W346: 0 | X346: 0 | Y346: 0 | Z346: 0 | AA346: 0 | AB346: 0 | AC346: 0 | AD346: 0
K347: 1 | L347: 40-SPRUM-07501400 | M347: Campari | N347: Rum | O347: Appleton | P347: APT | Q347: Appleton Estate Rare Blend 12 Years | R347: 750ml | S347: 12 | T347: 0 | U347: 0 | V347: 0 | W347: 0 | X347: 0 | Y347: 0 | Z347: 0 | AA347: 0 | AB347: 0 | AC347: 0 | AD347: 0
K348: 1 | L348: 46-ABRGP-07000051 | M348: Campari | N348: Whisky | O348: Glen Grant | P348: GGT | Q348: Glen Grant Single Malt Scotch Whisky Arboralis (Gift Pack) | R348: 700ml | S348: 6 | T348: 0 | U348: 0 | V348: 0 | W348: 0 | X348: 0 | Y348: 0 | Z348: 0 | AA348: 0 | AB348: 0 | AC348: 0 | AD348: 0
K349: 1 | L349: 51-WISPA-07505015 | M349: Luc Belaire | N349: Sparkling Wine | O349: Luc Belaire | P349: LUC | Q349: Luc Belaire Rare Luxe | R349: 750ml | S349: 6 | T349: 0 | U349: 0 | V349: 0 | W349: 0 | X349: 0 | Y349: 0 | Z349: 0 | AA349: 0 | AB349: 0 | AC349: 0 | AD349: 0
... K364: 1 | L364: 64-SPLIQ-02001041 | M364: Laiba | N364: Liqueur | O364: Laiba | P364: LAI | Q364: Laiba Twisted Negroni | R364: 200ml | S364: 12 | T364: 0 | U364: 0 | V364: 0 | W364: 0 | X364: 0 | Y364: 0 | Z364: 0 | AA364: 0 | AB364: 0 | AC364: 0 | AD364: 0
K365: 2 | L365: {='02'!B13:T365} -> 04-SPWHI-07007491 | M365: TEG | N365: Single Malt Scotch | O365: The Macallan | P365: MAC | Q365: The Macallan Sherry Oak 12YO | R365: 700ml | S365: 12 | T365: 0 | U365: 0 | V365: 0 | W365: 0 | X365: 0 | Y365: 0 | Z365: 0 | AA365: 0 | AB365: 0 | AC365: 0 | AD365: 0
K366: 2 | L366: 04-SPWHI-07017065 | M366: TEG | N366: Single Malt Scotch | O366: The Macallan | P366: MAC | Q366: The Macallan Sherry Oak 18YO | R366: 700ml | S366: 6 | T366: 0 | U366: 0 | V366: 0 | W366: 0 | X366: 0 | Y366: 0 | Z366: 0 | AA366: 0 | AB366: 0 | AC366: 0 | AD366: 0
K367: 2 | L367: 04-SPWHI-07006031 | M367: TEG | N367: Single Malt Scotch | O367: The Macallan | P367: MAC | Q367: The Macallan Sherry Oak 25YO | R367: 700ml | S367: 3 | T367: 0 | U367: 0 | V367: 0 | W367: 0 | X367: 0 | Y367: 0 | Z367: 0 | AA367: 0 | AB367: 0 | AC367: 0 | AD367: 0
K368: 2 | L368: 04-SPWHI-07006048 | M368: TEG | N368: Single Malt Scotch | O368: The Macallan | P368: MAC | Q368: The Macallan Sherry Oak 30YO | R368: 700ml | S368: 3 | T368: 0 | U368: 0 | V368: 0 | W368: 0 | X368: 0 | Y368: 0 | Z368: 0 | AA368: 0 | AB368: 0 | AC368: 0 | AD368: 0
K369: 2 | L369: 04-SPWHI-07003009 | M369: TEG | N369: Single Malt Scotch | O369: The Macallan | P369: MAC | Q369: The Macallan Double Cask 12YO | R369: 700ml | S369: 12 | T369: 0 | U369: 0 | V369: 0 | W369: 0 | X369: 0 | Y369: 0 | Z369: 0 | AA369: 0 | AB369: 0 | AC369: 0 | AD369: 0
K370: 2 | L370: 04-SPWHI-07007700 | M370: TEG | N370: Single Malt Scotch | O370: The Macallan | P370: MAC | Q370: The Macallan Double Cask 15YO | R370: 700ml | S370: 6 | T370: 0 | U370: 0 | V370: 0 | W370: 0 | X370: 0 | Y370: 0 | Z370: 0 | AA370: 0 | AB370: 0 | AC370: 0 | AD370: 0
K371: 2 | L371: 04-SPWHI-07009254 | M371: TEG | N371: Single Malt Scotch | O371: The Macallan | P371: MAC | Q371: The Macallan Double Cask 18YO | R371: 700ml | S371: 6 | T371: 0 | U371: 0 | V371: 0 | W371: 0 | X371: 0 | Y371: 0 | Z371: 0 | AA371: 0 | AB371: 0 | AC371: 0 | AD371: 0
K372: 2 | L372: 04-SPWHI-07000311 | M372: TEG | N372: Single Malt Scotch | O372: The Macallan | P372: MAC | Q372: The Macallan Double Cask 30YO | R372: 700ml | S372: 3 | T372: 0 | U372: 0 | V372: 0 | W372: 0 | X372: 0 | Y372: 0 | Z372: 0 | AA372: 0 | AB372: 0 | AC372: 0 | AD372: 0
K373: 2 | L373: 04-SPWHI-07000796 | M373: TEG | N373: Single Malt Scotch | O373: The Macallan | P373: MAC | Q373: The Macallan Triple Cask 12YO | R373: 700ml | S373: 12 | T373: 0 | U373: 0 | V373: 0 | W373: 0 | X373: 0 | Y373: 0 | Z373: 0 | AA373: 0 | AB373: 0 | AC373: 0 | AD373: 0
K374: 2 | L374: 04-24HMN-07002650 | M374: TEG | N374: Single Malt Scotch | O374: The Macallan | P374: MAC | Q374: The Macallan Harmony Vibrant Oak | R374: 700ml | S374: 6 | T374: 0 | U374: 0 | V374: 0 | W374: 0 | X374: 0 | Y374: 0 | Z374: 0 | AA374: 0 | AB374: 0 | AC374: 0 | AD374: 0
K375: 2 | L375: 04-23WHI-07002322 | M375: TEG | N375: Single Malt Scotch | O375: The Macallan | P375: MAC | Q375: The Macallan Harmony Collection Amber Meadow | R375: 700ml | S375: 12 | T375: 0 | U375: 0 | V375: 0 | W375: 0 | X375: 0 | Y375: 0 | Z375: 0 | AA375: 0 | AB375: 0 | AC375: 0 | AD375: 0
K376: 2 | L376: 04-SPWHI-07000557 | M376: TEG | N376: Single Malt Scotch | O376: The Macallan | P376: MAC | Q376: The Macallan Harmony Collection | R376: 700ml | S376: 6 | T376: 0 | U376: 0 | V376: 0 | W376: 0 | X376: 0 | Y376: 0 | Z376: 0 | AA376: 0 | AB376: 0 | AC376: 0 | AD376: 0
K377: 2 | L377: 04-SPWHI-07001226 | M377: TEG | N377: Single Malt Scotch | O377: The Macallan | P377: MAC | Q377: The Macallan Harmony Collection Intense Arabica | R377: 700ml | S377: 6 | T377: 0 | U377: 0 | V377: 0 | W377: 0 | X377: 0 | Y377: 0 | Z377: 0 | AA377: 0 | AB377: 0 | AC377: 0 | AD377: 0
... K689: 2 | L689: 29-SPGIN-07006351 | M689: Remy Cointreau | N689: Gin | O689: Botanist | P689: BOT | Q689: The Botanist Islay Dry Gin (Gift Box) | R689: 700ml | S689: 4 | T689: 0 | U689: 0 | V689: 0 | W689: 0 | X689: 0 | Y689: 0 | Z689: 0 | AA689: 0 | AB689: 0 | AC689: 0 | AD689: 0
K690: 2 | L690: 31-SPMIX-1450PACK | M690: Campari | N690: Liqueur | O690: Aperol/Cinzano | Q690: Aperol + Cinzano Prosecco | R690: 1450ml | S690: 3 | T690: 0 | U690: 0 | V690: 0 | W690: 0 | X690: 0 | Y690: 0 | Z690: 0 | AA690: 0 | AB690: 0 | AC690: 0 | AD690: 0
K691: 2 | L691: 31-SPPAC-07000575 | M691: Campari | N691: Liqueur | O691: Aperol | P691: APR | Q691: Aperol Glass Set | R691: 700ml | S691: 5 | T691: 0 | U691: 0 | V691: 0 | W691: 0 | X691: 0 | Y691: 0 | Z691: 0 | AA691: 0 | AB691: 0 | AC691: 0 | AD691: 0
K692: 2 | L692: 32-06LIQ-05001051 | M692: Campari | N692: Liqueur | O692: Campari | P692: CAM | Q692: Campari Negroni Liqueur | R692: 500ml | S692: 6 | T692: 0 | U692: 0 | V692: 0 | W692: 0 | X692: 0 | Y692: 0 | Z692: 0 | AA692: 0 | AB692: 0 | AC692: 0 | AD692: 0
K693: 2 | L693: 32-06LIQ-07501402 | M693: Campari | N693: Liqueur | O693: Campari | P693: CAM | Q693: Campari Bitter 750 ml | R693: 750ml | S693: 6 | T693: 0 | U693: 0 | V693: 0 | W693: 0 | X693: 0 | Y693: 0 | Z693: 0 | AA693: 0 | AB693: 0 | AC693: 0 | AD693: 0
K694: 2 | L694: 32-SPPAC-07509002 | M694: Campari | N694: Liqueur | O694: Campari | P694: CAM | Q694: Campari Negroni Set | R694: 2250ml | S694: 4 | T694: 0 | U694: 0 | V694: 0 | W694: 0 | X694: 0 | Y694: 0 | Z694: 0 | AA694: 0 | AB694: 0 | AC694: 0 | AD694: 0
K695: 2 | L695: 33-SPGIN-07502000 | M695: Campari | N695: Gin | O695: Bulldog | P695: BUL | Q695: Bulldog London Dry Gin 750 ml | R695: 750ml | S695: 6 | T695: 0 | U695: 0 | V695: 0 | W695: 0 | X695: 0 | Y695: 0 | Z695: 0 | AA695: 0 | AB695: 0 | AC695: 0 | AD695: 0
K696: 2 | L696: 33-SPPAC-07506102 | M696: Campari | N696: Gin | O696: Bulldog | P696: BUL | Q696: Bulldog Gin Glass Set | R696: 750ml | S696: 6 | T696: 0 | U696: 0 | V696: 0 | W696: 0 | X696: 0 | Y696: 0 | Z696: 0 | AA696: 0 | AB696: 0 | AC696: 0 | AD696: 0
K697: 2 | L697: 34-12VOD-01808261 | M697: Campari | N697: Vodka | O697: Skyy | P697: SKY | Q697: Skyy Vodka 180 ml (P12) | R697: 180ml | S697: 12 | T697: 0 | U697: 0 | V697: 0 | W697: 0 | X697: 0 | Y697: 0 | Z697: 0 | AA697: 0 | AB697: 0 | AC697: 0 | AD697: 0
K698: 2 | L698: 34-SPVOD-07007004 | M698: Campari | N698: Vodka | O698: Skyy | P698: SKY | Q698: Skyy Vodka | R698: 700ml | S698: 12 | T698: 0 | U698: 0 | V698: 0 | W698: 0 | X698: 0 | Y698: 0 | Z698: 0 | AA698: 0 | AB698: 0 | AC698: 0 | AD698: 0
K699: 2 | L699: 37-SPWHI-07002834 | M699: Campari | N699: Whisky | O699: Wild Turkey | P699: WTK | Q699: Wild Turkey Rye Whiskey 700ml | R699: 700ml | S699: 12 | T699: 0 | U699: 0 | V699: 0 | W699: 0 | X699: 0 | Y699: 0 | Z699: 0 | AA699: 0 | AB699: 0 | AC699: 0 | AD699: 0
K700: 2 | L700: 40-SPRUM-07501400 | M700: Campari | N700: Rum | O700: Appleton | P700: APT | Q700: Appleton Estate Rare Blend 12 Years | R700: 750ml | S700: 12 | T700: 0 | U700: 0 | V700: 0 | W700: 0 | X700: 0 | Y700: 0 | Z700: 0 | AA700: 0 | AB700: 0 | AC700: 0 | AD700: 0
K701: 2 | L701: 46-ABRGP-07000051 | M701: Campari | N701: Whisky | O701: Glen Grant | P701: GGT | Q701: Glen Grant Single Malt Scotch Whisky Arboralis (Gift Pack) | R701: 700ml | S701: 6 | T701: 0 | U701: 0 | V701: 0 | W701: 0 | X701: 0 | Y701: 0 | Z701: 0 | AA701: 0 | AB701: 0 | AC701: 0 | AD701: 0
K702: 2 | L702: 51-WISPA-07505015 | M702: Luc Belaire | N702: Sparkling Wine | O702: Luc Belaire | P702: LUC | Q702: Luc Belaire Rare Luxe | R702: 750ml | S702: 6 | T702: 0 | U702: 0 | V702: 0 | W702: 0 | X702: 0 | Y702: 0 | Z702: 0 | AA702: 0 | AB702: 0 | AC702: 0 | AD702: 0
... K717: 2 | L717: 64-SPLIQ-02001041 | M717: Laiba | N717: Liqueur | O717: Laiba | P717: LAI | Q717: Laiba Twisted Negroni | R717: 200ml | S717: 12 | T717: 0 | U717: 0 | V717: 0 | W717: 0 | X717: 0 | Y717: 0 | Z717: 0 | AA717: 0 | AB717: 0 | AC717: 0 | AD717: 0
K718: 3 | L718: {='03'!B13:T365} -> 04-SPWHI-07007491 | M718: TEG | N718: Single Malt Scotch | O718: The Macallan | P718: MAC | Q718: The Macallan Sherry Oak 12YO | R718: 700ml | S718: 12 | T718: 0 | U718: 0 | V718: 0 | W718: 0 | X718: 0 | Y718: 0 | Z718: 0 | AA718: 0 | AB718: 0 | AC718: 0 | AD718: 0
K719: 3 | L719: 04-SPWHI-07017065 | M719: TEG | N719: Single Malt Scotch | O719: The Macallan | P719: MAC | Q719: The Macallan Sherry Oak 18YO | R719: 700ml | S719: 6 | T719: 0 | U719: 0 | V719: 0 | W719: 0 | X719: 0 | Y719: 0 | Z719: 0 | AA719: 0 | AB719: 0 | AC719: 0 | AD719: 0
K720: 3 | L720: 04-SPWHI-07006031 | M720: TEG | N720: Single Malt Scotch | O720: The Macallan | P720: MAC | Q720: The Macallan Sherry Oak 25YO | R720: 700ml | S720: 3 | T720: 0 | U720: 0 | V720: 0 | W720: 0 | X720: 0 | Y720: 0 | Z720: 0 | AA720: 0 | AB720: 0 | AC720: 0 | AD720: 0
K721: 3 | L721: 04-SPWHI-07006048 | M721: TEG | N721: Single Malt Scotch | O721: The Macallan | P721: MAC | Q721: The Macallan Sherry Oak 30YO | R721: 700ml | S721: 3 | T721: 0 | U721: 0 | V721: 0 | W721: 0 | X721: 0 | Y721: 0 | Z721: 0 | AA721: 0 | AB721: 0 | AC721: 0 | AD721: 0
K722: 3 | L722: 04-SPWHI-07003009 | M722: TEG | N722: Single Malt Scotch | O722: The Macallan | P722: MAC | Q722: The Macallan Double Cask 12YO | R722: 700ml | S722: 12 | T722: 0 | U722: 0 | V722: 0 | W722: 0 | X722: 0 | Y722: 0 | Z722: 0 | AA722: 0 | AB722: 0 | AC722: 0 | AD722: 0
K723: 3 | L723: 04-SPWHI-07007700 | M723: TEG | N723: Single Malt Scotch | O723: The Macallan | P723: MAC | Q723: The Macallan Double Cask 15YO | R723: 700ml | S723: 6 | T723: 0 | U723: 0 | V723: 0 | W723: 0 | X723: 0 | Y723: 0 | Z723: 0 | AA723: 0 | AB723: 0 | AC723: 0 | AD723: 0
K724: 3 | L724: 04-SPWHI-07009254 | M724: TEG | N724: Single Malt Scotch | O724: The Macallan | P724: MAC | Q724: The Macallan Double Cask 18YO | R724: 700ml | S724: 6 | T724: 0 | U724: 0 | V724: 0 | W724: 0 | X724: 0 | Y724: 0 | Z724: 0 | AA724: 0 | AB724: 0 | AC724: 0 | AD724: 0
K725: 3 | L725: 04-SPWHI-07000311 | M725: TEG | N725: Single Malt Scotch | O725: The Macallan | P725: MAC | Q725: The Macallan Double Cask 30YO | R725: 700ml | S725: 3 | T725: 0 | U725: 0 | V725: 0 | W725: 0 | X725: 0 | Y725: 0 | Z725: 0 | AA725: 0 | AB725: 0 | AC725: 0 | AD725: 0
K726: 3 | L726: 04-SPWHI-07000796 | M726: TEG | N726: Single Malt Scotch | O726: The Macallan | P726: MAC | Q726: The Macallan Triple Cask 12YO | R726: 700ml | S726: 12 | T726: 0 | U726: 0 | V726: 0 | W726: 0 | X726: 0 | Y726: 0 | Z726: 0 | AA726: 0 | AB726: 0 | AC726: 0 | AD726: 0
K727: 3 | L727: 04-24HMN-07002650 | M727: TEG | N727: Single Malt Scotch | O727: The Macallan | P727: MAC | Q727: The Macallan Harmony Vibrant Oak | R727: 700ml | S727: 6 | T727: 0 | U727: 0 | V727: 0 | W727: 0 | X727: 0 | Y727: 0 | Z727: 0 | AA727: 0 | AB727: 0 | AC727: 0 | AD727: 0
K728: 3 | L728: 04-23WHI-07002322 | M728: TEG | N728: Single Malt Scotch | O728: The Macallan | P728: MAC | Q728: The Macallan Harmony Collection Amber Meadow | R728: 700ml | S728: 12 | T728: 0 | U728: 0 | V728: 0 | W728: 0 | X728: 0 | Y728: 0 | Z728: 0 | AA728: 0 | AB728: 0 | AC728: 0 | AD728: 0
K729: 3 | L729: 04-SPWHI-07000557 | M729: TEG | N729: Single Malt Scotch | O729: The Macallan | P729: MAC | Q729: The Macallan Harmony Collection | R729: 700ml | S729: 6 | T729: 0 | U729: 0 | V729: 0 | W729: 0 | X729: 0 | Y729: 0 | Z729: 0 | AA729: 0 | AB729: 0 | AC729: 0 | AD729: 0
K730: 3 | L730: 04-SPWHI-07001226 | M730: TEG | N730: Single Malt Scotch | O730: The Macallan | P730: MAC | Q730: The Macallan Harmony Collection Intense Arabica | R730: 700ml | S730: 6 | T730: 0 | U730: 0 | V730: 0 | W730: 0 | X730: 0 | Y730: 0 | Z730: 0 | AA730: 0 | AB730: 0 | AC730: 0 | AD730: 0
... K1042: 3 | L1042: 29-SPGIN-07006351 | M1042: Remy Cointreau | N1042: Gin | O1042: Botanist | P1042: BOT | Q1042: The Botanist Islay Dry Gin (Gift Box) | R1042: 700ml | S1042: 4 | T1042: 0 | U1042: 0 | V1042: 0 | W1042: 0 | X1042: 0 | Y1042: 0 | Z1042: 0 | AA1042: 0 | AB1042: 0 | AC1042: 0 | AD1042: 0
K1043: 3 | L1043: 31-SPMIX-1450PACK | M1043: Campari | N1043: Liqueur | O1043: Aperol/Cinzano | Q1043: Aperol + Cinzano Prosecco | R1043: 1450ml | S1043: 3 | T1043: 0 | U1043: 0 | V1043: 0 | W1043: 0 | X1043: 0 | Y1043: 0 | Z1043: 0 | AA1043: 0 | AB1043: 0 | AC1043: 0 | AD1043: 0
K1044: 3 | L1044: 31-SPPAC-07000575 | M1044: Campari | N1044: Liqueur | O1044: Aperol | P1044: APR | Q1044: Aperol Glass Set | R1044: 700ml | S1044: 5 | T1044: 0 | U1044: 0 | V1044: 0 | W1044: 0 | X1044: 0 | Y1044: 0 | Z1044: 0 | AA1044: 0 | AB1044: 0 | AC1044: 0 | AD1044: 0
K1045: 3 | L1045: 32-06LIQ-05001051 | M1045: Campari | N1045: Liqueur | O1045: Campari | P1045: CAM | Q1045: Campari Negroni Liqueur | R1045: 500ml | S1045: 6 | T1045: 0 | U1045: 0 | V1045: 0 | W1045: 0 | X1045: 0 | Y1045: 0 | Z1045: 0 | AA1045: 0 | AB1045: 0 | AC1045: 0 | AD1045: 0
K1046: 3 | L1046: 32-06LIQ-07501402 | M1046: Campari | N1046: Liqueur | O1046: Campari | P1046: CAM | Q1046: Campari Bitter 750 ml | R1046: 750ml | S1046: 6 | T1046: 0 | U1046: 0 | V1046: 0 | W1046: 0 | X1046: 0 | Y1046: 0 | Z1046: 0 | AA1046: 0 | AB1046: 0 | AC1046: 0 | AD1046: 0
K1047: 3 | L1047: 32-SPPAC-07509002 | M1047: Campari | N1047: Liqueur | O1047: Campari | P1047: CAM | Q1047: Campari Negroni Set | R1047: 2250ml | S1047: 4 | T1047: 0 | U1047: 0 | V1047: 0 | W1047: 0 | X1047: 0 | Y1047: 0 | Z1047: 0 | AA1047: 0 | AB1047: 0 | AC1047: 0 | AD1047: 0
K1048: 3 | L1048: 33-SPGIN-07502000 | M1048: Campari | N1048: Gin | O1048: Bulldog | P1048: BUL | Q1048: Bulldog London Dry Gin 750 ml | R1048: 750ml | S1048: 6 | T1048: 0 | U1048: 0 | V1048: 0 | W1048: 0 | X1048: 0 | Y1048: 0 | Z1048: 0 | AA1048: 0 | AB1048: 0 | AC1048: 0 | AD1048: 0
K1049: 3 | L1049: 33-SPPAC-07506102 | M1049: Campari | N1049: Gin | O1049: Bulldog | P1049: BUL | Q1049: Bulldog Gin Glass Set | R1049: 750ml | S1049: 6 | T1049: 0 | U1049: 0 | V1049: 0 | W1049: 0 | X1049: 0 | Y1049: 0 | Z1049: 0 | AA1049: 0 | AB1049: 0 | AC1049: 0 | AD1049: 0
K1050: 3 | L1050: 34-12VOD-01808261 | M1050: Campari | N1050: Vodka | O1050: Skyy | P1050: SKY | Q1050: Skyy Vodka 180 ml (P12) | R1050: 180ml | S1050: 12 | T1050: 0 | U1050: 0 | V1050: 0 | W1050: 0 | X1050: 0 | Y1050: 0 | Z1050: 0 | AA1050: 0 | AB1050: 0 | AC1050: 0 | AD1050: 0
K1051: 3 | L1051: 34-SPVOD-07007004 | M1051: Campari | N1051: Vodka | O1051: Skyy | P1051: SKY | Q1051: Skyy Vodka | R1051: 700ml | S1051: 12 | T1051: 0 | U1051: 0 | V1051: 0 | W1051: 0 | X1051: 0 | Y1051: 0 | Z1051: 0 | AA1051: 0 | AB1051: 0 | AC1051: 0 | AD1051: 0
K1052: 3 | L1052: 37-SPWHI-07002834 | M1052: Campari | N1052: Whisky | O1052: Wild Turkey | P1052: WTK | Q1052: Wild Turkey Rye Whiskey 700ml | R1052: 700ml | S1052: 12 | T1052: 0 | U1052: 0 | V1052: 0 | W1052: 0 | X1052: 0 | Y1052: 0 | Z1052: 0 | AA1052: 0 | AB1052: 0 | AC1052: 0 | AD1052: 0
K1053: 3 | L1053: 40-SPRUM-07501400 | M1053: Campari | N1053: Rum | O1053: Appleton | P1053: APT | Q1053: Appleton Estate Rare Blend 12 Years | R1053: 750ml | S1053: 12 | T1053: 0 | U1053: 0 | V1053: 0 | W1053: 0 | X1053: 0 | Y1053: 0 | Z1053: 0 | AA1053: 0 | AB1053: 0 | AC1053: 0 | AD1053: 0
...

Sheet SUMMARY
B1: Outlet Rebate Calculation Form
B2: Outlet Name: | C2: =IF(INDEX!C3="","",INDEX!C3) -> Outlet Name | E2: Area: | F2: =IF(INDEX!C9="","",INDEX!C9) -> Area | J2: ='CASH REBATE'!$P$22 -> FALSE | K2: ='CASH REBATE'!$P$24 -> FALSE | L2: ='CASH REBATE'!$P$26 -> FALSE | M2: ='CASH REBATE'!$P$28 -> FALSE | N2: ='CASH REBATE'!$P$30 -> FALSE | O2: ='CASH REBATE'!$P$32 -> FALSE | P2: ='CASH REBATE'!$Q$22 -> FALSE | Q2: ='CASH REBATE'!$Q$24 -> FALSE | R2: ='CASH REBATE'!$Q$26 -> FALSE | S2: ='CASH REBATE'!$Q$28 -> FALSE | T2: ='CASH REBATE'!$Q$30 -> FALSE | U2: ='CASH REBATE'!$Q$32 -> FALSE | V2: ACTUAL VOL BTLS | Y2: ='CASH REBATE'!$P$22 -> FALSE | Z2: ='CASH REBATE'!$P$24 -> FALSE | AA2: ='CASH REBATE'!$P$26 -> FALSE | AB2: ='CASH REBATE'!$P$28 -> FALSE | AC2: ='CASH REBATE'!$P$30 -> FALSE | AD2: ='CASH REBATE'!$P$32 -> FALSE | AE2: ='CASH REBATE'!$Q$22 -> FALSE | AF2: ='CASH REBATE'!$Q$24 -> FALSE | AG2: ='CASH REBATE'!$Q$26 -> FALSE | AH2: ='CASH REBATE'!$Q$28 -> FALSE | AI2: ='CASH REBATE'!$Q$30 -> FALSE | AJ2: ='CASH REBATE'!$Q$32 -> FALSE | AK2: ACTUAL VALUE IN VAT | AN2: ='CASH REBATE'!$P$22 -> FALSE | AO2: ='CASH REBATE'!$P$24 -> FALSE | AP2: ='CASH REBATE'!$P$26 -> FALSE | AQ2: ='CASH REBATE'!$P$28 -> FALSE | AR2: ='CASH REBATE'!$P$30 -> FALSE | AS2: ='CASH REBATE'!$P$32 -> FALSE | AT2: ='CASH REBATE'!$Q$22 -> FALSE | AU2: ='CASH REBATE'!$Q$24 -> FALSE | AV2: ='CASH REBATE'!$Q$26 -> FALSE | AW2: ='CASH REBATE'!$Q$28 -> FALSE | AX2: ='CASH REBATE'!$Q$30 -> FALSE | AY2: ='CASH REBATE'!$Q$32 -> FALSE | AZ2: ACTUAL VALUE EX VAT | BC2: ='CASH REBATE'!$P$22 -> FALSE | BD2: ='CASH REBATE'!$P$24 -> FALSE | BE2: ='CASH REBATE'!$P$26 -> FALSE | BF2: ='CASH REBATE'!$P$28 -> FALSE | BG2: ='CASH REBATE'!$P$30 -> FALSE | BH2: ='CASH REBATE'!$P$32 -> FALSE | BI2: ='CASH REBATE'!$Q$22 -> FALSE | BJ2: ='CASH REBATE'!$Q$24 -> FALSE | BK2: ='CASH REBATE'!$Q$26 -> FALSE | BL2: ='CASH REBATE'!$Q$28 -> FALSE | BM2: ='CASH REBATE'!$Q$30 -> FALSE | BN2: ='CASH REBATE'!$Q$32 -> FALSE | BO2: ACTUAL REBATE VALUE
BQ3: f
B4: Legal Name: | C4: =IF(INDEX!C5="","",INDEX!C5) -> Outlet Company Limited | E4: Agent: | F4: =IF(INDEX!C11="","",INDEX!C11) -> Agent name | I4: ALL PRINCIPLE | J4: =SUM(J12:J394) -> 0 | K4: =SUM(K12:K394) -> 0 | L4: =SUM(L12:L394) -> 0 | M4: =SUM(M12:M394) -> 0 | N4: =SUM(N12:N394) -> 0 | O4: =SUM(O12:O394) -> 10 | P4: =SUM(P12:P394) -> 0 | Q4: =SUM(Q12:Q394) -> 0 | ... W4: =SUM(W12:W394) -> 0 | Y4: =SUM(Y12:Y394) -> 0 | Z4: =SUM(Z12:Z394) -> 0 | AA4: =SUM(AA12:AA394) -> 0 | AB4: =SUM(AB12:AB394) -> 0 | AC4: =SUM(AC12:AC394) -> 0 | AD4: =SUM(AD12:AD394) -> 10700 | AE4: =SUM(AE12:AE394) -> 0 | AF4: =SUM(AF12:AF394) -> 0 | ... AL4: =SUM(AL12:AL394) -> 0 | AN4: =SUM(AN12:AN394) -> 0 | AO4: =SUM(AO12:AO394) -> 0 | AP4: =SUM(AP12:AP394) -> 0 | AQ4: =SUM(AQ12:AQ394) -> 0 | AR4: =SUM(AR12:AR394) -> 0 | AS4: =SUM(AS12:AS394) -> 10000 | AT4: =SUM(AT12:AT394) -> 0 | AU4: =SUM(AU12:AU394) -> 0 | ... BA4: =SUM(BA12:BA394) -> 0 | BC4: =SUM(BC12:BC394) -> 0 | BD4: =SUM(BD12:BD394) -> 0 | BE4: =SUM(BE12:BE394) -> 0 | BF4: =SUM(BF12:BF394) -> 0 | BG4: =SUM(BG12:BG394) -> 0 | BH4: =SUM(BH12:BH394) -> 0 | BI4: =SUM(BI12:BI394) -> 0 | BJ4: =SUM(BJ12:BJ394) -> 0 | ... BO4: =SUM(BO12:BO394) -> 0 | BP4: =SUMIFS($BC4:$BN4,$BC$2:$BN$2,"TRUE") -> 0
B6: BDE: | C6: =IF(INDEX!C7="","",INDEX!C7) -> Name of BDE | E6: Supervisor: | F6: =IF(INDEX!C13="","",INDEX!C13) -> Manager Name | I6: Campari | J6: =SUMIFS(J$12:J$394,$C$12:$C$394,$I$6) -> 0 | K6: =SUMIFS(K$12:K$394,$C$12:$C$394,$I$6) -> 0 | L6: =SUMIFS(L$12:L$394,$C$12:$C$394,$I$6) -> 0 | M6: =SUMIFS(M$12:M$394,$C$12:$C$394,$I$6) -> 0 | N6: =SUMIFS(N$12:N$394,$C$12:$C$394,$I$6) -> 0 | O6: =SUMIFS(O$12:O$394,$C$12:$C$394,$I$6) -> 0 | P6: =SUMIFS(P$12:P$394,$C$12:$C$394,$I$6) -> 0 | Q6: =SUMIFS(Q$12:Q$394,$C$12:$C$394,$I$6) -> 0 | ... U6: =SUMIFS(U$12:U$394,$C$12:$C$394,$I$6) -> 0 | V6: =SUMIFS(V$12:V$394,$C$12:$C$394,$I$8) -> 0 | W6: =SUMIFS(W$12:W$394,$C$12:$C$394,$I$8) -> 0 | Y6: =SUMIFS(Y$12:Y$349,$C$12:$C$349,$I$6) -> 0 | Z6: =SUMIFS(Z$12:Z$349,$C$12:$C$349,$I$6) -> 0 | AA6: =SUMIFS(AA$12:AA$349,$C$12:$C$349,$I$6) -> 0 | AB6: =SUMIFS(AB$12:AB$349,$C$12:$C$349,$I$6) -> 0 | AC6: =SUMIFS(AC$12:AC$349,$C$12:$C$349,$I$6) -> 0 | AD6: =SUMIFS(AD$12:AD$349,$C$12:$C$349,$I$6) -> 0 | AE6: =SUMIFS(AE$12:AE$349,$C$12:$C$349,$I$6) -> 0 | AF6: =SUMIFS(AF$12:AF$349,$C$12:$C$349,$I$6) -> 0 | ... AL6: =SUMIFS(AL$12:AL$349,$C$12:$C$349,$I$6) -> 0 | AN6: =SUMIFS(AN$12:AN$349,$C$12:$C$349,$I$6) -> 0 | AO6: =SUMIFS(AO$12:AO$349,$C$12:$C$349,$I$6) -> 0 | AP6: =SUMIFS(AP$12:AP$349,$C$12:$C$349,$I$6) -> 0 | AQ6: =SUMIFS(AQ$12:AQ$349,$C$12:$C$349,$I$6) -> 0 | AR6: =SUMIFS(AR$12:AR$349,$C$12:$C$349,$I$6) -> 0 | AS6: =SUMIFS(AS$12:AS$349,$C$12:$C$349,$I$6) -> 0 | AT6: =SUMIFS(AT$12:AT$349,$C$12:$C$349,$I$6) -> 0 | AU6: =SUMIFS(AU$12:AU$349,$C$12:$C$349,$I$6) -> 0 | ... BA6: =SUMIFS(BA$12:BA$349,$C$12:$C$349,$I$6) -> 0 | BC6: =SUMIFS(BC$12:BC$394,$C$12:$C$394,$I$8) -> 0 | BD6: =SUMIFS(BD$12:BD$394,$C$12:$C$394,$I$8) -> 0 | BE6: =SUMIFS(BE$12:BE$394,$C$12:$C$394,$I$8) -> 0 | BF6: =SUMIFS(BF$12:BF$394,$C$12:$C$394,$I$8) -> 0 | BG6: =SUMIFS(BG$12:BG$394,$C$12:$C$394,$I$8) -> 0 | BH6: =SUMIFS(BH$12:BH$394,$C$12:$C$394,$I$8) -> 0 | BI6: =SUMIFS(BI$12:BI$394,$C$12:$C$394,$I$8) -> 0 | BJ6: =SUMIFS(BJ$12:BJ$394,$C$12:$C$394,$I$8) -> 0 | ... BO6: =SUMIFS(BO$12:BO$394,$C$12:$C$394,$I$8) -> 0 | BP6: =SUMIFS($BC6:$BN6,$BC$2:$BN$2,"TRUE") -> 0
J10: =SUBTOTAL(9,J13:J354) -> 0 | K10: =SUBTOTAL(9,K13:K354) -> 0 | L10: =SUBTOTAL(9,L13:L354) -> 0 | M10: =SUBTOTAL(9,M13:M354) -> 0 | N10: =SUBTOTAL(9,N13:N354) -> 0 | O10: =SUBTOTAL(9,O13:O354) -> 10 | P10: =SUBTOTAL(9,P13:P354) -> 0 | Q10: =SUBTOTAL(9,Q13:Q354) -> 0 | ... BP10: =SUBTOTAL(9,BP13:BP354) -> 0
B11: Principle | C11: Principle | D11: Category | E11: Brand | F11: Brand Code | G11: Product | H11: Size | I11: Packing | J11: Volume (Bts) | W11: Selected MTH | Y11: Price IN. VAT | AL11: Selected MTH | AN11: Price EX. VAT | BA11: Selected MTH | BC11: Rebate | BP11: Selected MTH
J12: JAN | K12: FEB | L12: MAR | M12: APR | N12: MAY | O12: JUN | P12: JUL | Q12: AUG | R12: SEP | S12: OCT | T12: NOV | U12: DEC | V12: VOL (Bts) | W12: VOL (bts) | X12: x | Y12: JAN | Z12: FEB | AA12: MAR | AB12: APR | AC12: MAY | AD12: JUN | AE12: JUL | AF12: AUG | AG12: SEP | AH12: OCT | AI12: NOV | AJ12: DEC | AK12: Price in VAT | AL12: Price in VAT | AM12: x | AN12: JAN | AO12: FEB | AP12: MAR | AQ12: APR | AR12: MAY | AS12: JUN | AT12: JUL | AU12: AUG | AV12: SEP | AW12: OCT | AX12: NOV | AY12: DEC | AZ12: Price ex VAT | BA12: Price ex VAT | BB12: x | BC12: JAN | BD12: FEB | BE12: MAR | BF12: APR | BG12: MAY | BH12: JUN | BI12: JUL | BJ12: AUG | BK12: SEP | BL12: OCT | BM12: NOV | BN12: DEC | BO12: REBATE | BP12: Amount
B13: {=MAPPING!$B$3:$I$296} -> 04-SPWHI-07007491 | C13: TEG | D13: Single Malt Scotch | E13: The Macallan | F13: MAC | G13: The Macallan Sherry Oak 12YO | H13: 700ml | I13: 12 | J13: ='01'!N13 -> 0 | K13: ='02'!N13 -> 0 | L13: ='03'!N13 -> 0 | M13: ='04'!N13 -> 0 | N13: ='05'!N13 -> 0 | O13: ='06'!N13 -> 0 | P13: ='07'!N13 -> 0 | Q13: ='08'!N13 -> 0 | R13: ='09'!N13 -> 0 | S13: ='10'!N13 -> 0 | T13: ='11'!N13 -> 0 | U13: ='12'!N13 -> 0 | V13: =SUM(J13:U13) -> 0 | W13: =SUMIFS($J13:$U13,$J$2:$U$2,"TRUE") -> 0 | Y13: ='01'!R13 -> 0 | Z13: ='02'!R13 -> 0 | AA13: ='03'!R13 -> 0 | AB13: ='04'!R13 -> 0 | AC13: ='05'!R13 -> 0 | AD13: ='06'!R13 -> 0 | AE13: ='07'!R13 -> 0 | AF13: ='08'!R13 -> 0 | AG13: ='09'!R13 -> 0 | AH13: ='10'!R13 -> 0 | AI13: ='11'!R13 -> 0 | AJ13: ='12'!R13 -> 0 | AK13: =SUM(Y13:AJ13) -> 0 | AL13: =SUMIFS($Y13:$AJ13,$Y$2:$AJ$2,"TRUE") -> 0 | AN13: ='01'!S13 -> 0 | AO13: ='02'!S13 -> 0 | AP13: ='03'!S13 -> 0 | AQ13: ='04'!S13 -> 0 | AR13: ='05'!S13 -> 0 | AS13: ='06'!S13 -> 0 | AT13: ='07'!S13 -> 0 | AU13: ='08'!S13 -> 0 | AV13: ='09'!S13 -> 0 | AW13: ='10'!S13 -> 0 | AX13: ='11'!S13 -> 0 | AY13: ='12'!S13 -> 0 | AZ13: =SUM(AN13:AY13) -> 0 | BA13: =SUMIFS($AN13:$AY13,$AN$2:$AY$2,"TRUE") -> 0 | BC13: ='01'!T13 -> 0 | BD13: ='02'!T13 -> 0 | BE13: ='03'!T13 -> 0 | BF13: ='04'!T13 -> 0 | BG13: ='05'!T13 -> 0 | BH13: ='06'!T13 -> 0 | BI13: ='07'!T13 -> 0 | BJ13: ='08'!T13 -> 0 | BK13: ='09'!T13 -> 0 | BL13: ='10'!T13 -> 0 | BM13: ='11'!T13 -> 0 | BN13: ='12'!T13 -> 0 | BO13: =SUM(BC13:BN13) -> 0 | BP13: =SUMIFS($BC13:$BN13,$BC$2:$BN$2,"TRUE") -> 0
B14: 04-SPWHI-07017065 | C14: TEG | D14: Single Malt Scotch | E14: The Macallan | F14: MAC | G14: The Macallan Sherry Oak 18YO | H14: 700ml | I14: 6 | J14: ='01'!N14 -> 0 | K14: ='02'!N14 -> 0 | L14: ='03'!N14 -> 0 | M14: ='04'!N14 -> 0 | N14: ='05'!N14 -> 0 | O14: ='06'!N14 -> 0 | P14: ='07'!N14 -> 0 | Q14: ='08'!N14 -> 0 | R14: ='09'!N14 -> 0 | S14: ='10'!N14 -> 0 | T14: ='11'!N14 -> 0 | U14: ='12'!N14 -> 0 | V14: =SUM(J14:U14) -> 0 | W14: =SUMIFS($J14:$U14,$J$2:$U$2,"TRUE") -> 0 | Y14: ='01'!R14 -> 0 | Z14: ='02'!R14 -> 0 | AA14: ='03'!R14 -> 0 | AB14: ='04'!R14 -> 0 | AC14: ='05'!R14 -> 0 | AD14: ='06'!R14 -> 0 | AE14: ='07'!R14 -> 0 | AF14: ='08'!R14 -> 0 | AG14: ='09'!R14 -> 0 | AH14: ='10'!R14 -> 0 | AI14: ='11'!R14 -> 0 | AJ14: ='12'!R14 -> 0 | AK14: =SUM(Y14:AJ14) -> 0 | AL14: =SUMIFS($Y14:$AJ14,$Y$2:$AJ$2,"TRUE") -> 0 | AN14: ='01'!S14 -> 0 | AO14: ='02'!S14 -> 0 | AP14: ='03'!S14 -> 0 | AQ14: ='04'!S14 -> 0 | AR14: ='05'!S14 -> 0 | AS14: ='06'!S14 -> 0 | AT14: ='07'!S14 -> 0 | AU14: ='08'!S14 -> 0 | AV14: ='09'!S14 -> 0 | AW14: ='10'!S14 -> 0 | AX14: ='11'!S14 -> 0 | AY14: ='12'!S14 -> 0 | AZ14: =SUM(AN14:AY14) -> 0 | BA14: =SUMIFS($AN14:$AY14,$AN$2:$AY$2,"TRUE") -> 0 | BC14: ='01'!T14 -> 0 | BD14: ='02'!T14 -> 0 | BE14: ='03'!T14 -> 0 | BF14: ='04'!T14 -> 0 | BG14: ='05'!T14 -> 0 | BH14: ='06'!T14 -> 0 | BI14: ='07'!T14 -> 0 | BJ14: ='08'!T14 -> 0 | BK14: ='09'!T14 -> 0 | BL14: ='10'!T14 -> 0 | BM14: ='11'!T14 -> 0 | BN14: ='12'!T14 -> 0 | BO14: =SUM(BC14:BN14) -> 0 | BP14: =SUMIFS($BC14:$BN14,$BC$2:$BN$2,"TRUE") -> 0
B15: 04-SPWHI-07006031 | C15: TEG | D15: Single Malt Scotch | E15: The Macallan | F15: MAC | G15: The Macallan Sherry Oak 25YO | H15: 700ml | I15: 3 | J15: ='01'!N15 -> 0 | K15: ='02'!N15 -> 0 | L15: ='03'!N15 -> 0 | M15: ='04'!N15 -> 0 | N15: ='05'!N15 -> 0 | O15: ='06'!N15 -> 10 | P15: ='07'!N15 -> 0 | Q15: ='08'!N15 -> 0 | R15: ='09'!N15 -> 0 | S15: ='10'!N15 -> 0 | T15: ='11'!N15 -> 0 | U15: ='12'!N15 -> 0 | V15: =SUM(J15:U15) -> 10 | W15: =SUMIFS($J15:$U15,$J$2:$U$2,"TRUE") -> 0 | Y15: ='01'!R15 -> 0 | Z15: ='02'!R15 -> 0 | AA15: ='03'!R15 -> 0 | AB15: ='04'!R15 -> 0 | AC15: ='05'!R15 -> 0 | AD15: ='06'!R15 -> 10700 | AE15: ='07'!R15 -> 0 | AF15: ='08'!R15 -> 0 | AG15: ='09'!R15 -> 0 | AH15: ='10'!R15 -> 0 | AI15: ='11'!R15 -> 0 | AJ15: ='12'!R15 -> 0 | AK15: =SUM(Y15:AJ15) -> 10700 | AL15: =SUMIFS($Y15:$AJ15,$Y$2:$AJ$2,"TRUE") -> 0 | AN15: ='01'!S15 -> 0 | AO15: ='02'!S15 -> 0 | AP15: ='03'!S15 -> 0 | AQ15: ='04'!S15 -> 0 | AR15: ='05'!S15 -> 0 | AS15: ='06'!S15 -> 10000 | AT15: ='07'!S15 -> 0 | AU15: ='08'!S15 -> 0 | AV15: ='09'!S15 -> 0 | AW15: ='10'!S15 -> 0 | AX15: ='11'!S15 -> 0 | AY15: ='12'!S15 -> 0 | AZ15: =SUM(AN15:AY15) -> 10000 | BA15: =SUMIFS($AN15:$AY15,$AN$2:$AY$2,"TRUE") -> 0 | BC15: ='01'!T15 -> 0 | BD15: ='02'!T15 -> 0 | BE15: ='03'!T15 -> 0 | BF15: ='04'!T15 -> 0 | BG15: ='05'!T15 -> 0 | BH15: ='06'!T15 -> 0 | BI15: ='07'!T15 -> 0 | BJ15: ='08'!T15 -> 0 | BK15: ='09'!T15 -> 0 | BL15: ='10'!T15 -> 0 | BM15: ='11'!T15 -> 0 | BN15: ='12'!T15 -> 0 | BO15: =SUM(BC15:BN15) -> 0 | BP15: =SUMIFS($BC15:$BN15,$BC$2:$BN$2,"TRUE") -> 0
B16: 04-SPWHI-07006048 | C16: TEG | D16: Single Malt Scotch | E16: The Macallan | F16: MAC | G16: The Macallan Sherry Oak 30YO | H16: 700ml | I16: 3 | J16: ='01'!N16 -> 0 | K16: ='02'!N16 -> 0 | L16: ='03'!N16 -> 0 | M16: ='04'!N16 -> 0 | N16: ='05'!N16 -> 0 | O16: ='06'!N16 -> 0 | P16: ='07'!N16 -> 0 | Q16: ='08'!N16 -> 0 | R16: ='09'!N16 -> 0 | S16: ='10'!N16 -> 0 | T16: ='11'!N16 -> 0 | U16: ='12'!N16 -> 0 | V16: =SUM(J16:U16) -> 0 | W16: =SUMIFS($J16:$U16,$J$2:$U$2,"TRUE") -> 0 | Y16: ='01'!R16 -> 0 | Z16: ='02'!R16 -> 0 | AA16: ='03'!R16 -> 0 | AB16: ='04'!R16 -> 0 | AC16: ='05'!R16 -> 0 | AD16: ='06'!R16 -> 0 | AE16: ='07'!R16 -> 0 | AF16: ='08'!R16 -> 0 | AG16: ='09'!R16 -> 0 | AH16: ='10'!R16 -> 0 | AI16: ='11'!R16 -> 0 | AJ16: ='12'!R16 -> 0 | AK16: =SUM(Y16:AJ16) -> 0 | AL16: =SUMIFS($Y16:$AJ16,$Y$2:$AJ$2,"TRUE") -> 0 | AN16: ='01'!S16 -> 0 | AO16: ='02'!S16 -> 0 | AP16: ='03'!S16 -> 0 | AQ16: ='04'!S16 -> 0 | AR16: ='05'!S16 -> 0 | AS16: ='06'!S16 -> 0 | AT16: ='07'!S16 -> 0 | AU16: ='08'!S16 -> 0 | AV16: ='09'!S16 -> 0 | AW16: ='10'!S16 -> 0 | AX16: ='11'!S16 -> 0 | AY16: ='12'!S16 -> 0 | AZ16: =SUM(AN16:AY16) -> 0 | BA16: =SUMIFS($AN16:$AY16,$AN$2:$AY$2,"TRUE") -> 0 | BC16: ='01'!T16 -> 0 | BD16: ='02'!T16 -> 0 | BE16: ='03'!T16 -> 0 | BF16: ='04'!T16 -> 0 | BG16: ='05'!T16 -> 0 | BH16: ='06'!T16 -> 0 | BI16: ='07'!T16 -> 0 | BJ16: ='08'!T16 -> 0 | BK16: ='09'!T16 -> 0 | BL16: ='10'!T16 -> 0 | BM16: ='11'!T16 -> 0 | BN16: ='12'!T16 -> 0 | BO16: =SUM(BC16:BN16) -> 0 | BP16: =SUMIFS($BC16:$BN16,$BC$2:$BN$2,"TRUE") -> 0
B17: 04-SPWHI-07003009 | C17: TEG | D17: Single Malt Scotch | E17: The Macallan | F17: MAC | G17: The Macallan Double Cask 12YO | H17: 700ml | I17: 12 | J17: ='01'!N17 -> 0 | K17: ='02'!N17 -> 0 | L17: ='03'!N17 -> 0 | M17: ='04'!N17 -> 0 | N17: ='05'!N17 -> 0 | O17: ='06'!N17 -> 0 | P17: ='07'!N17 -> 0 | Q17: ='08'!N17 -> 0 | R17: ='09'!N17 -> 0 | S17: ='10'!N17 -> 0 | T17: ='11'!N17 -> 0 | U17: ='12'!N17 -> 0 | V17: =SUM(J17:U17) -> 0 | W17: =SUMIFS($J17:$U17,$J$2:$U$2,"TRUE") -> 0 | Y17: ='01'!R17 -> 0 | Z17: ='02'!R17 -> 0 | AA17: ='03'!R17 -> 0 | AB17: ='04'!R17 -> 0 | AC17: ='05'!R17 -> 0 | AD17: ='06'!R17 -> 0 | AE17: ='07'!R17 -> 0 | AF17: ='08'!R17 -> 0 | AG17: ='09'!R17 -> 0 | AH17: ='10'!R17 -> 0 | AI17: ='11'!R17 -> 0 | AJ17: ='12'!R17 -> 0 | AK17: =SUM(Y17:AJ17) -> 0 | AL17: =SUMIFS($Y17:$AJ17,$Y$2:$AJ$2,"TRUE") -> 0 | AN17: ='01'!S17 -> 0 | AO17: ='02'!S17 -> 0 | AP17: ='03'!S17 -> 0 | AQ17: ='04'!S17 -> 0 | AR17: ='05'!S17 -> 0 | AS17: ='06'!S17 -> 0 | AT17: ='07'!S17 -> 0 | AU17: ='08'!S17 -> 0 | AV17: ='09'!S17 -> 0 | AW17: ='10'!S17 -> 0 | AX17: ='11'!S17 -> 0 | AY17: ='12'!S17 -> 0 | AZ17: =SUM(AN17:AY17) -> 0 | BA17: =SUMIFS($AN17:$AY17,$AN$2:$AY$2,"TRUE") -> 0 | BC17: ='01'!T17 -> 0 | BD17: ='02'!T17 -> 0 | BE17: ='03'!T17 -> 0 | BF17: ='04'!T17 -> 0 | BG17: ='05'!T17 -> 0 | BH17: ='06'!T17 -> 0 | BI17: ='07'!T17 -> 0 | BJ17: ='08'!T17 -> 0 | BK17: ='09'!T17 -> 0 | BL17: ='10'!T17 -> 0 | BM17: ='11'!T17 -> 0 | BN17: ='12'!T17 -> 0 | BO17: =SUM(BC17:BN17) -> 0 | BP17: =SUMIFS($BC17:$BN17,$BC$2:$BN$2,"TRUE") -> 0
B18: 04-SPWHI-07007700 | C18: TEG | D18: Single Malt Scotch | E18: The Macallan | F18: MAC | G18: The Macallan Double Cask 15YO | H18: 700ml | I18: 6 | J18: ='01'!N18 -> 0 | K18: ='02'!N18 -> 0 | L18: ='03'!N18 -> 0 | M18: ='04'!N18 -> 0 | N18: ='05'!N18 -> 0 | O18: ='06'!N18 -> 0 | P18: ='07'!N18 -> 0 | Q18: ='08'!N18 -> 0 | R18: ='09'!N18 -> 0 | S18: ='10'!N18 -> 0 | T18: ='11'!N18 -> 0 | U18: ='12'!N18 -> 0 | V18: =SUM(J18:U18) -> 0 | W18: =SUMIFS($J18:$U18,$J$2:$U$2,"TRUE") -> 0 | Y18: ='01'!R18 -> 0 | Z18: ='02'!R18 -> 0 | AA18: ='03'!R18 -> 0 | AB18: ='04'!R18 -> 0 | AC18: ='05'!R18 -> 0 | AD18: ='06'!R18 -> 0 | AE18: ='07'!R18 -> 0 | AF18: ='08'!R18 -> 0 | AG18: ='09'!R18 -> 0 | AH18: ='10'!R18 -> 0 | AI18: ='11'!R18 -> 0 | AJ18: ='12'!R18 -> 0 | AK18: =SUM(Y18:AJ18) -> 0 | AL18: =SUMIFS($Y18:$AJ18,$Y$2:$AJ$2,"TRUE") -> 0 | AN18: ='01'!S18 -> 0 | AO18: ='02'!S18 -> 0 | AP18: ='03'!S18 -> 0 | AQ18: ='04'!S18 -> 0 | AR18: ='05'!S18 -> 0 | AS18: ='06'!S18 -> 0 | AT18: ='07'!S18 -> 0 | AU18: ='08'!S18 -> 0 | AV18: ='09'!S18 -> 0 | AW18: ='10'!S18 -> 0 | AX18: ='11'!S18 -> 0 | AY18: ='12'!S18 -> 0 | AZ18: =SUM(AN18:AY18) -> 0 | BA18: =SUMIFS($AN18:$AY18,$AN$2:$AY$2,"TRUE") -> 0 | BC18: ='01'!T18 -> 0 | BD18: ='02'!T18 -> 0 | BE18: ='03'!T18 -> 0 | BF18: ='04'!T18 -> 0 | BG18: ='05'!T18 -> 0 | BH18: ='06'!T18 -> 0 | BI18: ='07'!T18 -> 0 | BJ18: ='08'!T18 -> 0 | BK18: ='09'!T18 -> 0 | BL18: ='10'!T18 -> 0 | BM18: ='11'!T18 -> 0 | BN18: ='12'!T18 -> 0 | BO18: =SUM(BC18:BN18) -> 0 | BP18: =SUMIFS($BC18:$BN18,$BC$2:$BN$2,"TRUE") -> 0
B19: 04-SPWHI-07009254 | C19: TEG | D19: Single Malt Scotch | E19: The Macallan | F19: MAC | G19: The Macallan Double Cask 18YO | H19: 700ml | I19: 6 | J19: ='01'!N19 -> 0 | K19: ='02'!N19 -> 0 | L19: ='03'!N19 -> 0 | M19: ='04'!N19 -> 0 | N19: ='05'!N19 -> 0 | O19: ='06'!N19 -> 0 | P19: ='07'!N19 -> 0 | Q19: ='08'!N19 -> 0 | R19: ='09'!N19 -> 0 | S19: ='10'!N19 -> 0 | T19: ='11'!N19 -> 0 | U19: ='12'!N19 -> 0 | V19: =SUM(J19:U19) -> 0 | W19: =SUMIFS($J19:$U19,$J$2:$U$2,"TRUE") -> 0 | Y19: ='01'!R19 -> 0 | Z19: ='02'!R19 -> 0 | AA19: ='03'!R19 -> 0 | AB19: ='04'!R19 -> 0 | AC19: ='05'!R19 -> 0 | AD19: ='06'!R19 -> 0 | AE19: ='07'!R19 -> 0 | AF19: ='08'!R19 -> 0 | AG19: ='09'!R19 -> 0 | AH19: ='10'!R19 -> 0 | AI19: ='11'!R19 -> 0 | AJ19: ='12'!R19 -> 0 | AK19: =SUM(Y19:AJ19) -> 0 | AL19: =SUMIFS($Y19:$AJ19,$Y$2:$AJ$2,"TRUE") -> 0 | AN19: ='01'!S19 -> 0 | AO19: ='02'!S19 -> 0 | AP19: ='03'!S19 -> 0 | AQ19: ='04'!S19 -> 0 | AR19: ='05'!S19 -> 0 | AS19: ='06'!S19 -> 0 | AT19: ='07'!S19 -> 0 | AU19: ='08'!S19 -> 0 | AV19: ='09'!S19 -> 0 | AW19: ='10'!S19 -> 0 | AX19: ='11'!S19 -> 0 | AY19: ='12'!S19 -> 0 | AZ19: =SUM(AN19:AY19) -> 0 | BA19: =SUMIFS($AN19:$AY19,$AN$2:$AY$2,"TRUE") -> 0 | BC19: ='01'!T19 -> 0 | BD19: ='02'!T19 -> 0 | BE19: ='03'!T19 -> 0 | BF19: ='04'!T19 -> 0 | BG19: ='05'!T19 -> 0 | BH19: ='06'!T19 -> 0 | BI19: ='07'!T19 -> 0 | BJ19: ='08'!T19 -> 0 | BK19: ='09'!T19 -> 0 | BL19: ='10'!T19 -> 0 | BM19: ='11'!T19 -> 0 | BN19: ='12'!T19 -> 0 | BO19: =SUM(BC19:BN19) -> 0 | BP19: =SUMIFS($BC19:$BN19,$BC$2:$BN$2,"TRUE") -> 0
B20: 04-SPWHI-07000311 | C20: TEG | D20: Single Malt Scotch | E20: The Macallan | F20: MAC | G20: The Macallan Double Cask 30YO | H20: 700ml | I20: 3 | J20: ='01'!N20 -> 0 | K20: ='02'!N20 -> 0 | L20: ='03'!N20 -> 0 | M20: ='04'!N20 -> 0 | N20: ='05'!N20 -> 0 | O20: ='06'!N20 -> 0 | P20: ='07'!N20 -> 0 | Q20: ='08'!N20 -> 0 | R20: ='09'!N20 -> 0 | S20: ='10'!N20 -> 0 | T20: ='11'!N20 -> 0 | U20: ='12'!N20 -> 0 | V20: =SUM(J20:U20) -> 0 | W20: =SUMIFS($J20:$U20,$J$2:$U$2,"TRUE") -> 0 | Y20: ='01'!R20 -> 0 | Z20: ='02'!R20 -> 0 | AA20: ='03'!R20 -> 0 | AB20: ='04'!R20 -> 0 | AC20: ='05'!R20 -> 0 | AD20: ='06'!R20 -> 0 | AE20: ='07'!R20 -> 0 | AF20: ='08'!R20 -> 0 | AG20: ='09'!R20 -> 0 | AH20: ='10'!R20 -> 0 | AI20: ='11'!R20 -> 0 | AJ20: ='12'!R20 -> 0 | AK20: =SUM(Y20:AJ20) -> 0 | AL20: =SUMIFS($Y20:$AJ20,$Y$2:$AJ$2,"TRUE") -> 0 | AN20: ='01'!S20 -> 0 | AO20: ='02'!S20 -> 0 | AP20: ='03'!S20 -> 0 | AQ20: ='04'!S20 -> 0 | AR20: ='05'!S20 -> 0 | AS20: ='06'!S20 -> 0 | AT20: ='07'!S20 -> 0 | AU20: ='08'!S20 -> 0 | AV20: ='09'!S20 -> 0 | AW20: ='10'!S20 -> 0 | AX20: ='11'!S20 -> 0 | AY20: ='12'!S20 -> 0 | AZ20: =SUM(AN20:AY20) -> 0 | BA20: =SUMIFS($AN20:$AY20,$AN$2:$AY$2,"TRUE") -> 0 | BC20: ='01'!T20 -> 0 | BD20: ='02'!T20 -> 0 | BE20: ='03'!T20 -> 0 | BF20: ='04'!T20 -> 0 | BG20: ='05'!T20 -> 0 | BH20: ='06'!T20 -> 0 | BI20: ='07'!T20 -> 0 | BJ20: ='08'!T20 -> 0 | BK20: ='09'!T20 -> 0 | BL20: ='10'!T20 -> 0 | BM20: ='11'!T20 -> 0 | BN20: ='12'!T20 -> 0 | BO20: =SUM(BC20:BN20) -> 0 | BP20: =SUMIFS($BC20:$BN20,$BC$2:$BN$2,"TRUE") -> 0
B21: 04-SPWHI-07000796 | C21: TEG | D21: Single Malt Scotch | E21: The Macallan | F21: MAC | G21: The Macallan Triple Cask 12YO | H21: 700ml | I21: 12 | J21: ='01'!N21 -> 0 | K21: ='02'!N21 -> 0 | L21: ='03'!N21 -> 0 | M21: ='04'!N21 -> 0 | N21: ='05'!N21 -> 0 | O21: ='06'!N21 -> 0 | P21: ='07'!N21 -> 0 | Q21: ='08'!N21 -> 0 | R21: ='09'!N21 -> 0 | S21: ='10'!N21 -> 0 | T21: ='11'!N21 -> 0 | U21: ='12'!N21 -> 0 | V21: =SUM(J21:U21) -> 0 | W21: =SUMIFS($J21:$U21,$J$2:$U$2,"TRUE") -> 0 | Y21: ='01'!R21 -> 0 | Z21: ='02'!R21 -> 0 | AA21: ='03'!R21 -> 0 | AB21: ='04'!R21 -> 0 | AC21: ='05'!R21 -> 0 | AD21: ='06'!R21 -> 0 | AE21: ='07'!R21 -> 0 | AF21: ='08'!R21 -> 0 | AG21: ='09'!R21 -> 0 | AH21: ='10'!R21 -> 0 | AI21: ='11'!R21 -> 0 | AJ21: ='12'!R21 -> 0 | AK21: =SUM(Y21:AJ21) -> 0 | AL21: =SUMIFS($Y21:$AJ21,$Y$2:$AJ$2,"TRUE") -> 0 | AN21: ='01'!S21 -> 0 | AO21: ='02'!S21 -> 0 | AP21: ='03'!S21 -> 0 | AQ21: ='04'!S21 -> 0 | AR21: ='05'!S21 -> 0 | AS21: ='06'!S21 -> 0 | AT21: ='07'!S21 -> 0 | AU21: ='08'!S21 -> 0 | AV21: ='09'!S21 -> 0 | AW21: ='10'!S21 -> 0 | AX21: ='11'!S21 -> 0 | AY21: ='12'!S21 -> 0 | AZ21: =SUM(AN21:AY21) -> 0 | BA21: =SUMIFS($AN21:$AY21,$AN$2:$AY$2,"TRUE") -> 0 | BC21: ='01'!T21 -> 0 | BD21: ='02'!T21 -> 0 | BE21: ='03'!T21 -> 0 | BF21: ='04'!T21 -> 0 | BG21: ='05'!T21 -> 0 | BH21: ='06'!T21 -> 0 | BI21: ='07'!T21 -> 0 | BJ21: ='08'!T21 -> 0 | BK21: ='09'!T21 -> 0 | BL21: ='10'!T21 -> 0 | BM21: ='11'!T21 -> 0 | BN21: ='12'!T21 -> 0 | BO21: =SUM(BC21:BN21) -> 0 | BP21: =SUMIFS($BC21:$BN21,$BC$2:$BN$2,"TRUE") -> 0
B22: 04-24HMN-07002650 | C22: TEG | D22: Single Malt Scotch | E22: The Macallan | F22: MAC | G22: The Macallan Harmony Vibrant Oak | H22: 700ml | I22: 6 | J22: ='01'!N22 -> 0 | K22: ='02'!N22 -> 0 | L22: ='03'!N22 -> 0 | M22: ='04'!N22 -> 0 | N22: ='05'!N22 -> 0 | O22: ='06'!N22 -> 0 | P22: ='07'!N22 -> 0 | Q22: ='08'!N22 -> 0 | R22: ='09'!N22 -> 0 | S22: ='10'!N22 -> 0 | T22: ='11'!N22 -> 0 | U22: ='12'!N22 -> 0 | V22: =SUM(J22:U22) -> 0 | W22: =SUMIFS($J22:$U22,$J$2:$U$2,"TRUE") -> 0 | Y22: ='01'!R22 -> 0 | Z22: ='02'!R22 -> 0 | AA22: ='03'!R22 -> 0 | AB22: ='04'!R22 -> 0 | AC22: ='05'!R22 -> 0 | AD22: ='06'!R22 -> 0 | AE22: ='07'!R22 -> 0 | AF22: ='08'!R22 -> 0 | AG22: ='09'!R22 -> 0 | AH22: ='10'!R22 -> 0 | AI22: ='11'!R22 -> 0 | AJ22: ='12'!R22 -> 0 | AK22: =SUM(Y22:AJ22) -> 0 | AL22: =SUMIFS($Y22:$AJ22,$Y$2:$AJ$2,"TRUE") -> 0 | AN22: ='01'!S22 -> 0 | AO22: ='02'!S22 -> 0 | AP22: ='03'!S22 -> 0 | AQ22: ='04'!S22 -> 0 | AR22: ='05'!S22 -> 0 | AS22: ='06'!S22 -> 0 | AT22: ='07'!S22 -> 0 | AU22: ='08'!S22 -> 0 | AV22: ='09'!S22 -> 0 | AW22: ='10'!S22 -> 0 | AX22: ='11'!S22 -> 0 | AY22: ='12'!S22 -> 0 | AZ22: =SUM(AN22:AY22) -> 0 | BA22: =SUMIFS($AN22:$AY22,$AN$2:$AY$2,"TRUE") -> 0 | BC22: ='01'!T22 -> 0 | BD22: ='02'!T22 -> 0 | BE22: ='03'!T22 -> 0 | BF22: ='04'!T22 -> 0 | BG22: ='05'!T22 -> 0 | BH22: ='06'!T22 -> 0 | BI22: ='07'!T22 -> 0 | BJ22: ='08'!T22 -> 0 | BK22: ='09'!T22 -> 0 | BL22: ='10'!T22 -> 0 | BM22: ='11'!T22 -> 0 | BN22: ='12'!T22 -> 0 | BO22: =SUM(BC22:BN22) -> 0 | BP22: =SUMIFS($BC22:$BN22,$BC$2:$BN$2,"TRUE") -> 0
B23: 04-23WHI-07002322 | C23: TEG | D23: Single Malt Scotch | E23: The Macallan | F23: MAC | G23: The Macallan Harmony Collection Amber Meadow | H23: 700ml | I23: 12 | J23: ='01'!N23 -> 0 | K23: ='02'!N23 -> 0 | L23: ='03'!N23 -> 0 | M23: ='04'!N23 -> 0 | N23: ='05'!N23 -> 0 | O23: ='06'!N23 -> 0 | P23: ='07'!N23 -> 0 | Q23: ='08'!N23 -> 0 | R23: ='09'!N23 -> 0 | S23: ='10'!N23 -> 0 | T23: ='11'!N23 -> 0 | U23: ='12'!N23 -> 0 | V23: =SUM(J23:U23) -> 0 | W23: =SUMIFS($J23:$U23,$J$2:$U$2,"TRUE") -> 0 | Y23: ='01'!R23 -> 0 | Z23: ='02'!R23 -> 0 | AA23: ='03'!R23 -> 0 | AB23: ='04'!R23 -> 0 | AC23: ='05'!R23 -> 0 | AD23: ='06'!R23 -> 0 | AE23: ='07'!R23 -> 0 | AF23: ='08'!R23 -> 0 | AG23: ='09'!R23 -> 0 | AH23: ='10'!R23 -> 0 | AI23: ='11'!R23 -> 0 | AJ23: ='12'!R23 -> 0 | AK23: =SUM(Y23:AJ23) -> 0 | AL23: =SUMIFS($Y23:$AJ23,$Y$2:$AJ$2,"TRUE") -> 0 | AN23: ='01'!S23 -> 0 | AO23: ='02'!S23 -> 0 | AP23: ='03'!S23 -> 0 | AQ23: ='04'!S23 -> 0 | AR23: ='05'!S23 -> 0 | AS23: ='06'!S23 -> 0 | AT23: ='07'!S23 -> 0 | AU23: ='08'!S23 -> 0 | AV23: ='09'!S23 -> 0 | AW23: ='10'!S23 -> 0 | AX23: ='11'!S23 -> 0 | AY23: ='12'!S23 -> 0 | AZ23: =SUM(AN23:AY23) -> 0 | BA23: =SUMIFS($AN23:$AY23,$AN$2:$AY$2,"TRUE") -> 0 | BC23: ='01'!T23 -> 0 | BD23: ='02'!T23 -> 0 | BE23: ='03'!T23 -> 0 | BF23: ='04'!T23 -> 0 | BG23: ='05'!T23 -> 0 | BH23: ='06'!T23 -> 0 | BI23: ='07'!T23 -> 0 | BJ23: ='08'!T23 -> 0 | BK23: ='09'!T23 -> 0 | BL23: ='10'!T23 -> 0 | BM23: ='11'!T23 -> 0 | BN23: ='12'!T23 -> 0 | BO23: =SUM(BC23:BN23) -> 0 | BP23: =SUMIFS($BC23:$BN23,$BC$2:$BN$2,"TRUE") -> 0
B24: 04-SPWHI-07000557 | C24: TEG | D24: Single Malt Scotch | E24: The Macallan | F24: MAC | G24: The Macallan Harmony Collection | H24: 700ml | I24: 6 | J24: ='01'!N24 -> 0 | K24: ='02'!N24 -> 0 | L24: ='03'!N24 -> 0 | M24: ='04'!N24 -> 0 | N24: ='05'!N24 -> 0 | O24: ='06'!N24 -> 0 | P24: ='07'!N24 -> 0 | Q24: ='08'!N24 -> 0 | R24: ='09'!N24 -> 0 | S24: ='10'!N24 -> 0 | T24: ='11'!N24 -> 0 | U24: ='12'!N24 -> 0 | V24: =SUM(J24:U24) -> 0 | W24: =SUMIFS($J24:$U24,$J$2:$U$2,"TRUE") -> 0 | Y24: ='01'!R24 -> 0 | Z24: ='02'!R24 -> 0 | AA24: ='03'!R24 -> 0 | AB24: ='04'!R24 -> 0 | AC24: ='05'!R24 -> 0 | AD24: ='06'!R24 -> 0 | AE24: ='07'!R24 -> 0 | AF24: ='08'!R24 -> 0 | AG24: ='09'!R24 -> 0 | AH24: ='10'!R24 -> 0 | AI24: ='11'!R24 -> 0 | AJ24: ='12'!R24 -> 0 | AK24: =SUM(Y24:AJ24) -> 0 | AL24: =SUMIFS($Y24:$AJ24,$Y$2:$AJ$2,"TRUE") -> 0 | AN24: ='01'!S24 -> 0 | AO24: ='02'!S24 -> 0 | AP24: ='03'!S24 -> 0 | AQ24: ='04'!S24 -> 0 | AR24: ='05'!S24 -> 0 | AS24: ='06'!S24 -> 0 | AT24: ='07'!S24 -> 0 | AU24: ='08'!S24 -> 0 | AV24: ='09'!S24 -> 0 | AW24: ='10'!S24 -> 0 | AX24: ='11'!S24 -> 0 | AY24: ='12'!S24 -> 0 | AZ24: =SUM(AN24:AY24) -> 0 | BA24: =SUMIFS($AN24:$AY24,$AN$2:$AY$2,"TRUE") -> 0 | BC24: ='01'!T24 -> 0 | BD24: ='02'!T24 -> 0 | BE24: ='03'!T24 -> 0 | BF24: ='04'!T24 -> 0 | BG24: ='05'!T24 -> 0 | BH24: ='06'!T24 -> 0 | BI24: ='07'!T24 -> 0 | BJ24: ='08'!T24 -> 0 | BK24: ='09'!T24 -> 0 | BL24: ='10'!T24 -> 0 | BM24: ='11'!T24 -> 0 | BN24: ='12'!T24 -> 0 | BO24: =SUM(BC24:BN24) -> 0 | BP24: =SUMIFS($BC24:$BN24,$BC$2:$BN$2,"TRUE") -> 0
B25: 04-SPWHI-07001226 | C25: TEG | D25: Single Malt Scotch | E25: The Macallan | F25: MAC | G25: The Macallan Harmony Collection Intense Arabica | H25: 700ml | I25: 6 | J25: ='01'!N25 -> 0 | K25: ='02'!N25 -> 0 | L25: ='03'!N25 -> 0 | M25: ='04'!N25 -> 0 | N25: ='05'!N25 -> 0 | O25: ='06'!N25 -> 0 | P25: ='07'!N25 -> 0 | Q25: ='08'!N25 -> 0 | R25: ='09'!N25 -> 0 | S25: ='10'!N25 -> 0 | T25: ='11'!N25 -> 0 | U25: ='12'!N25 -> 0 | V25: =SUM(J25:U25) -> 0 | W25: =SUMIFS($J25:$U25,$J$2:$U$2,"TRUE") -> 0 | Y25: ='01'!R25 -> 0 | Z25: ='02'!R25 -> 0 | AA25: ='03'!R25 -> 0 | AB25: ='04'!R25 -> 0 | AC25: ='05'!R25 -> 0 | AD25: ='06'!R25 -> 0 | AE25: ='07'!R25 -> 0 | AF25: ='08'!R25 -> 0 | AG25: ='09'!R25 -> 0 | AH25: ='10'!R25 -> 0 | AI25: ='11'!R25 -> 0 | AJ25: ='12'!R25 -> 0 | AK25: =SUM(Y25:AJ25) -> 0 | AL25: =SUMIFS($Y25:$AJ25,$Y$2:$AJ$2,"TRUE") -> 0 | AN25: ='01'!S25 -> 0 | AO25: ='02'!S25 -> 0 | AP25: ='03'!S25 -> 0 | AQ25: ='04'!S25 -> 0 | AR25: ='05'!S25 -> 0 | AS25: ='06'!S25 -> 0 | AT25: ='07'!S25 -> 0 | AU25: ='08'!S25 -> 0 | AV25: ='09'!S25 -> 0 | AW25: ='10'!S25 -> 0 | AX25: ='11'!S25 -> 0 | AY25: ='12'!S25 -> 0 | AZ25: =SUM(AN25:AY25) -> 0 | BA25: =SUMIFS($AN25:$AY25,$AN$2:$AY$2,"TRUE") -> 0 | BC25: ='01'!T25 -> 0 | BD25: ='02'!T25 -> 0 | BE25: ='03'!T25 -> 0 | BF25: ='04'!T25 -> 0 | BG25: ='05'!T25 -> 0 | BH25: ='06'!T25 -> 0 | BI25: ='07'!T25 -> 0 | BJ25: ='08'!T25 -> 0 | BK25: ='09'!T25 -> 0 | BL25: ='10'!T25 -> 0 | BM25: ='11'!T25 -> 0 | BN25: ='12'!T25 -> 0 | BO25: =SUM(BC25:BN25) -> 0 | BP25: =SUMIFS($BC25:$BN25,$BC$2:$BN$2,"TRUE") -> 0
... B306: 20-SPTEQ-07001308 | C306: Proximo | D306: Tequila | E306: Jose Cuervo | F306: JOC | G306: Jose Cuervo Especial Reposado Tequila 35% | H306: 700ml | I306: 12 | J306: ='01'!N306 -> 0 | K306: ='02'!N306 -> 0 | L306: ='03'!N306 -> 0 | M306: ='04'!N306 -> 0 | N306: ='05'!N306 -> 0 | O306: ='06'!N306 -> 0 | P306: ='07'!N306 -> 0 | Q306: ='08'!N306 -> 0 | R306: ='09'!N306 -> 0 | S306: ='10'!N306 -> 0 | T306: ='11'!N306 -> 0 | U306: ='12'!N306 -> 0 | V306: =SUM(J306:U306) -> 0 | W306: =SUMIFS($J306:$U306,$J$2:$U$2,"TRUE") -> 0 | Y306: ='01'!R306 -> 0 | Z306: ='02'!R306 -> 0 | AA306: ='03'!R306 -> 0 | AB306: ='04'!R306 -> 0 | AC306: ='05'!R306 -> 0 | AD306: ='06'!R306 -> 0 | AE306: ='07'!R306 -> 0 | AF306: ='08'!R306 -> 0 | AG306: ='09'!R306 -> 0 | AH306: ='10'!R306 -> 0 | AI306: ='11'!R306 -> 0 | AJ306: ='12'!R306 -> 0 | AK306: =SUM(Y306:AJ306) -> 0 | AL306: =SUMIFS($Y306:$AJ306,$Y$2:$AJ$2,"TRUE") -> 0 | AN306: ='01'!S306 -> 0 | AO306: ='02'!S306 -> 0 | AP306: ='03'!S306 -> 0 | AQ306: ='04'!S306 -> 0 | AR306: ='05'!S306 -> 0 | AS306: ='06'!S306 -> 0 | AT306: ='07'!S306 -> 0 | AU306: ='08'!S306 -> 0 | AV306: ='09'!S306 -> 0 | AW306: ='10'!S306 -> 0 | AX306: ='11'!S306 -> 0 | AY306: ='12'!S306 -> 0 | AZ306: =SUM(AN306:AY306) -> 0 | BA306: =SUMIFS($AN306:$AY306,$AN$2:$AY$2,"TRUE") -> 0 | BC306: ='01'!T306 -> 0 | BD306: ='02'!T306 -> 0 | BE306: ='03'!T306 -> 0 | BF306: ='04'!T306 -> 0 | BG306: ='05'!T306 -> 0 | BH306: ='06'!T306 -> 0 | BI306: ='07'!T306 -> 0 | BJ306: ='08'!T306 -> 0 | BK306: ='09'!T306 -> 0 | BL306: ='10'!T306 -> 0 | BM306: ='11'!T306 -> 0 | BN306: ='12'!T306 -> 0 | BO306: =SUM(BC306:BN306) -> 0 | BP306: =SUMIFS($BC306:$BN306,$BC$2:$BN$2,"TRUE") -> 0
J307: ='01'!N307 -> 0 | K307: ='02'!N307 -> 0 | L307: ='03'!N307 -> 0 | M307: ='04'!N307 -> 0 | N307: ='05'!N307 -> 0 | O307: ='06'!N307 -> 0 | P307: ='07'!N307 -> 0 | Q307: ='08'!N307 -> 0 | R307: ='09'!N307 -> 0 | S307: ='10'!N307 -> 0 | T307: ='11'!N307 -> 0 | U307: ='12'!N307 -> 0 | V307: =SUM(J307:U307) -> 0 | W307: =SUMIFS($J307:$U307,$J$2:$U$2,"TRUE") -> 0 | Y307: ='01'!R307 -> 0 | Z307: ='02'!R307 -> 0 | AA307: ='03'!R307 -> 0 | AB307: ='04'!R307 -> 0 | AC307: ='05'!R307 -> 0 | AD307: ='06'!R307 -> 0 | AE307: ='07'!R307 -> 0 | AF307: ='08'!R307 -> 0 | AG307: ='09'!R307 -> 0 | AH307: ='10'!R307 -> 0 | AI307: ='11'!R307 -> 0 | AJ307: ='12'!R307 -> 0 | AK307: =SUM(Y307:AJ307) -> 0 | AL307: =SUMIFS($Y307:$AJ307,$Y$2:$AJ$2,"TRUE") -> 0 | AN307: ='01'!S307 -> 0 | AO307: ='02'!S307 -> 0 | AP307: ='03'!S307 -> 0 | AQ307: ='04'!S307 -> 0 | AR307: ='05'!S307 -> 0 | AS307: ='06'!S307 -> 0 | AT307: ='07'!S307 -> 0 | AU307: ='08'!S307 -> 0 | AV307: ='09'!S307 -> 0 | AW307: ='10'!S307 -> 0 | AX307: ='11'!S307 -> 0 | AY307: ='12'!S307 -> 0 | AZ307: =SUM(AN307:AY307) -> 0 | BA307: =SUMIFS($AN307:$AY307,$AN$2:$AY$2,"TRUE") -> 0 | BC307: ='01'!T307 -> 0 | BD307: ='02'!T307 -> 0 | BE307: ='03'!T307 -> 0 | BF307: ='04'!T307 -> 0 | BG307: ='05'!T307 -> 0 | BH307: ='06'!T307 -> 0 | BI307: ='07'!T307 -> 0 | BJ307: ='08'!T307 -> 0 | BK307: ='09'!T307 -> 0 | BL307: ='10'!T307 -> 0 | BM307: ='11'!T307 -> 0 | BN307: ='12'!T307 -> 0 | BO307: =SUM(BC307:BN307) -> 0 | BP307: =SUMIFS($BC307:$BN307,$BC$2:$BN$2,"TRUE") -> 0
J308: ='01'!N308 -> 0 | K308: ='02'!N308 -> 0 | L308: ='03'!N308 -> 0 | M308: ='04'!N308 -> 0 | N308: ='05'!N308 -> 0 | O308: ='06'!N308 -> 0 | P308: ='07'!N308 -> 0 | Q308: ='08'!N308 -> 0 | R308: ='09'!N308 -> 0 | S308: ='10'!N308 -> 0 | T308: ='11'!N308 -> 0 | U308: ='12'!N308 -> 0 | V308: =SUM(J308:U308) -> 0 | W308: =SUMIFS($J308:$U308,$J$2:$U$2,"TRUE") -> 0 | Y308: ='01'!R308 -> 0 | Z308: ='02'!R308 -> 0 | AA308: ='03'!R308 -> 0 | AB308: ='04'!R308 -> 0 | AC308: ='05'!R308 -> 0 | AD308: ='06'!R308 -> 0 | AE308: ='07'!R308 -> 0 | AF308: ='08'!R308 -> 0 | AG308: ='09'!R308 -> 0 | AH308: ='10'!R308 -> 0 | AI308: ='11'!R308 -> 0 | AJ308: ='12'!R308 -> 0 | AK308: =SUM(Y308:AJ308) -> 0 | AL308: =SUMIFS($Y308:$AJ308,$Y$2:$AJ$2,"TRUE") -> 0 | AN308: ='01'!S308 -> 0 | AO308: ='02'!S308 -> 0 | AP308: ='03'!S308 -> 0 | AQ308: ='04'!S308 -> 0 | AR308: ='05'!S308 -> 0 | AS308: ='06'!S308 -> 0 | AT308: ='07'!S308 -> 0 | AU308: ='08'!S308 -> 0 | AV308: ='09'!S308 -> 0 | AW308: ='10'!S308 -> 0 | AX308: ='11'!S308 -> 0 | AY308: ='12'!S308 -> 0 | AZ308: =SUM(AN308:AY308) -> 0 | BA308: =SUMIFS($AN308:$AY308,$AN$2:$AY$2,"TRUE") -> 0 | BC308: ='01'!T308 -> 0 | BD308: ='02'!T308 -> 0 | BE308: ='03'!T308 -> 0 | BF308: ='04'!T308 -> 0 | BG308: ='05'!T308 -> 0 | BH308: ='06'!T308 -> 0 | BI308: ='07'!T308 -> 0 | BJ308: ='08'!T308 -> 0 | BK308: ='09'!T308 -> 0 | BL308: ='10'!T308 -> 0 | BM308: ='11'!T308 -> 0 | BN308: ='12'!T308 -> 0 | BO308: =SUM(BC308:BN308) -> 0 | BP308: =SUMIFS($BC308:$BN308,$BC$2:$BN$2,"TRUE") -> 0
J309: ='01'!N309 -> 0 | K309: ='02'!N309 -> 0 | L309: ='03'!N309 -> 0 | M309: ='04'!N309 -> 0 | N309: ='05'!N309 -> 0 | O309: ='06'!N309 -> 0 | P309: ='07'!N309 -> 0 | Q309: ='08'!N309 -> 0 | R309: ='09'!N309 -> 0 | S309: ='10'!N309 -> 0 | T309: ='11'!N309 -> 0 | U309: ='12'!N309 -> 0 | V309: =SUM(J309:U309) -> 0 | W309: =SUMIFS($J309:$U309,$J$2:$U$2,"TRUE") -> 0 | Y309: ='01'!R309 -> 0 | Z309: ='02'!R309 -> 0 | AA309: ='03'!R309 -> 0 | AB309: ='04'!R309 -> 0 | AC309: ='05'!R309 -> 0 | AD309: ='06'!R309 -> 0 | AE309: ='07'!R309 -> 0 | AF309: ='08'!R309 -> 0 | AG309: ='09'!R309 -> 0 | AH309: ='10'!R309 -> 0 | AI309: ='11'!R309 -> 0 | AJ309: ='12'!R309 -> 0 | AK309: =SUM(Y309:AJ309) -> 0 | AL309: =SUMIFS($Y309:$AJ309,$Y$2:$AJ$2,"TRUE") -> 0 | AN309: ='01'!S309 -> 0 | AO309: ='02'!S309 -> 0 | AP309: ='03'!S309 -> 0 | AQ309: ='04'!S309 -> 0 | AR309: ='05'!S309 -> 0 | AS309: ='06'!S309 -> 0 | AT309: ='07'!S309 -> 0 | AU309: ='08'!S309 -> 0 | AV309: ='09'!S309 -> 0 | AW309: ='10'!S309 -> 0 | AX309: ='11'!S309 -> 0 | AY309: ='12'!S309 -> 0 | AZ309: =SUM(AN309:AY309) -> 0 | BA309: =SUMIFS($AN309:$AY309,$AN$2:$AY$2,"TRUE") -> 0 | BC309: ='01'!T309 -> 0 | BD309: ='02'!T309 -> 0 | BE309: ='03'!T309 -> 0 | BF309: ='04'!T309 -> 0 | BG309: ='05'!T309 -> 0 | BH309: ='06'!T309 -> 0 | BI309: ='07'!T309 -> 0 | BJ309: ='08'!T309 -> 0 | BK309: ='09'!T309 -> 0 | BL309: ='10'!T309 -> 0 | BM309: ='11'!T309 -> 0 | BN309: ='12'!T309 -> 0 | BO309: =SUM(BC309:BN309) -> 0 | BP309: =SUMIFS($BC309:$BN309,$BC$2:$BN$2,"TRUE") -> 0
J310: ='01'!N310 -> 0 | K310: ='02'!N310 -> 0 | L310: ='03'!N310 -> 0 | M310: ='04'!N310 -> 0 | N310: ='05'!N310 -> 0 | O310: ='06'!N310 -> 0 | P310: ='07'!N310 -> 0 | Q310: ='08'!N310 -> 0 | R310: ='09'!N310 -> 0 | S310: ='10'!N310 -> 0 | T310: ='11'!N310 -> 0 | U310: ='12'!N310 -> 0 | V310: =SUM(J310:U310) -> 0 | W310: =SUMIFS($J310:$U310,$J$2:$U$2,"TRUE") -> 0 | Y310: ='01'!R310 -> 0 | Z310: ='02'!R310 -> 0 | AA310: ='03'!R310 -> 0 | AB310: ='04'!R310 -> 0 | AC310: ='05'!R310 -> 0 | AD310: ='06'!R310 -> 0 | AE310: ='07'!R310 -> 0 | AF310: ='08'!R310 -> 0 | AG310: ='09'!R310 -> 0 | AH310: ='10'!R310 -> 0 | AI310: ='11'!R310 -> 0 | AJ310: ='12'!R310 -> 0 | AK310: =SUM(Y310:AJ310) -> 0 | AL310: =SUMIFS($Y310:$AJ310,$Y$2:$AJ$2,"TRUE") -> 0 | AN310: ='01'!S310 -> 0 | AO310: ='02'!S310 -> 0 | AP310: ='03'!S310 -> 0 | AQ310: ='04'!S310 -> 0 | AR310: ='05'!S310 -> 0 | AS310: ='06'!S310 -> 0 | AT310: ='07'!S310 -> 0 | AU310: ='08'!S310 -> 0 | AV310: ='09'!S310 -> 0 | AW310: ='10'!S310 -> 0 | AX310: ='11'!S310 -> 0 | AY310: ='12'!S310 -> 0 | AZ310: =SUM(AN310:AY310) -> 0 | BA310: =SUMIFS($AN310:$AY310,$AN$2:$AY$2,"TRUE") -> 0 | BC310: ='01'!T310 -> 0 | BD310: ='02'!T310 -> 0 | BE310: ='03'!T310 -> 0 | BF310: ='04'!T310 -> 0 | BG310: ='05'!T310 -> 0 | BH310: ='06'!T310 -> 0 | BI310: ='07'!T310 -> 0 | BJ310: ='08'!T310 -> 0 | BK310: ='09'!T310 -> 0 | BL310: ='10'!T310 -> 0 | BM310: ='11'!T310 -> 0 | BN310: ='12'!T310 -> 0 | BO310: =SUM(BC310:BN310) -> 0 | BP310: =SUMIFS($BC310:$BN310,$BC$2:$BN$2,"TRUE") -> 0
J311: ='01'!N311 -> 0 | K311: ='02'!N311 -> 0 | L311: ='03'!N311 -> 0 | M311: ='04'!N311 -> 0 | N311: ='05'!N311 -> 0 | O311: ='06'!N311 -> 0 | P311: ='07'!N311 -> 0 | Q311: ='08'!N311 -> 0 | R311: ='09'!N311 -> 0 | S311: ='10'!N311 -> 0 | T311: ='11'!N311 -> 0 | U311: ='12'!N311 -> 0 | V311: =SUM(J311:U311) -> 0 | W311: =SUMIFS($J311:$U311,$J$2:$U$2,"TRUE") -> 0 | Y311: ='01'!R311 -> 0 | Z311: ='02'!R311 -> 0 | AA311: ='03'!R311 -> 0 | AB311: ='04'!R311 -> 0 | AC311: ='05'!R311 -> 0 | AD311: ='06'!R311 -> 0 | AE311: ='07'!R311 -> 0 | AF311: ='08'!R311 -> 0 | AG311: ='09'!R311 -> 0 | AH311: ='10'!R311 -> 0 | AI311: ='11'!R311 -> 0 | AJ311: ='12'!R311 -> 0 | AK311: =SUM(Y311:AJ311) -> 0 | AL311: =SUMIFS($Y311:$AJ311,$Y$2:$AJ$2,"TRUE") -> 0 | AN311: ='01'!S311 -> 0 | AO311: ='02'!S311 -> 0 | AP311: ='03'!S311 -> 0 | AQ311: ='04'!S311 -> 0 | AR311: ='05'!S311 -> 0 | AS311: ='06'!S311 -> 0 | AT311: ='07'!S311 -> 0 | AU311: ='08'!S311 -> 0 | AV311: ='09'!S311 -> 0 | AW311: ='10'!S311 -> 0 | AX311: ='11'!S311 -> 0 | AY311: ='12'!S311 -> 0 | AZ311: =SUM(AN311:AY311) -> 0 | BA311: =SUMIFS($AN311:$AY311,$AN$2:$AY$2,"TRUE") -> 0 | BC311: ='01'!T311 -> 0 | BD311: ='02'!T311 -> 0 | BE311: ='03'!T311 -> 0 | BF311: ='04'!T311 -> 0 | BG311: ='05'!T311 -> 0 | BH311: ='06'!T311 -> 0 | BI311: ='07'!T311 -> 0 | BJ311: ='08'!T311 -> 0 | BK311: ='09'!T311 -> 0 | BL311: ='10'!T311 -> 0 | BM311: ='11'!T311 -> 0 | BN311: ='12'!T311 -> 0 | BO311: =SUM(BC311:BN311) -> 0 | BP311: =SUMIFS($BC311:$BN311,$BC$2:$BN$2,"TRUE") -> 0
J312: ='01'!N312 -> 0 | K312: ='02'!N312 -> 0 | L312: ='03'!N312 -> 0 | M312: ='04'!N312 -> 0 | N312: ='05'!N312 -> 0 | O312: ='06'!N312 -> 0 | P312: ='07'!N312 -> 0 | Q312: ='08'!N312 -> 0 | R312: ='09'!N312 -> 0 | S312: ='10'!N312 -> 0 | T312: ='11'!N312 -> 0 | U312: ='12'!N312 -> 0 | V312: =SUM(J312:U312) -> 0 | W312: =SUMIFS($J312:$U312,$J$2:$U$2,"TRUE") -> 0 | Y312: ='01'!R312 -> 0 | Z312: ='02'!R312 -> 0 | AA312: ='03'!R312 -> 0 | AB312: ='04'!R312 -> 0 | AC312: ='05'!R312 -> 0 | AD312: ='06'!R312 -> 0 | AE312: ='07'!R312 -> 0 | AF312: ='08'!R312 -> 0 | AG312: ='09'!R312 -> 0 | AH312: ='10'!R312 -> 0 | AI312: ='11'!R312 -> 0 | AJ312: ='12'!R312 -> 0 | AK312: =SUM(Y312:AJ312) -> 0 | AL312: =SUMIFS($Y312:$AJ312,$Y$2:$AJ$2,"TRUE") -> 0 | AN312: ='01'!S312 -> 0 | AO312: ='02'!S312 -> 0 | AP312: ='03'!S312 -> 0 | AQ312: ='04'!S312 -> 0 | AR312: ='05'!S312 -> 0 | AS312: ='06'!S312 -> 0 | AT312: ='07'!S312 -> 0 | AU312: ='08'!S312 -> 0 | AV312: ='09'!S312 -> 0 | AW312: ='10'!S312 -> 0 | AX312: ='11'!S312 -> 0 | AY312: ='12'!S312 -> 0 | AZ312: =SUM(AN312:AY312) -> 0 | BA312: =SUMIFS($AN312:$AY312,$AN$2:$AY$2,"TRUE") -> 0 | BC312: ='01'!T312 -> 0 | BD312: ='02'!T312 -> 0 | BE312: ='03'!T312 -> 0 | BF312: ='04'!T312 -> 0 | BG312: ='05'!T312 -> 0 | BH312: ='06'!T312 -> 0 | BI312: ='07'!T312 -> 0 | BJ312: ='08'!T312 -> 0 | BK312: ='09'!T312 -> 0 | BL312: ='10'!T312 -> 0 | BM312: ='11'!T312 -> 0 | BN312: ='12'!T312 -> 0 | BO312: =SUM(BC312:BN312) -> 0 | BP312: =SUMIFS($BC312:$BN312,$BC$2:$BN$2,"TRUE") -> 0
J313: ='01'!N313 -> 0 | K313: ='02'!N313 -> 0 | L313: ='03'!N313 -> 0 | M313: ='04'!N313 -> 0 | N313: ='05'!N313 -> 0 | O313: ='06'!N313 -> 0 | P313: ='07'!N313 -> 0 | Q313: ='08'!N313 -> 0 | R313: ='09'!N313 -> 0 | S313: ='10'!N313 -> 0 | T313: ='11'!N313 -> 0 | U313: ='12'!N313 -> 0 | V313: =SUM(J313:U313) -> 0 | W313: =SUMIFS($J313:$U313,$J$2:$U$2,"TRUE") -> 0 | Y313: ='01'!R313 -> 0 | Z313: ='02'!R313 -> 0 | AA313: ='03'!R313 -> 0 | AB313: ='04'!R313 -> 0 | AC313: ='05'!R313 -> 0 | AD313: ='06'!R313 -> 0 | AE313: ='07'!R313 -> 0 | AF313: ='08'!R313 -> 0 | AG313: ='09'!R313 -> 0 | AH313: ='10'!R313 -> 0 | AI313: ='11'!R313 -> 0 | AJ313: ='12'!R313 -> 0 | AK313: =SUM(Y313:AJ313) -> 0 | AL313: =SUMIFS($Y313:$AJ313,$Y$2:$AJ$2,"TRUE") -> 0 | AN313: ='01'!S313 -> 0 | AO313: ='02'!S313 -> 0 | AP313: ='03'!S313 -> 0 | AQ313: ='04'!S313 -> 0 | AR313: ='05'!S313 -> 0 | AS313: ='06'!S313 -> 0 | AT313: ='07'!S313 -> 0 | AU313: ='08'!S313 -> 0 | AV313: ='09'!S313 -> 0 | AW313: ='10'!S313 -> 0 | AX313: ='11'!S313 -> 0 | AY313: ='12'!S313 -> 0 | AZ313: =SUM(AN313:AY313) -> 0 | BA313: =SUMIFS($AN313:$AY313,$AN$2:$AY$2,"TRUE") -> 0 | BC313: ='01'!T313 -> 0 | BD313: ='02'!T313 -> 0 | BE313: ='03'!T313 -> 0 | BF313: ='04'!T313 -> 0 | BG313: ='05'!T313 -> 0 | BH313: ='06'!T313 -> 0 | BI313: ='07'!T313 -> 0 | BJ313: ='08'!T313 -> 0 | BK313: ='09'!T313 -> 0 | BL313: ='10'!T313 -> 0 | BM313: ='11'!T313 -> 0 | BN313: ='12'!T313 -> 0 | BO313: =SUM(BC313:BN313) -> 0 | BP313: =SUMIFS($BC313:$BN313,$BC$2:$BN$2,"TRUE") -> 0
J314: ='01'!N314 -> 0 | K314: ='02'!N314 -> 0 | L314: ='03'!N314 -> 0 | M314: ='04'!N314 -> 0 | N314: ='05'!N314 -> 0 | O314: ='06'!N314 -> 0 | P314: ='07'!N314 -> 0 | Q314: ='08'!N314 -> 0 | R314: ='09'!N314 -> 0 | S314: ='10'!N314 -> 0 | T314: ='11'!N314 -> 0 | U314: ='12'!N314 -> 0 | V314: =SUM(J314:U314) -> 0 | W314: =SUMIFS($J314:$U314,$J$2:$U$2,"TRUE") -> 0 | Y314: ='01'!R314 -> 0 | Z314: ='02'!R314 -> 0 | AA314: ='03'!R314 -> 0 | AB314: ='04'!R314 -> 0 | AC314: ='05'!R314 -> 0 | AD314: ='06'!R314 -> 0 | AE314: ='07'!R314 -> 0 | AF314: ='08'!R314 -> 0 | AG314: ='09'!R314 -> 0 | AH314: ='10'!R314 -> 0 | AI314: ='11'!R314 -> 0 | AJ314: ='12'!R314 -> 0 | AK314: =SUM(Y314:AJ314) -> 0 | AL314: =SUMIFS($Y314:$AJ314,$Y$2:$AJ$2,"TRUE") -> 0 | AN314: ='01'!S314 -> 0 | AO314: ='02'!S314 -> 0 | AP314: ='03'!S314 -> 0 | AQ314: ='04'!S314 -> 0 | AR314: ='05'!S314 -> 0 | AS314: ='06'!S314 -> 0 | AT314: ='07'!S314 -> 0 | AU314: ='08'!S314 -> 0 | AV314: ='09'!S314 -> 0 | AW314: ='10'!S314 -> 0 | AX314: ='11'!S314 -> 0 | AY314: ='12'!S314 -> 0 | AZ314: =SUM(AN314:AY314) -> 0 | BA314: =SUMIFS($AN314:$AY314,$AN$2:$AY$2,"TRUE") -> 0 | BC314: ='01'!T314 -> 0 | BD314: ='02'!T314 -> 0 | BE314: ='03'!T314 -> 0 | BF314: ='04'!T314 -> 0 | BG314: ='05'!T314 -> 0 | BH314: ='06'!T314 -> 0 | BI314: ='07'!T314 -> 0 | BJ314: ='08'!T314 -> 0 | BK314: ='09'!T314 -> 0 | BL314: ='10'!T314 -> 0 | BM314: ='11'!T314 -> 0 | BN314: ='12'!T314 -> 0 | BO314: =SUM(BC314:BN314) -> 0 | BP314: =SUMIFS($BC314:$BN314,$BC$2:$BN$2,"TRUE") -> 0
J315: ='01'!N315 -> 0 | K315: ='02'!N315 -> 0 | L315: ='03'!N315 -> 0 | M315: ='04'!N315 -> 0 | N315: ='05'!N315 -> 0 | O315: ='06'!N315 -> 0 | P315: ='07'!N315 -> 0 | Q315: ='08'!N315 -> 0 | R315: ='09'!N315 -> 0 | S315: ='10'!N315 -> 0 | T315: ='11'!N315 -> 0 | U315: ='12'!N315 -> 0 | V315: =SUM(J315:U315) -> 0 | W315: =SUMIFS($J315:$U315,$J$2:$U$2,"TRUE") -> 0 | Y315: ='01'!R315 -> 0 | Z315: ='02'!R315 -> 0 | AA315: ='03'!R315 -> 0 | AB315: ='04'!R315 -> 0 | AC315: ='05'!R315 -> 0 | AD315: ='06'!R315 -> 0 | AE315: ='07'!R315 -> 0 | AF315: ='08'!R315 -> 0 | AG315: ='09'!R315 -> 0 | AH315: ='10'!R315 -> 0 | AI315: ='11'!R315 -> 0 | AJ315: ='12'!R315 -> 0 | AK315: =SUM(Y315:AJ315) -> 0 | AL315: =SUMIFS($Y315:$AJ315,$Y$2:$AJ$2,"TRUE") -> 0 | AN315: ='01'!S315 -> 0 | AO315: ='02'!S315 -> 0 | AP315: ='03'!S315 -> 0 | AQ315: ='04'!S315 -> 0 | AR315: ='05'!S315 -> 0 | AS315: ='06'!S315 -> 0 | AT315: ='07'!S315 -> 0 | AU315: ='08'!S315 -> 0 | AV315: ='09'!S315 -> 0 | AW315: ='10'!S315 -> 0 | AX315: ='11'!S315 -> 0 | AY315: ='12'!S315 -> 0 | AZ315: =SUM(AN315:AY315) -> 0 | BA315: =SUMIFS($AN315:$AY315,$AN$2:$AY$2,"TRUE") -> 0 | BC315: ='01'!T315 -> 0 | BD315: ='02'!T315 -> 0 | BE315: ='03'!T315 -> 0 | BF315: ='04'!T315 -> 0 | BG315: ='05'!T315 -> 0 | BH315: ='06'!T315 -> 0 | BI315: ='07'!T315 -> 0 | BJ315: ='08'!T315 -> 0 | BK315: ='09'!T315 -> 0 | BL315: ='10'!T315 -> 0 | BM315: ='11'!T315 -> 0 | BN315: ='12'!T315 -> 0 | BO315: =SUM(BC315:BN315) -> 0 | BP315: =SUMIFS($BC315:$BN315,$BC$2:$BN$2,"TRUE") -> 0
J316: ='01'!N316 -> 0 | K316: ='02'!N316 -> 0 | L316: ='03'!N316 -> 0 | M316: ='04'!N316 -> 0 | N316: ='05'!N316 -> 0 | O316: ='06'!N316 -> 0 | P316: ='07'!N316 -> 0 | Q316: ='08'!N316 -> 0 | R316: ='09'!N316 -> 0 | S316: ='10'!N316 -> 0 | T316: ='11'!N316 -> 0 | U316: ='12'!N316 -> 0 | V316: =SUM(J316:U316) -> 0 | W316: =SUMIFS($J316:$U316,$J$2:$U$2,"TRUE") -> 0 | Y316: ='01'!R316 -> 0 | Z316: ='02'!R316 -> 0 | AA316: ='03'!R316 -> 0 | AB316: ='04'!R316 -> 0 | AC316: ='05'!R316 -> 0 | AD316: ='06'!R316 -> 0 | AE316: ='07'!R316 -> 0 | AF316: ='08'!R316 -> 0 | AG316: ='09'!R316 -> 0 | AH316: ='10'!R316 -> 0 | AI316: ='11'!R316 -> 0 | AJ316: ='12'!R316 -> 0 | AK316: =SUM(Y316:AJ316) -> 0 | AL316: =SUMIFS($Y316:$AJ316,$Y$2:$AJ$2,"TRUE") -> 0 | AN316: ='01'!S316 -> 0 | AO316: ='02'!S316 -> 0 | AP316: ='03'!S316 -> 0 | AQ316: ='04'!S316 -> 0 | AR316: ='05'!S316 -> 0 | AS316: ='06'!S316 -> 0 | AT316: ='07'!S316 -> 0 | AU316: ='08'!S316 -> 0 | AV316: ='09'!S316 -> 0 | AW316: ='10'!S316 -> 0 | AX316: ='11'!S316 -> 0 | AY316: ='12'!S316 -> 0 | AZ316: =SUM(AN316:AY316) -> 0 | BA316: =SUMIFS($AN316:$AY316,$AN$2:$AY$2,"TRUE") -> 0 | BC316: ='01'!T316 -> 0 | BD316: ='02'!T316 -> 0 | BE316: ='03'!T316 -> 0 | BF316: ='04'!T316 -> 0 | BG316: ='05'!T316 -> 0 | BH316: ='06'!T316 -> 0 | BI316: ='07'!T316 -> 0 | BJ316: ='08'!T316 -> 0 | BK316: ='09'!T316 -> 0 | BL316: ='10'!T316 -> 0 | BM316: ='11'!T316 -> 0 | BN316: ='12'!T316 -> 0 | BO316: =SUM(BC316:BN316) -> 0 | BP316: =SUMIFS($BC316:$BN316,$BC$2:$BN$2,"TRUE") -> 0
J317: ='01'!N317 -> 0 | K317: ='02'!N317 -> 0 | L317: ='03'!N317 -> 0 | M317: ='04'!N317 -> 0 | N317: ='05'!N317 -> 0 | O317: ='06'!N317 -> 0 | P317: ='07'!N317 -> 0 | Q317: ='08'!N317 -> 0 | R317: ='09'!N317 -> 0 | S317: ='10'!N317 -> 0 | T317: ='11'!N317 -> 0 | U317: ='12'!N317 -> 0 | V317: =SUM(J317:U317) -> 0 | W317: =SUMIFS($J317:$U317,$J$2:$U$2,"TRUE") -> 0 | Y317: ='01'!R317 -> 0 | Z317: ='02'!R317 -> 0 | AA317: ='03'!R317 -> 0 | AB317: ='04'!R317 -> 0 | AC317: ='05'!R317 -> 0 | AD317: ='06'!R317 -> 0 | AE317: ='07'!R317 -> 0 | AF317: ='08'!R317 -> 0 | AG317: ='09'!R317 -> 0 | AH317: ='10'!R317 -> 0 | AI317: ='11'!R317 -> 0 | AJ317: ='12'!R317 -> 0 | AK317: =SUM(Y317:AJ317) -> 0 | AL317: =SUMIFS($Y317:$AJ317,$Y$2:$AJ$2,"TRUE") -> 0 | AN317: ='01'!S317 -> 0 | AO317: ='02'!S317 -> 0 | AP317: ='03'!S317 -> 0 | AQ317: ='04'!S317 -> 0 | AR317: ='05'!S317 -> 0 | AS317: ='06'!S317 -> 0 | AT317: ='07'!S317 -> 0 | AU317: ='08'!S317 -> 0 | AV317: ='09'!S317 -> 0 | AW317: ='10'!S317 -> 0 | AX317: ='11'!S317 -> 0 | AY317: ='12'!S317 -> 0 | AZ317: =SUM(AN317:AY317) -> 0 | BA317: =SUMIFS($AN317:$AY317,$AN$2:$AY$2,"TRUE") -> 0 | BC317: ='01'!T317 -> 0 | BD317: ='02'!T317 -> 0 | BE317: ='03'!T317 -> 0 | BF317: ='04'!T317 -> 0 | BG317: ='05'!T317 -> 0 | BH317: ='06'!T317 -> 0 | BI317: ='07'!T317 -> 0 | BJ317: ='08'!T317 -> 0 | BK317: ='09'!T317 -> 0 | BL317: ='10'!T317 -> 0 | BM317: ='11'!T317 -> 0 | BN317: ='12'!T317 -> 0 | BO317: =SUM(BC317:BN317) -> 0 | BP317: =SUMIFS($BC317:$BN317,$BC$2:$BN$2,"TRUE") -> 0
J318: ='01'!N318 -> 0 | K318: ='02'!N318 -> 0 | L318: ='03'!N318 -> 0 | M318: ='04'!N318 -> 0 | N318: ='05'!N318 -> 0 | O318: ='06'!N318 -> 0 | P318: ='07'!N318 -> 0 | Q318: ='08'!N318 -> 0 | R318: ='09'!N318 -> 0 | S318: ='10'!N318 -> 0 | T318: ='11'!N318 -> 0 | U318: ='12'!N318 -> 0 | V318: =SUM(J318:U318) -> 0 | W318: =SUMIFS($J318:$U318,$J$2:$U$2,"TRUE") -> 0 | Y318: ='01'!R318 -> 0 | Z318: ='02'!R318 -> 0 | AA318: ='03'!R318 -> 0 | AB318: ='04'!R318 -> 0 | AC318: ='05'!R318 -> 0 | AD318: ='06'!R318 -> 0 | AE318: ='07'!R318 -> 0 | AF318: ='08'!R318 -> 0 | AG318: ='09'!R318 -> 0 | AH318: ='10'!R318 -> 0 | AI318: ='11'!R318 -> 0 | AJ318: ='12'!R318 -> 0 | AK318: =SUM(Y318:AJ318) -> 0 | AL318: =SUMIFS($Y318:$AJ318,$Y$2:$AJ$2,"TRUE") -> 0 | AN318: ='01'!S318 -> 0 | AO318: ='02'!S318 -> 0 | AP318: ='03'!S318 -> 0 | AQ318: ='04'!S318 -> 0 | AR318: ='05'!S318 -> 0 | AS318: ='06'!S318 -> 0 | AT318: ='07'!S318 -> 0 | AU318: ='08'!S318 -> 0 | AV318: ='09'!S318 -> 0 | AW318: ='10'!S318 -> 0 | AX318: ='11'!S318 -> 0 | AY318: ='12'!S318 -> 0 | AZ318: =SUM(AN318:AY318) -> 0 | BA318: =SUMIFS($AN318:$AY318,$AN$2:$AY$2,"TRUE") -> 0 | BC318: ='01'!T318 -> 0 | BD318: ='02'!T318 -> 0 | BE318: ='03'!T318 -> 0 | BF318: ='04'!T318 -> 0 | BG318: ='05'!T318 -> 0 | BH318: ='06'!T318 -> 0 | BI318: ='07'!T318 -> 0 | BJ318: ='08'!T318 -> 0 | BK318: ='09'!T318 -> 0 | BL318: ='10'!T318 -> 0 | BM318: ='11'!T318 -> 0 | BN318: ='12'!T318 -> 0 | BO318: =SUM(BC318:BN318) -> 0 | BP318: =SUMIFS($BC318:$BN318,$BC$2:$BN$2,"TRUE") -> 0
... J394: ='01'!N394 -> 0 | K394: ='02'!N394 -> 0 | L394: ='03'!N394 -> 0 | M394: ='04'!N394 -> 0 | N394: ='05'!N394 -> 0 | O394: ='06'!N394 -> 0 | P394: ='07'!N394 -> 0 | Q394: ='08'!N394 -> 0 | R394: ='09'!N394 -> 0 | S394: ='10'!N394 -> 0 | T394: ='11'!N394 -> 0 | U394: ='12'!N394 -> 0 | V394: =SUM(J394:U394) -> 0 | W394: =SUMIFS($J394:$U394,$J$2:$U$2,"TRUE") -> 0 | Y394: ='01'!R394 -> 0 | Z394: ='02'!R394 -> 0 | AA394: ='03'!R394 -> 0 | AB394: ='04'!R394 -> 0 | AC394: ='05'!R394 -> 0 | AD394: ='06'!R394 -> 0 | AE394: ='07'!R394 -> 0 | AF394: ='08'!R394 -> 0 | AG394: ='09'!R394 -> 0 | AH394: ='10'!R394 -> 0 | AI394: ='11'!R394 -> 0 | AJ394: ='12'!R394 -> 0 | AK394: =SUM(Y394:AJ394) -> 0 | AL394: =SUMIFS($Y394:$AJ394,$Y$2:$AJ$2,"TRUE") -> 0 | AN394: ='01'!S394 -> 0 | AO394: ='02'!S394 -> 0 | AP394: ='03'!S394 -> 0 | AQ394: ='04'!S394 -> 0 | AR394: ='05'!S394 -> 0 | AS394: ='06'!S394 -> 0 | AT394: ='07'!S394 -> 0 | AU394: ='08'!S394 -> 0 | AV394: ='09'!S394 -> 0 | AW394: ='10'!S394 -> 0 | AX394: ='11'!S394 -> 0 | AY394: ='12'!S394 -> 0 | AZ394: =SUM(AN394:AY394) -> 0 | BA394: =SUMIFS($AN394:$AY394,$AN$2:$AY$2,"TRUE") -> 0 | BC394: ='01'!T394 -> 0 | BD394: ='02'!T394 -> 0 | BE394: ='03'!T394 -> 0 | BF394: ='04'!T394 -> 0 | BG394: ='05'!T394 -> 0 | BH394: ='06'!T394 -> 0 | BI394: ='07'!T394 -> 0 | BJ394: ='08'!T394 -> 0 | BK394: ='09'!T394 -> 0 | BL394: ='10'!T394 -> 0 | BM394: ='11'!T394 -> 0 | BN394: ='12'!T394 -> 0 | BO394: =SUM(BC394:BN394) -> 0 | BP394: =SUMIFS($BC394:$BN394,$BC$2:$BN$2,"TRUE") -> 0

Sheet 01
B1: Outlet Rebate Calculation Form
B2: Outlet Name : | C2: =IF(INDEX!C3="","",INDEX!C3) -> Outlet Name | E2: Area : | F2: =IF(INDEX!C9="","",INDEX!C9) -> Area | N2: Vol. (Btls.) | P2: Rebate (%) | R2: Price inc. VAT | S2: Price ex. VAT | T2: Rebate
B3: Legal Name : | C3: =IF(INDEX!C5="","",INDEX!C5) -> Outlet Company Limited | E3: Agent : | F3: =IF(INDEX!C11="","",INDEX!C11) -> Agent name | L3: ALL PRINCIPLE | N3: =SUM(N12:N394) -> 0 | P3: =IFERROR(T3/S3,"") | R3: =SUM(R12:R394) -> 0 | S3: =SUM(S12:S394) -> 0 | T3: =SUM(T12:T394) -> 0
B5: BDE : | C5: =IF(INDEX!C7="","",INDEX!C7) -> Name of BDE | E5: Manager : | F5: =IF(INDEX!C13="","",INDEX!C13) -> Manager Name | L5: Campari | N5: =SUMIFS(N$12:N$394,$C$12:$C$394,$L$5) -> 0 | P5: =IFERROR(T5/S5,"") | R5: =SUMIFS(R$12:R$394,$C$12:$C$394,$L$5) -> 0 | S5: =SUMIFS(S$12:S$394,$C$12:$C$394,$L$5) -> 0 | T5: =SUMIFS(T$12:T$394,$C$12:$C$394,$L$5) -> 0
B7: Type of Contract : | C7: =INDEX!C21 -> Marketing Contract & Yearly Contract | L7: ATT | N7: =SUMIFS($N$12:N394,$W$12:$W$394,"ALCHEMY") -> 0 | P7: =IFERROR(T7/S7,"") | R7: =SUMIFS($R$12:R394,$W$12:$W$394,"ALCHEMY") -> 0 | S7: =SUMIFS($S$12:S394,$W$12:$W$394,"ALCHEMY") -> 0 | T7: =SUMIFS($T$12:T394,$W$12:$W$394,"ALCHEMY") -> 0
B9: Contract Period : | C9: =INDEX!C19 -> 01 Jan 26 - 31 Dec 26 | L9: BBC | N9: =SUMIFS($N$12:N394,$W$12:$W$394,"BBC") -> 0 | P9: =IFERROR(T9/S9,"") | R9: =SUMIFS($R$12:R394,$W$12:$W$394,"BBC") -> 0 | S9: =SUMIFS($S$12:S394,$W$12:$W$394,"BBC") -> 0 | T9: =SUMIFS($T$12:T394,$W$12:$W$394,"BBC") -> 0
B10: Period : | C10: JAN (change if needed)
K11: Input column J or K | N11: Input | R11: =SUBTOTAL(9,R13:R394) -> 0 | S11: =SUBTOTAL(9,S13:S394) -> 0 | T11: =SUBTOTAL(9,T13:T394) -> 0
B12: Code | C12: Principle | D12: Category | E12: Brand | F12: Brand Code | G12: Product | H12: Size | I12: Packing | J12: Wholesaler | K12: Price Inc. VAT | L12: Price Ex. VAT | M12: x | N12: Vol. (Btls.) | O12: x | P12: Rebate (%) | Q12: x | R12: Total Price Inc. VAT | S12: Total Price ex. VAT | T12: Total Rebate | U12: Check | V12: Pay
B13: {=MAPPING!$B$3:$I$490} -> 04-SPWHI-07007491 | C13: TEG | D13: Single Malt Scotch | E13: The Macallan | F13: MAC | G13: The Macallan Sherry Oak 12YO | H13: 700ml | I13: 12 | P13: {=MAPPING!J3:J490} -> 0 | R13: =IF(K13>0,K13*N13,L13*1.07*N13) -> 0 | S13: =ROUND(R13/1.07,2) -> 0 | T13: =IF(U13="Input Price only 1 column","",P13*S13) -> 0 | U13: =IF(AND(K13>0,L13>0),"Input Price only 1 column","OK") -> OK | V13: ='CASH REBATE'!$P$22 -> FALSE | W13: {=MAPPING!$A$3:$A$371} -> ALCHEMY
B14: 04-SPWHI-07017065 | C14: TEG | D14: Single Malt Scotch | E14: The Macallan | F14: MAC | G14: The Macallan Sherry Oak 18YO | H14: 700ml | I14: 6 | P14: 0 | R14: =IF(K14>0,K14*N14,L14*1.07*N14) -> 0 | S14: =ROUND(R14/1.07,2) -> 0 | T14: =IF(U14="Input Price only 1 column","",P14*S14) -> 0 | U14: =IF(AND(K14>0,L14>0),"Input Price only 1 column","OK") -> OK | V14: ='CASH REBATE'!$P$22 -> FALSE | W14: ALCHEMY
B15: 04-SPWHI-07006031 | C15: TEG | D15: Single Malt Scotch | E15: The Macallan | F15: MAC | G15: The Macallan Sherry Oak 25YO | H15: 700ml | I15: 3 | P15: 0 | R15: =IF(K15>0,K15*N15,L15*1.07*N15) -> 0 | S15: =ROUND(R15/1.07,2) -> 0 | T15: =IF(U15="Input Price only 1 column","",P15*S15) -> 0 | U15: =IF(AND(K15>0,L15>0),"Input Price only 1 column","OK") -> OK | V15: ='CASH REBATE'!$P$22 -> FALSE | W15: ALCHEMY
B16: 04-SPWHI-07006048 | C16: TEG | D16: Single Malt Scotch | E16: The Macallan | F16: MAC | G16: The Macallan Sherry Oak 30YO | H16: 700ml | I16: 3 | P16: 0 | R16: =IF(K16>0,K16*N16,L16*1.07*N16) -> 0 | S16: =ROUND(R16/1.07,2) -> 0 | T16: =IF(U16="Input Price only 1 column","",P16*S16) -> 0 | U16: =IF(AND(K16>0,L16>0),"Input Price only 1 column","OK") -> OK | V16: ='CASH REBATE'!$P$22 -> FALSE | W16: ALCHEMY
B17: 04-SPWHI-07003009 | C17: TEG | D17: Single Malt Scotch | E17: The Macallan | F17: MAC | G17: The Macallan Double Cask 12YO | H17: 700ml | I17: 12 | P17: 0 | R17: =IF(K17>0,K17*N17,L17*1.07*N17) -> 0 | S17: =ROUND(R17/1.07,2) -> 0 | T17: =IF(U17="Input Price only 1 column","",P17*S17) -> 0 | U17: =IF(AND(K17>0,L17>0),"Input Price only 1 column","OK") -> OK | V17: ='CASH REBATE'!$P$22 -> FALSE | W17: ALCHEMY
B18: 04-SPWHI-07007700 | C18: TEG | D18: Single Malt Scotch | E18: The Macallan | F18: MAC | G18: The Macallan Double Cask 15YO | H18: 700ml | I18: 6 | P18: 0 | R18: =IF(K18>0,K18*N18,L18*1.07*N18) -> 0 | S18: =ROUND(R18/1.07,2) -> 0 | T18: =IF(U18="Input Price only 1 column","",P18*S18) -> 0 | U18: =IF(AND(K18>0,L18>0),"Input Price only 1 column","OK") -> OK | V18: ='CASH REBATE'!$P$22 -> FALSE | W18: ALCHEMY
B19: 04-SPWHI-07009254 | C19: TEG | D19: Single Malt Scotch | E19: The Macallan | F19: MAC | G19: The Macallan Double Cask 18YO | H19: 700ml | I19: 6 | P19: 0 | R19: =IF(K19>0,K19*N19,L19*1.07*N19) -> 0 | S19: =ROUND(R19/1.07,2) -> 0 | T19: =IF(U19="Input Price only 1 column","",P19*S19) -> 0 | U19: =IF(AND(K19>0,L19>0),"Input Price only 1 column","OK") -> OK | V19: ='CASH REBATE'!$P$22 -> FALSE | W19: ALCHEMY
B20: 04-SPWHI-07000311 | C20: TEG | D20: Single Malt Scotch | E20: The Macallan | F20: MAC | G20: The Macallan Double Cask 30YO | H20: 700ml | I20: 3 | P20: 0 | R20: =IF(K20>0,K20*N20,L20*1.07*N20) -> 0 | S20: =ROUND(R20/1.07,2) -> 0 | T20: =IF(U20="Input Price only 1 column","",P20*S20) -> 0 | U20: =IF(AND(K20>0,L20>0),"Input Price only 1 column","OK") -> OK | V20: ='CASH REBATE'!$P$22 -> FALSE | W20: ALCHEMY
B21: 04-SPWHI-07000796 | C21: TEG | D21: Single Malt Scotch | E21: The Macallan | F21: MAC | G21: The Macallan Triple Cask 12YO | H21: 700ml | I21: 12 | P21: 0 | R21: =IF(K21>0,K21*N21,L21*1.07*N21) -> 0 | S21: =ROUND(R21/1.07,2) -> 0 | T21: =IF(U21="Input Price only 1 column","",P21*S21) -> 0 | U21: =IF(AND(K21>0,L21>0),"Input Price only 1 column","OK") -> OK | V21: ='CASH REBATE'!$P$22 -> FALSE | W21: ALCHEMY
B22: 04-24HMN-07002650 | C22: TEG | D22: Single Malt Scotch | E22: The Macallan | F22: MAC | G22: The Macallan Harmony Vibrant Oak | H22: 700ml | I22: 6 | P22: 0 | R22: =IF(K22>0,K22*N22,L22*1.07*N22) -> 0 | S22: =ROUND(R22/1.07,2) -> 0 | T22: =IF(U22="Input Price only 1 column","",P22*S22) -> 0 | U22: =IF(AND(K22>0,L22>0),"Input Price only 1 column","OK") -> OK | V22: ='CASH REBATE'!$P$22 -> FALSE | W22: ALCHEMY
B23: 04-23WHI-07002322 | C23: TEG | D23: Single Malt Scotch | E23: The Macallan | F23: MAC | G23: The Macallan Harmony Collection Amber Meadow | H23: 700ml | I23: 12 | P23: 0 | R23: =IF(K23>0,K23*N23,L23*1.07*N23) -> 0 | S23: =ROUND(R23/1.07,2) -> 0 | T23: =IF(U23="Input Price only 1 column","",P23*S23) -> 0 | U23: =IF(AND(K23>0,L23>0),"Input Price only 1 column","OK") -> OK | V23: ='CASH REBATE'!$P$22 -> FALSE | W23: ALCHEMY
B24: 04-SPWHI-07000557 | C24: TEG | D24: Single Malt Scotch | E24: The Macallan | F24: MAC | G24: The Macallan Harmony Collection | H24: 700ml | I24: 6 | P24: 0 | R24: =IF(K24>0,K24*N24,L24*1.07*N24) -> 0 | S24: =ROUND(R24/1.07,2) -> 0 | T24: =IF(U24="Input Price only 1 column","",P24*S24) -> 0 | U24: =IF(AND(K24>0,L24>0),"Input Price only 1 column","OK") -> OK | V24: ='CASH REBATE'!$P$22 -> FALSE | W24: ALCHEMY
B25: 04-SPWHI-07001226 | C25: TEG | D25: Single Malt Scotch | E25: The Macallan | F25: MAC | G25: The Macallan Harmony Collection Intense Arabica | H25: 700ml | I25: 6 | P25: 0 | R25: =IF(K25>0,K25*N25,L25*1.07*N25) -> 0 | S25: =ROUND(R25/1.07,2) -> 0 | T25: =IF(U25="Input Price only 1 column","",P25*S25) -> 0 | U25: =IF(AND(K25>0,L25>0),"Input Price only 1 column","OK") -> OK | V25: ='CASH REBATE'!$P$22 -> FALSE | W25: ALCHEMY
... B337: 29-SPGIN-07006351 | C337: Remy Cointreau | D337: Gin | E337: Botanist | F337: BOT | G337: The Botanist Islay Dry Gin (Gift Box) | H337: 700ml | I337: 4 | P337: 0 | R337: =IF(K337>0,K337*N337,L337*1.07*N337) -> 0 | S337: =ROUND(R337/1.07,2) -> 0 | T337: =IF(U337="Input Price only 1 column","",P337*S337) -> 0 | U337: =IF(AND(K337>0,L337>0),"Input Price only 1 column","OK") -> OK | V337: ='CASH REBATE'!$P$22 -> FALSE | W337: ALCHEMY
B338: 31-SPMIX-1450PACK | C338: Campari | D338: Liqueur | E338: Aperol/Cinzano | G338: Aperol + Cinzano Prosecco | H338: 1450ml | I338: 3 | P338: 0 | R338: =IF(K338>0,K338*N338,L338*1.07*N338) -> 0 | S338: =ROUND(R338/1.07,2) -> 0 | T338: =IF(U338="Input Price only 1 column","",P338*S338) -> 0 | U338: =IF(AND(K338>0,L338>0),"Input Price only 1 column","OK") -> OK | V338: ='CASH REBATE'!$P$22 -> FALSE | W338: ALCHEMY
B339: 31-SPPAC-07000575 | C339: Campari | D339: Liqueur | E339: Aperol | F339: APR | G339: Aperol Glass Set | H339: 700ml | I339: 5 | P339: 0 | R339: =IF(K339>0,K339*N339,L339*1.07*N339) -> 0 | S339: =ROUND(R339/1.07,2) -> 0 | T339: =IF(U339="Input Price only 1 column","",P339*S339) -> 0 | U339: =IF(AND(K339>0,L339>0),"Input Price only 1 column","OK") -> OK | V339: ='CASH REBATE'!$P$22 -> FALSE | W339: ALCHEMY
B340: 32-06LIQ-05001051 | C340: Campari | D340: Liqueur | E340: Campari | F340: CAM | G340: Campari Negroni Liqueur | H340: 500ml | I340: 6 | P340: 0 | R340: =IF(K340>0,K340*N340,L340*1.07*N340) -> 0 | S340: =ROUND(R340/1.07,2) -> 0 | T340: =IF(U340="Input Price only 1 column","",P340*S340) -> 0 | U340: =IF(AND(K340>0,L340>0),"Input Price only 1 column","OK") -> OK | V340: ='CASH REBATE'!$P$22 -> FALSE | W340: ALCHEMY
B341: 32-06LIQ-07501402 | C341: Campari | D341: Liqueur | E341: Campari | F341: CAM | G341: Campari Bitter 750 ml | H341: 750ml | I341: 6 | P341: 0 | R341: =IF(K341>0,K341*N341,L341*1.07*N341) -> 0 | S341: =ROUND(R341/1.07,2) -> 0 | T341: =IF(U341="Input Price only 1 column","",P341*S341) -> 0 | U341: =IF(AND(K341>0,L341>0),"Input Price only 1 column","OK") -> OK | V341: ='CASH REBATE'!$P$22 -> FALSE | W341: ALCHEMY
B342: 32-SPPAC-07509002 | C342: Campari | D342: Liqueur | E342: Campari | F342: CAM | G342: Campari Negroni Set | H342: 2250ml | I342: 4 | P342: 0 | R342: =IF(K342>0,K342*N342,L342*1.07*N342) -> 0 | S342: =ROUND(R342/1.07,2) -> 0 | T342: =IF(U342="Input Price only 1 column","",P342*S342) -> 0 | U342: =IF(AND(K342>0,L342>0),"Input Price only 1 column","OK") -> OK | V342: ='CASH REBATE'!$P$22 -> FALSE | W342: ALCHEMY
B343: 33-SPGIN-07502000 | C343: Campari | D343: Gin | E343: Bulldog | F343: BUL | G343: Bulldog London Dry Gin 750 ml | H343: 750ml | I343: 6 | P343: 0 | R343: =IF(K343>0,K343*N343,L343*1.07*N343) -> 0 | S343: =ROUND(R343/1.07,2) -> 0 | T343: =IF(U343="Input Price only 1 column","",P343*S343) -> 0 | U343: =IF(AND(K343>0,L343>0),"Input Price only 1 column","OK") -> OK | V343: ='CASH REBATE'!$P$22 -> FALSE | W343: ALCHEMY
B344: 33-SPPAC-07506102 | C344: Campari | D344: Gin | E344: Bulldog | F344: BUL | G344: Bulldog Gin Glass Set | H344: 750ml | I344: 6 | P344: 0 | R344: =IF(K344>0,K344*N344,L344*1.07*N344) -> 0 | S344: =ROUND(R344/1.07,2) -> 0 | T344: =IF(U344="Input Price only 1 column","",P344*S344) -> 0 | U344: =IF(AND(K344>0,L344>0),"Input Price only 1 column","OK") -> OK | V344: ='CASH REBATE'!$P$22 -> FALSE | W344: ALCHEMY
B345: 34-12VOD-01808261 | C345: Campari | D345: Vodka | E345: Skyy | F345: SKY | G345: Skyy Vodka 180 ml (P12) | H345: 180ml | I345: 12 | P345: 0 | R345: =IF(K345>0,K345*N345,L345*1.07*N345) -> 0 | S345: =ROUND(R345/1.07,2) -> 0 | T345: =IF(U345="Input Price only 1 column","",P345*S345) -> 0 | U345: =IF(AND(K345>0,L345>0),"Input Price only 1 column","OK") -> OK | V345: ='CASH REBATE'!$P$22 -> FALSE | W345: ALCHEMY
B346: 34-SPVOD-07007004 | C346: Campari | D346: Vodka | E346: Skyy | F346: SKY | G346: Skyy Vodka | H346: 700ml | I346: 12 | P346: 0 | R346: =IF(K346>0,K346*N346,L346*1.07*N346) -> 0 | S346: =ROUND(R346/1.07,2) -> 0 | T346: =IF(U346="Input Price only 1 column","",P346*S346) -> 0 | U346: =IF(AND(K346>0,L346>0),"Input Price only 1 column","OK") -> OK | V346: ='CASH REBATE'!$P$22 -> FALSE | W346: ALCHEMY
B347: 37-SPWHI-07002834 | C347: Campari | D347: Whisky | E347: Wild Turkey | F347: WTK | G347: Wild Turkey Rye Whiskey 700ml | H347: 700ml | I347: 12 | P347: 0 | R347: =IF(K347>0,K347*N347,L347*1.07*N347) -> 0 | S347: =ROUND(R347/1.07,2) -> 0 | T347: =IF(U347="Input Price only 1 column","",P347*S347) -> 0 | U347: =IF(AND(K347>0,L347>0),"Input Price only 1 column","OK") -> OK | V347: ='CASH REBATE'!$P$22 -> FALSE | W347: ALCHEMY
B348: 40-SPRUM-07501400 | C348: Campari | D348: Rum | E348: Appleton | F348: APT | G348: Appleton Estate Rare Blend 12 Years | H348: 750ml | I348: 12 | P348: 0 | R348: =IF(K348>0,K348*N348,L348*1.07*N348) -> 0 | S348: =ROUND(R348/1.07,2) -> 0 | T348: =IF(U348="Input Price only 1 column","",P348*S348) -> 0 | U348: =IF(AND(K348>0,L348>0),"Input Price only 1 column","OK") -> OK | V348: ='CASH REBATE'!$P$22 -> FALSE | W348: ALCHEMY
B349: 46-ABRGP-07000051 | C349: Campari | D349: Whisky | E349: Glen Grant | F349: GGT | G349: Glen Grant Single Malt Scotch Whisky Arboralis (Gift Pack) | H349: 700ml | I349: 6 | P349: 0 | R349: =IF(K349>0,K349*N349,L349*1.07*N349) -> 0 | S349: =ROUND(R349/1.07,2) -> 0 | T349: =IF(U349="Input Price only 1 column","",P349*S349) -> 0 | U349: =IF(AND(K349>0,L349>0),"Input Price only 1 column","OK") -> OK | V349: ='CASH REBATE'!$P$22 -> FALSE | W349: ALCHEMY
B350: 51-WISPA-07505015 | C350: Luc Belaire | D350: Sparkling Wine | E350: Luc Belaire | F350: LUC | G350: Luc Belaire Rare Luxe | H350: 750ml | I350: 6 | P350: 0 | R350: =IF(K350>0,K350*N350,L350*1.07*N350) -> 0 | S350: =ROUND(R350/1.07,2) -> 0 | T350: =IF(U350="Input Price only 1 column","",P350*S350) -> 0 | U350: =IF(AND(K350>0,L350>0),"Input Price only 1 column","OK") -> OK | V350: ='CASH REBATE'!$P$22 -> FALSE | W350: ALCHEMY
... B368: 75-06WHI-07007038 | C368: Vok | D368: Whisky | E368: Real Mccoy | F368: RMC | G368: Real Mccoy Bourbon Whiskey | H368: 700ml | I368: 6 | P368: 0 | R368: =IF(K368>0,K368*N368,L368*1.07*N368) -> 0 | S368: =ROUND(R368/1.07,2) -> 0 | T368: =IF(U368="Input Price only 1 column","",P368*S368) -> 0 | U368: =IF(AND(K368>0,L368>0),"Input Price only 1 column","OK") -> OK | V368: ='CASH REBATE'!$P$22 -> FALSE | W368: ALCHEMY
B369: 76-SPSHE-05001041 | C369: Edrington | D369: Wine | E369: Valdespino | G369: Valdespino Don Gonzalo Oloroso Sherry Wine | H369: 500ml | I369: 6 | P369: 0 | R369: =IF(K369>0,K369*N369,L369*1.07*N369) -> 0 | S369: =ROUND(R369/1.07,2) -> 0 | T369: =IF(U369="Input Price only 1 column","",P369*S369) -> 0 | U369: =IF(AND(K369>0,L369>0),"Input Price only 1 column","OK") -> OK | V369: ='CASH REBATE'!$P$22 -> FALSE | W369: ALCHEMY
B370: 76-SPSHE-07500938 | C370: Edrington | D370: Wine | E370: Valdespino | G370: Valdespino El Candado PX Sherry Wine | H370: 700ml | I370: 6 | P370: 0 | R370: =IF(K370>0,K370*N370,L370*1.07*N370) -> 0 | S370: =ROUND(R370/1.07,2) -> 0 | T370: =IF(U370="Input Price only 1 column","",P370*S370) -> 0 | U370: =IF(AND(K370>0,L370>0),"Input Price only 1 column","OK") -> OK | V370: ='CASH REBATE'!$P$22 -> FALSE | W370: ALCHEMY
B371: 76-SPVER-07500174 | C371: Edrington | D371: Vermouth | E371: Valdespino | G371: Valdespino Vermouth | H371: 700ml | I371: 6 | P371: 0 | R371: =IF(K371>0,K371*N371,L371*1.07*N371) -> 0 | S371: =ROUND(R371/1.07,2) -> 0 | T371: =IF(U371="Input Price only 1 column","",P371*S371) -> 0 | U371: =IF(AND(K371>0,L371>0),"Input Price only 1 column","OK") -> OK | V371: ='CASH REBATE'!$P$22 -> FALSE | W371: ALCHEMY
B372: 42-SPVER-10000853 | C372: Campari | D372: Vermouth | E372: Cinzano | F372: CZV | G372: CINZANO VERMOUTH EXTRA DRY 1L | H372: 1000ml | I372: 12 | P372: 0 | R372: =IF(K372>0,K372*N372,L372*1.07*N372) -> 0 | S372: =ROUND(R372/1.07,2) -> 0 | T372: =IF(U372="Input Price only 1 column","",P372*S372) -> 0 | U372: =IF(AND(K372>0,L372>0),"Input Price only 1 column","OK") -> OK | V372: ='CASH REBATE'!$P$22 -> FALSE | W372: ALCHEMY
B373: 52-WISPB-07503811 | C373: Pommery | D373: Champagne | E373: Pommery | F373: POM | G373: Champagne Heidsieck Monopole Blue Top Brut | H373: 750ml | I373: 6 | P373: 0 | R373: =IF(K373>0,K373*N373,L373*1.07*N373) -> 0 | S373: =ROUND(R373/1.07,2) -> 0 | T373: =IF(U373="Input Price only 1 column","",P373*S373) -> 0 | U373: =IF(AND(K373>0,L373>0),"Input Price only 1 column","OK") -> OK | V373: ='CASH REBATE'!$P$22 -> FALSE | W373: ALCHEMY
B374: 24-26CNY-07000401 | C374: Remy Cointreau | D374: Cognac | E374: Remy | F374: RMM | G374: Louis XIII CNY26 | H374: 700ml | I374: 1 | P374: 0 | R374: =IF(K374>0,K374*N374,L374*1.07*N374) -> 0 | S374: =ROUND(R374/1.07,2) -> 0 | T374: =IF(U374="Input Price only 1 column","",P374*S374) -> 0 | U374: =IF(AND(K374>0,L374>0),"Input Price only 1 column","OK") -> OK | V374: ='CASH REBATE'!$P$22 -> FALSE | W374: ALCHEMY
B375: 42-SPVER-10000822 | C375: Campari | D375: Vermouth | E375: Cinzano | F375: CZV | G375: Cinzano Bianco Vermouth | H375: 1000ml | I375: 12 | P375: 0 | R375: =IF(K375>0,K375*N375,L375*1.07*N375) -> 0 | S375: =ROUND(R375/1.07,2) -> 0 | T375: =IF(U375="Input Price only 1 column","",P375*S375) -> 0 | U375: =IF(AND(K375>0,L375>0),"Input Price only 1 column","OK") -> OK | V375: ='CASH REBATE'!$P$22 -> FALSE | W375: ALCHEMY
B376: 76-SPVER-07502857 | C376: Edrington | D376: Vermouth | E376: Valdespino | G376: VALDESPINO ORIGEN VERMOUTH 15% 0.75L | H376: 750ml | I376: 6 | P376: 0 | R376: =IF(K376>0,K376*N376,L376*1.07*N376) -> 0 | S376: =ROUND(R376/1.07,2) -> 0 | T376: =IF(U376="Input Price only 1 column","",P376*S376) -> 0 | U376: =IF(AND(K376>0,L376>0),"Input Price only 1 column","OK") -> OK | V376: ='CASH REBATE'!$P$22 -> FALSE | W376: ALCHEMY
B377: 103LOWHI-10000617 | C377: LOCH LOMOND GROUP | D377: WHISKY | E377: HIGH COMMISSIONER | G377: HIGH COMMISSIONER BLENDED 40% 12x1L | H377: 1000ml | I377: 12 | P377: 0 | R377: =IF(K377>0,K377*N377,L377*1.07*N377) -> 0 | S377: =ROUND(R377/1.07,2) -> 0 | T377: =IF(U377="Input Price only 1 column","",P377*S377) -> 0 | U377: =IF(AND(K377>0,L377>0),"Input Price only 1 column","OK") -> OK | V377: ='CASH REBATE'!$P$22 -> FALSE | W377: ALCHEMY
B378: 103LOWHI-07000211 | C378: LOCH LOMOND GROUP | D378: WHISKY | E378: HIGH COMMISSIONER | G378: HIGH COMMISSIONER BLENDED 40% 12x0.7L | H378: 700ml | I378: 12 | P378: 0 | R378: =IF(K378>0,K378*N378,L378*1.07*N378) -> 0 | S378: =ROUND(R378/1.07,2) -> 0 | T378: =IF(U378="Input Price only 1 column","",P378*S378) -> 0 | U378: =IF(AND(K378>0,L378>0),"Input Price only 1 column","OK") -> OK | V378: ='CASH REBATE'!$P$22 -> FALSE | W378: ALCHEMY
B379: 103LOWHI-03500129 | C379: LOCH LOMOND GROUP | D379: WHISKY | E379: HIGH COMMISSIONER | G379: HIGH COMMISSIONER BLENDED 40% 24x0.35L | H379: 350ml | I379: 24 | P379: 0 | R379: =IF(K379>0,K379*N379,L379*1.07*N379) -> 0 | S379: =ROUND(R379/1.07,2) -> 0 | T379: =IF(U379="Input Price only 1 column","",P379*S379) -> 0 | U379: =IF(AND(K379>0,L379>0),"Input Price only 1 column","OK") -> OK | V379: ='CASH REBATE'!$P$22 -> FALSE | W379: ALCHEMY
B380: 103LOWHI-02000068 | C380: LOCH LOMOND GROUP | D380: WHISKY | E380: HIGH COMMISSIONER | G380: HIGH COMMISSIONER BLENDED 40% 48x0.2L | H380: 200ml | I380: 48 | P380: 0 | R380: =IF(K380>0,K380*N380,L380*1.07*N380) -> 0 | S380: =ROUND(R380/1.07,2) -> 0 | T380: =IF(U380="Input Price only 1 column","",P380*S380) -> 0 | U380: =IF(AND(K380>0,L380>0),"Input Price only 1 column","OK") -> OK | V380: ='CASH REBATE'!$P$22 -> FALSE | W380: ALCHEMY
B381: 106LOWHI-07003219 | C381: LOCH LOMOND GROUP | D381: WHISKY | E381: LOCH LOMOND | G381: LOCH LOMOND ORIGINAL SCOTCH WHISKY | H381: 700ml | I381: 6 | P381: 0 | R381: =IF(K381>0,K381*N381,L381*1.07*N381) -> 0 | S381: =ROUND(R381/1.07,2) -> 0 | T381: =IF(U381="Input Price only 1 column","",P381*S381) -> 0 | U381: =IF(AND(K381>0,L381>0),"Input Price only 1 column","OK") -> OK | V381: ='CASH REBATE'!$P$22 -> FALSE | W381: ALCHEMY
B382: 106LOWHI-07007216 | C382: LOCH LOMOND GROUP | D382: WHISKY | E382: LOCH LOMOND | G382: LOCH LOMOND AGED 12 YEARS SCOTCH WHISKY | H382: 700ml | I382: 6 | P382: 0 | R382: =IF(K382>0,K382*N382,L382*1.07*N382) -> 0 | S382: =ROUND(R382/1.07,2) -> 0 | T382: =IF(U382="Input Price only 1 column","",P382*S382) -> 0 | U382: =IF(AND(K382>0,L382>0),"Input Price only 1 column","OK") -> OK | V382: ='CASH REBATE'!$P$22 -> FALSE
B383: 106LOWHI-07009215 | C383: LOCH LOMOND GROUP | D383: WHISKY | E383: LOCH LOMOND | G383: LOCH LOMOND AGED 18 YEARS SCOTCH WHISKY | H383: 700ml | I383: 6 | P383: 0 | R383: =IF(K383>0,K383*N383,L383*1.07*N383) -> 0 | S383: =ROUND(R383/1.07,2) -> 0 | T383: =IF(U383="Input Price only 1 column","",P383*S383) -> 0 | U383: =IF(AND(K383>0,L383>0),"Input Price only 1 column","OK") -> OK | V383: ='CASH REBATE'!$P$22 -> FALSE
B384: 04-SPWHI-07001257 | C384: Edrington | D384: WHISKY | E384: The Macallan | F384: MAC | G384: THE MACALLAN LITHA WHISKY | H384: 700ml | I384: 6 | P384: 0 | R384: =IF(K384>0,K384*N384,L384*1.07*N384) -> 0 | S384: =ROUND(R384/1.07,2) -> 0 | T384: =IF(U384="Input Price only 1 column","",P384*S384) -> 0 | U384: =IF(AND(K384>0,L384>0),"Input Price only 1 column","OK") -> OK | V384: ='CASH REBATE'!$P$22 -> FALSE
B385: 42-SPVER-10000061 | C385: Campari Group | D385: Vermouth | E385: Del Professore | G385: Del Professore Rosso Vermouth | H385: 1000ml | I385: 6 | P385: 0 | R385: =IF(K385>0,K385*N385,L385*1.07*N385) -> 0 | S385: =ROUND(R385/1.07,2) -> 0 | T385: =IF(U385="Input Price only 1 column","",P385*S385) -> 0 | U385: =IF(AND(K385>0,L385>0),"Input Price only 1 column","OK") -> OK | V385: ='CASH REBATE'!$P$22 -> FALSE
B386: 42-WISPA-07503171 | C386: Campari Group | D386: Sparkling Wine | E386: Riccadonna | G386: Riccadonna To Spritz | H386: 750ml | I386: 6 | P386: 0 | R386: =IF(K386>0,K386*N386,L386*1.07*N386) -> 0 | S386: =ROUND(R386/1.07,2) -> 0 | T386: =IF(U386="Input Price only 1 column","",P386*S386) -> 0 | U386: =IF(AND(K386>0,L386>0),"Input Price only 1 column","OK") -> OK | V386: ='CASH REBATE'!$P$22 -> FALSE
B387: 57-SPLIQ-07000707 | C387: Campari | D387: Liqueur | E387: Ouzo | F387: OUZ | G387: Ouzo 12 Liqueur | H387: 700ml | I387: 6 | P387: 0 | R387: =IF(K387>0,K387*N387,L387*1.07*N387) -> 0 | S387: =ROUND(R387/1.07,2) -> 0 | T387: =IF(U387="Input Price only 1 column","",P387*S387) -> 0 | U387: =IF(AND(K387>0,L387>0),"Input Price only 1 column","OK") -> OK | V387: ='CASH REBATE'!$P$22 -> FALSE
B388: 58-SPLIQ-07009164 | C388: Ancho | D388: Liqueur | E388: Ancho | F388: BRC | G388: Ancho Reyes Verde Liqueur | H388: 700ml | I388: 6 | P388: 0 | R388: =IF(K388>0,K388*N388,L388*1.07*N388) -> 0 | S388: =ROUND(R388/1.07,2) -> 0 | T388: =IF(U388="Input Price only 1 column","",P388*S388) -> 0 | U388: =IF(AND(K388>0,L388>0),"Input Price only 1 column","OK") -> OK | V388: ='CASH REBATE'!$P$22 -> FALSE
B389: 66-SPGIN-07000064 | C389: Bareksten | D389: Gin | E389: Bareksten | F389: BAR | G389: Bareksten Botanical Gin | H389: 700ml | I389: 6 | P389: 0 | R389: =IF(K389>0,K389*N389,L389*1.07*N389) -> 0 | S389: =ROUND(R389/1.07,2) -> 0 | T389: =IF(U389="Input Price only 1 column","",P389*S389) -> 0 | U389: =IF(AND(K389>0,L389>0),"Input Price only 1 column","OK") -> OK | V389: ='CASH REBATE'!$P$22 -> FALSE
B390: 84-SPLIQ-07500002 | C390: BIGGAR & LEITH | D390: Liqueur | E390: BIGGAR & LEITH | F390: BGL | G390: Hotel Starlino Aperitivo Orange | H390: 750ml | I390: 6 | P390: 0 | R390: =IF(K390>0,K390*N390,L390*1.07*N390) -> 0 | S390: =ROUND(R390/1.07,2) -> 0 | T390: =IF(U390="Input Price only 1 column","",P390*S390) -> 0 | U390: =IF(AND(K390>0,L390>0),"Input Price only 1 column","OK") -> OK | V390: ='CASH REBATE'!$P$22 -> FALSE
B391: 84-SPLIQ-07500003 | C391: BIGGAR & LEITH | D391: Liqueur | E391: BIGGAR & LEITH | F391: BGL | G391: Hotel Starlino Aperitivo Rose | H391: 750ml | I391: 6 | P391: 0 | R391: =IF(K391>0,K391*N391,L391*1.07*N391) -> 0 | S391: =ROUND(R391/1.07,2) -> 0 | T391: =IF(U391="Input Price only 1 column","",P391*S391) -> 0 | U391: =IF(AND(K391>0,L391>0),"Input Price only 1 column","OK") -> OK | V391: ='CASH REBATE'!$P$22 -> FALSE
B392: 84-SPVER-07500001 | C392: BIGGAR & LEITH | D392: Vermouth | E392: BIGGAR & LEITH | F392: BGL | G392: Hotel Starlino Vermouth Rosso | H392: 750ml | I392: 6 | P392: 0 | R392: =IF(K392>0,K392*N392,L392*1.07*N392) -> 0 | S392: =ROUND(R392/1.07,2) -> 0 | T392: =IF(U392="Input Price only 1 column","",P392*S392) -> 0 | U392: =IF(AND(K392>0,L392>0),"Input Price only 1 column","OK") -> OK | V392: ='CASH REBATE'!$P$22 -> FALSE
B393: 85-SPLIQ-07000001 | C393: BIGGAR & LEITH | D393: Liqueur | E393: BIGGAR & LEITH | F393: BGL | G393: Shanky'S Whip Liqueur And Whisky Blend | H393: 700ml | I393: 6 | P393: 0 | R393: =IF(K393>0,K393*N393,L393*1.07*N393) -> 0 | S393: =ROUND(R393/1.07,2) -> 0 | T393: =IF(U393="Input Price only 1 column","",P393*S393) -> 0 | U393: =IF(AND(K393>0,L393>0),"Input Price only 1 column","OK") -> OK | V393: ='CASH REBATE'!$P$22 -> FALSE
B394: 86-SPLIQ-07000001 | C394: BIGGAR & LEITH | D394: Liqueur | E394: BIGGAR & LEITH | F394: BGL | G394: Stambecco Amaro Maraschino Liqueur | H394: 700ml | I394: 6 | P394: 0 | R394: =IF(K394>0,K394*N394,L394*1.07*N394) -> 0 | S394: =ROUND(R394/1.07,2) -> 0 | T394: =IF(U394="Input Price only 1 column","",P394*S394) -> 0 | U394: =IF(AND(K394>0,L394>0),"Input Price only 1 column","OK") -> OK | V394: ='CASH REBATE'!$P$22 -> FALSE
B395: 84-SPLIQ-07500852 | C395: BIGGAR & LEITH | D395: Liqueur | E395: BIGGAR & LEITH | F395: BGL | G395: Hotel Starlino Aperitivo Elderflower | H395: 750ml | I395: 6 | P395: 0
B396: GL-01WHI-07000203 | C396: BIGGAR & LEITH | D396: Whisky | E396: BIGGAR & LEITH | F396: BGL | G396: The Gladstone Axe American Oak Whisky | H396: 700ml | I396: 6 | P396: 0
B397: BU-03TEQ-05000371 | C397: BIGGAR & LEITH | D397: Tequila | E397: BIGGAR & LEITH | F397: BGL | G397: Butterfly Cannon Rosa Tequila 0.5L | H397: 500ml | I397: 6 | P397: 0
B398: BU-02TEQ-05000296 | C398: BIGGAR & LEITH | D398: Tequila | E398: BIGGAR & LEITH | F398: BGL | G398: Butterfly Cannon Cristalino Tequila 0.5L | H398: 500ml | I398: 6 | P398: 0
B399: SP-01RUM-07006059 | C399: Biggar & Leith | D399: Rum | E399: Biggar & Leith | F399: BGL | G399: Spytail Ginger Rum 0.7L | H399: 700ml | I399: 6 | P399: 0
B400: ST-01LIQ-07001224 | C400: BIGGAR & LEITH | D400: Liqueur | E400: BIGGAR & LEITH | F400: BGL | G400: Stambecco Tiramisu Liqueur 0.7L | H400: 700ml | I400: 6 | P400: 0
B401: BU-01TEQ-05000333 | C401: BIGGAR & LEITH | D401: Tequila | E401: BIGGAR & LEITH | F401: BGL | G401: Butterfly Cannon Blue Tequila 0.5L | H401: 500ml | I401: 6 | P401: 0
B402: 77-SPLIQ-10001617 | C402: Branca | D402: Liqueur | E402: Branca | F402: BRC | G402: Borghetti Espresso Liqueur | H402: 1000ml | I402: 6 | P402: 0
B403: 58-SPLIQ-07009065 | C403: Campari | D403: Liqueur | E403: Campari | F403: CAM | G403: Ancho Reyes Liqueur | H403: 700ml | I403: 6 | P403: 0
B404: 60-SPGIN-07000522 | C404: Campari | D404: Gin | E404: Campari | F404: CAM | G404: Ondina Gin | H404: 700ml | I404: 6 | P404: 0
B405: 55-SPMEZ-07502893 | C405: Clase Azul | D405: Mezcal | E405: Clase Azul | F405: CAZ | G405: Mezcal Clase Azul Durango | H405: 750ml | I405: 3 | P405: 0
B406: 55-SPTEQ-07504724 | C406: Clase Azul | D406: Tequila | E406: Clase Azul | F406: CAZ | G406: Tequila Clase Azul Anejo | H406: 750ml | I406: 3 | P406: 0
... B488: 99-SL001-07000013 | C488: BRANCA | D488: BITTER | E488: Fernet | F488: BRC | G488: Fernet Branca Bitters 700ml | H488: 700ml | I488: 6 | P488: 0
B489: GL-02WHI-07000241 | C489: BIGGAR & LEITH | D489: WHISKY | E489: The Gladstone | G489: The Gladstone Axe The Black Axe Whisky | H489: 700ml | I489: 6 | P489: 0
B490: SP-02RUM-07006523 | C490: Biggar & Leith | D490: Rum | E490: Spytail | G490: Spytail Cognac Barrel Rum | H490: 700ml | I490: 6 | P490: 0
B491: 80-SPWHI-07001488 | C491: GLENTURRET | D491: WHISKY | E491: Glenturret | F491: GTR | G491: The Glenturret Triple Wood Whisky (2024) | H491: 700ml | I491: 6 | P491: 0
B492: 79-SPGIN-07000392 | C492: LARK | D492: GIN | E492: Forty Spotted | G492: Forty Spotted Pinot Noir | H492: 700ml | I492: 6 | P492: 0
B493: 79-SPWHI-07003577 | C493: LARK | D493: WHISKY | E493: Lark | F493: LRK | G493: LARK NO. 151 FIRE TRAIL WHISKY | H493: 700ml | I493: 6 | P493: 0
B494: 79-SPWHI-07003584 | C494: LARK | D494: WHISKY | E494: Lark | F494: LRK | G494: LARK NO. 183 DEVIL'S STORM WHISKY | H494: 700ml | I494: 6 | P494: 0
B495: 79-SPWHI-07003607 | C495: LARK | D495: WHISKY | E495: Lark | F495: LRK | G495: LARK NO. 285 RUBY ABYSS WHISKY | H495: 700ml | I495: 6 | P495: 0
B496: 106PEWHI-07003015 | C496: PENDULUM | D496: WHISKY | E496: FABLE | G496: FABLE PALE HORSE 8 YEARS SCOTCH WHISKY | H496: 700ml | I496: 6 | P496: 0
B497: 106PEWHI-07002919 | C497: PENDULUM | D497: WHISKY | E497: FABLE | G497: FABLE CHAPTER 8 CANARY 11 YEARS SCOTCH WHISKY | H497: 700ml | I497: 6 | P497: 0
B498: 101SESPA-07500680 | C498: SERENA | D498: Sparkling Wine | E498: PIU | G498: Piu Brioso Vino Spumante Bianco | H498: 750ml | I498: 6 | P498: 0
B499: 101SESPA-07500703 | C499: SERENA | D499: Sparkling Wine | E499: PIU | G499: Piu Brioso Prosecco Valdobbiadene | H499: 750ml | I499: 6 | P499: 0
B500: 101SESPA-07500727 | C500: SERENA | D500: Sparkling Wine | E500: PIU | G500: Piu Brioso Prosecco Rose | H500: 750ml | I500: 6 | P500: 0

Sheet 02
B1: Outlet Rebate Calculation Form
B2: Outlet Name : | C2: =IF(INDEX!C3="","",INDEX!C3) -> Outlet Name | E2: Area : | F2: =IF(INDEX!C9="","",INDEX!C9) -> Area | N2: Vol. (Btls.) | P2: Rebate (%) | R2: Price inc. VAT | S2: Price ex. VAT | T2: Rebate
B3: Legal Name : | C3: =IF(INDEX!C5="","",INDEX!C5) -> Outlet Company Limited | E3: Agent : | F3: =IF(INDEX!C11="","",INDEX!C11) -> Agent name | L3: ALL PRINCIPLE | N3: =SUM(N12:N394) -> 0 | P3: =IFERROR(T3/S3,"") | R3: =SUM(R12:R394) -> 0 | S3: =SUM(S12:S394) -> 0 | T3: =SUM(T12:T394) -> 0
B5: BDE : | C5: =IF(INDEX!C7="","",INDEX!C7) -> Name of BDE | E5: Manager : | F5: =IF(INDEX!C13="","",INDEX!C13) -> Manager Name | L5: Campari | N5: =SUMIFS(N$12:N$394,$C$12:$C$394,$L$5) -> 0 | P5: =IFERROR(T5/S5,"") | R5: =SUMIFS(R$12:R$394,$C$12:$C$394,$L$5) -> 0 | S5: =SUMIFS(S$12:S$394,$C$12:$C$394,$L$5) -> 0 | T5: =SUMIFS(T$12:T$394,$C$12:$C$394,$L$5) -> 0
B7: Type of Contract : | C7: =INDEX!C21 -> Marketing Contract & Yearly Contract | L7: ATT | N7: =SUMIFS($N$12:N394,$W$12:$W$394,"ALCHEMY") -> 0 | P7: =IFERROR(T7/S7,"") | R7: =SUMIFS($R$12:R394,$W$12:$W$394,"ALCHEMY") -> 0 | S7: =SUMIFS($S$12:S394,$W$12:$W$394,"ALCHEMY") -> 0 | T7: =SUMIFS($T$12:T394,$W$12:$W$394,"ALCHEMY") -> 0
B9: Contract Period : | C9: =INDEX!C19 -> 01 Jan 26 - 31 Dec 26 | L9: BBC | N9: =SUMIFS($N$12:N394,$W$12:$W$394,"BBC") -> 0 | P9: =IFERROR(T9/S9,"") | R9: =SUMIFS($R$12:R394,$W$12:$W$394,"BBC") -> 0 | S9: =SUMIFS($S$12:S394,$W$12:$W$394,"BBC") -> 0 | T9: =SUMIFS($T$12:T394,$W$12:$W$394,"BBC") -> 0
B10: Period : | C10: FEB (change if needed)
K11: Input column J or K | N11: Input | R11: =SUBTOTAL(9,R13:R394) -> 0 | S11: =SUBTOTAL(9,S13:S394) -> 0 | T11: =SUBTOTAL(9,T13:T394) -> 0
B12: Code | C12: Principle | D12: Category | E12: Brand | F12: Brand Code | G12: Product | H12: Size | I12: Packing | J12: Wholesaler | K12: Price Inc. VAT | L12: Price Ex. VAT | M12: x | N12: Vol. (Btls.) | O12: x | P12: Rebate (%) | Q12: x | R12: Total Price Inc. VAT | S12: Total Price ex. VAT | T12: Total Rebate | U12: Check | V12: Pay
B13: {=MAPPING!$B$3:$I$490} -> 04-SPWHI-07007491 | C13: TEG | D13: Single Malt Scotch | E13: The Macallan | F13: MAC | G13: The Macallan Sherry Oak 12YO | H13: 700ml | I13: 12 | P13: {=MAPPING!J3:J490} -> 0 | R13: =IF(K13>0,K13*N13,L13*1.07*N13) -> 0 | S13: =ROUND(R13/1.07,2) -> 0 | T13: =IF(U13="Input Price only 1 column","",P13*S13) -> 0 | U13: =IF(AND(K13>0,L13>0),"Input Price only 1 column","OK") -> OK | V13: ='CASH REBATE'!$P$22 -> FALSE | W13: {=MAPPING!$A$3:$A$371} -> ALCHEMY
B14: 04-SPWHI-07017065 | C14: TEG | D14: Single Malt Scotch | E14: The Macallan | F14: MAC | G14: The Macallan Sherry Oak 18YO | H14: 700ml | I14: 6 | P14: 0 | R14: =IF(K14>0,K14*N14,L14*1.07*N14) -> 0 | S14: =ROUND(R14/1.07,2) -> 0 | T14: =IF(U14="Input Price only 1 column","",P14*S14) -> 0 | U14: =IF(AND(K14>0,L14>0),"Input Price only 1 column","OK") -> OK | V14: ='CASH REBATE'!$P$22 -> FALSE | W14: ALCHEMY
B15: 04-SPWHI-07006031 | C15: TEG | D15: Single Malt Scotch | E15: The Macallan | F15: MAC | G15: The Macallan Sherry Oak 25YO | H15: 700ml | I15: 3 | P15: 0 | R15: =IF(K15>0,K15*N15,L15*1.07*N15) -> 0 | S15: =ROUND(R15/1.07,2) -> 0 | T15: =IF(U15="Input Price only 1 column","",P15*S15) -> 0 | U15: =IF(AND(K15>0,L15>0),"Input Price only 1 column","OK") -> OK | V15: ='CASH REBATE'!$P$22 -> FALSE | W15: ALCHEMY
B16: 04-SPWHI-07006048 | C16: TEG | D16: Single Malt Scotch | E16: The Macallan | F16: MAC | G16: The Macallan Sherry Oak 30YO | H16: 700ml | I16: 3 | P16: 0 | R16: =IF(K16>0,K16*N16,L16*1.07*N16) -> 0 | S16: =ROUND(R16/1.07,2) -> 0 | T16: =IF(U16="Input Price only 1 column","",P16*S16) -> 0 | U16: =IF(AND(K16>0,L16>0),"Input Price only 1 column","OK") -> OK | V16: ='CASH REBATE'!$P$22 -> FALSE | W16: ALCHEMY
B17: 04-SPWHI-07003009 | C17: TEG | D17: Single Malt Scotch | E17: The Macallan | F17: MAC | G17: The Macallan Double Cask 12YO | H17: 700ml | I17: 12 | P17: 0 | R17: =IF(K17>0,K17*N17,L17*1.07*N17) -> 0 | S17: =ROUND(R17/1.07,2) -> 0 | T17: =IF(U17="Input Price only 1 column","",P17*S17) -> 0 | U17: =IF(AND(K17>0,L17>0),"Input Price only 1 column","OK") -> OK | V17: ='CASH REBATE'!$P$22 -> FALSE | W17: ALCHEMY
B18: 04-SPWHI-07007700 | C18: TEG | D18: Single Malt Scotch | E18: The Macallan | F18: MAC | G18: The Macallan Double Cask 15YO | H18: 700ml | I18: 6 | P18: 0 | R18: =IF(K18>0,K18*N18,L18*1.07*N18) -> 0 | S18: =ROUND(R18/1.07,2) -> 0 | T18: =IF(U18="Input Price only 1 column","",P18*S18) -> 0 | U18: =IF(AND(K18>0,L18>0),"Input Price only 1 column","OK") -> OK | V18: ='CASH REBATE'!$P$22 -> FALSE | W18: ALCHEMY
B19: 04-SPWHI-07009254 | C19: TEG | D19: Single Malt Scotch | E19: The Macallan | F19: MAC | G19: The Macallan Double Cask 18YO | H19: 700ml | I19: 6 | P19: 0 | R19: =IF(K19>0,K19*N19,L19*1.07*N19) -> 0 | S19: =ROUND(R19/1.07,2) -> 0 | T19: =IF(U19="Input Price only 1 column","",P19*S19) -> 0 | U19: =IF(AND(K19>0,L19>0),"Input Price only 1 column","OK") -> OK | V19: ='CASH REBATE'!$P$22 -> FALSE | W19: ALCHEMY
B20: 04-SPWHI-07000311 | C20: TEG | D20: Single Malt Scotch | E20: The Macallan | F20: MAC | G20: The Macallan Double Cask 30YO | H20: 700ml | I20: 3 | P20: 0 | R20: =IF(K20>0,K20*N20,L20*1.07*N20) -> 0 | S20: =ROUND(R20/1.07,2) -> 0 | T20: =IF(U20="Input Price only 1 column","",P20*S20) -> 0 | U20: =IF(AND(K20>0,L20>0),"Input Price only 1 column","OK") -> OK | V20: ='CASH REBATE'!$P$22 -> FALSE | W20: ALCHEMY
B21: 04-SPWHI-07000796 | C21: TEG | D21: Single Malt Scotch | E21: The Macallan | F21: MAC | G21: The Macallan Triple Cask 12YO | H21: 700ml | I21: 12 | P21: 0 | R21: =IF(K21>0,K21*N21,L21*1.07*N21) -> 0 | S21: =ROUND(R21/1.07,2) -> 0 | T21: =IF(U21="Input Price only 1 column","",P21*S21) -> 0 | U21: =IF(AND(K21>0,L21>0),"Input Price only 1 column","OK") -> OK | V21: ='CASH REBATE'!$P$22 -> FALSE | W21: ALCHEMY
B22: 04-24HMN-07002650 | C22: TEG | D22: Single Malt Scotch | E22: The Macallan | F22: MAC | G22: The Macallan Harmony Vibrant Oak | H22: 700ml | I22: 6 | P22: 0 | R22: =IF(K22>0,K22*N22,L22*1.07*N22) -> 0 | S22: =ROUND(R22/1.07,2) -> 0 | T22: =IF(U22="Input Price only 1 column","",P22*S22) -> 0 | U22: =IF(AND(K22>0,L22>0),"Input Price only 1 column","OK") -> OK | V22: ='CASH REBATE'!$P$22 -> FALSE | W22: ALCHEMY
B23: 04-23WHI-07002322 | C23: TEG | D23: Single Malt Scotch | E23: The Macallan | F23: MAC | G23: The Macallan Harmony Collection Amber Meadow | H23: 700ml | I23: 12 | P23: 0 | R23: =IF(K23>0,K23*N23,L23*1.07*N23) -> 0 | S23: =ROUND(R23/1.07,2) -> 0 | T23: =IF(U23="Input Price only 1 column","",P23*S23) -> 0 | U23: =IF(AND(K23>0,L23>0),"Input Price only 1 column","OK") -> OK | V23: ='CASH REBATE'!$P$22 -> FALSE | W23: ALCHEMY
B24: 04-SPWHI-07000557 | C24: TEG | D24: Single Malt Scotch | E24: The Macallan | F24: MAC | G24: The Macallan Harmony Collection | H24: 700ml | I24: 6 | P24: 0 | R24: =IF(K24>0,K24*N24,L24*1.07*N24) -> 0 | S24: =ROUND(R24/1.07,2) -> 0 | T24: =IF(U24="Input Price only 1 column","",P24*S24) -> 0 | U24: =IF(AND(K24>0,L24>0),"Input Price only 1 column","OK") -> OK | V24: ='CASH REBATE'!$P$22 -> FALSE | W24: ALCHEMY
B25: 04-SPWHI-07001226 | C25: TEG | D25: Single Malt Scotch | E25: The Macallan | F25: MAC | G25: The Macallan Harmony Collection Intense Arabica | H25: 700ml | I25: 6 | P25: 0 | R25: =IF(K25>0,K25*N25,L25*1.07*N25) -> 0 | S25: =ROUND(R25/1.07,2) -> 0 | T25: =IF(U25="Input Price only 1 column","",P25*S25) -> 0 | U25: =IF(AND(K25>0,L25>0),"Input Price only 1 column","OK") -> OK | V25: ='CASH REBATE'!$P$22 -> FALSE | W25: ALCHEMY
... B337: 29-SPGIN-07006351 | C337: Remy Cointreau | D337: Gin | E337: Botanist | F337: BOT | G337: The Botanist Islay Dry Gin (Gift Box) | H337: 700ml | I337: 4 | P337: 0 | R337: =IF(K337>0,K337*N337,L337*1.07*N337) -> 0 | S337: =ROUND(R337/1.07,2) -> 0 | T337: =IF(U337="Input Price only 1 column","",P337*S337) -> 0 | U337: =IF(AND(K337>0,L337>0),"Input Price only 1 column","OK") -> OK | V337: ='CASH REBATE'!$P$22 -> FALSE | W337: ALCHEMY
B338: 31-SPMIX-1450PACK | C338: Campari | D338: Liqueur | E338: Aperol/Cinzano | G338: Aperol + Cinzano Prosecco | H338: 1450ml | I338: 3 | P338: 0 | R338: =IF(K338>0,K338*N338,L338*1.07*N338) -> 0 | S338: =ROUND(R338/1.07,2) -> 0 | T338: =IF(U338="Input Price only 1 column","",P338*S338) -> 0 | U338: =IF(AND(K338>0,L338>0),"Input Price only 1 column","OK") -> OK | V338: ='CASH REBATE'!$P$22 -> FALSE | W338: ALCHEMY
B339: 31-SPPAC-07000575 | C339: Campari | D339: Liqueur | E339: Aperol | F339: APR | G339: Aperol Glass Set | H339: 700ml | I339: 5 | P339: 0 | R339: =IF(K339>0,K339*N339,L339*1.07*N339) -> 0 | S339: =ROUND(R339/1.07,2) -> 0 | T339: =IF(U339="Input Price only 1 column","",P339*S339) -> 0 | U339: =IF(AND(K339>0,L339>0),"Input Price only 1 column","OK") -> OK | V339: ='CASH REBATE'!$P$22 -> FALSE | W339: ALCHEMY
B340: 32-06LIQ-05001051 | C340: Campari | D340: Liqueur | E340: Campari | F340: CAM | G340: Campari Negroni Liqueur | H340: 500ml | I340: 6 | P340: 0 | R340: =IF(K340>0,K340*N340,L340*1.07*N340) -> 0 | S340: =ROUND(R340/1.07,2) -> 0 | T340: =IF(U340="Input Price only 1 column","",P340*S340) -> 0 | U340: =IF(AND(K340>0,L340>0),"Input Price only 1 column","OK") -> OK | V340: ='CASH REBATE'!$P$22 -> FALSE | W340: ALCHEMY
B341: 32-06LIQ-07501402 | C341: Campari | D341: Liqueur | E341: Campari | F341: CAM | G341: Campari Bitter 750 ml | H341: 750ml | I341: 6 | P341: 0 | R341: =IF(K341>0,K341*N341,L341*1.07*N341) -> 0 | S341: =ROUND(R341/1.07,2) -> 0 | T341: =IF(U341="Input Price only 1 column","",P341*S341) -> 0 | U341: =IF(AND(K341>0,L341>0),"Input Price only 1 column","OK") -> OK | V341: ='CASH REBATE'!$P$22 -> FALSE | W341: ALCHEMY
B342: 32-SPPAC-07509002 | C342: Campari | D342: Liqueur | E342: Campari | F342: CAM | G342: Campari Negroni Set | H342: 2250ml | I342: 4 | P342: 0 | R342: =IF(K342>0,K342*N342,L342*1.07*N342) -> 0 | S342: =ROUND(R342/1.07,2) -> 0 | T342: =IF(U342="Input Price only 1 column","",P342*S342) -> 0 | U342: =IF(AND(K342>0,L342>0),"Input Price only 1 column","OK") -> OK | V342: ='CASH REBATE'!$P$22 -> FALSE | W342: ALCHEMY
B343: 33-SPGIN-07502000 | C343: Campari | D343: Gin | E343: Bulldog | F343: BUL | G343: Bulldog London Dry Gin 750 ml | H343: 750ml | I343: 6 | P343: 0 | R343: =IF(K343>0,K343*N343,L343*1.07*N343) -> 0 | S343: =ROUND(R343/1.07,2) -> 0 | T343: =IF(U343="Input Price only 1 column","",P343*S343) -> 0 | U343: =IF(AND(K343>0,L343>0),"Input Price only 1 column","OK") -> OK | V343: ='CASH REBATE'!$P$22 -> FALSE | W343: ALCHEMY
B344: 33-SPPAC-07506102 | C344: Campari | D344: Gin | E344: Bulldog | F344: BUL | G344: Bulldog Gin Glass Set | H344: 750ml | I344: 6 | P344: 0 | R344: =IF(K344>0,K344*N344,L344*1.07*N344) -> 0 | S344: =ROUND(R344/1.07,2) -> 0 | T344: =IF(U344="Input Price only 1 column","",P344*S344) -> 0 | U344: =IF(AND(K344>0,L344>0),"Input Price only 1 column","OK") -> OK | V344: ='CASH REBATE'!$P$22 -> FALSE | W344: ALCHEMY
B345: 34-12VOD-01808261 | C345: Campari | D345: Vodka | E345: Skyy | F345: SKY | G345: Skyy Vodka 180 ml (P12) | H345: 180ml | I345: 12 | P345: 0 | R345: =IF(K345>0,K345*N345,L345*1.07*N345) -> 0 | S345: =ROUND(R345/1.07,2) -> 0 | T345: =IF(U345="Input Price only 1 column","",P345*S345) -> 0 | U345: =IF(AND(K345>0,L345>0),"Input Price only 1 column","OK") -> OK | V345: ='CASH REBATE'!$P$22 -> FALSE | W345: ALCHEMY
B346: 34-SPVOD-07007004 | C346: Campari | D346: Vodka | E346: Skyy | F346: SKY | G346: Skyy Vodka | H346: 700ml | I346: 12 | P346: 0 | R346: =IF(K346>0,K346*N346,L346*1.07*N346) -> 0 | S346: =ROUND(R346/1.07,2) -> 0 | T346: =IF(U346="Input Price only 1 column","",P346*S346) -> 0 | U346: =IF(AND(K346>0,L346>0),"Input Price only 1 column","OK") -> OK | V346: ='CASH REBATE'!$P$22 -> FALSE | W346: ALCHEMY
B347: 37-SPWHI-07002834 | C347: Campari | D347: Whisky | E347: Wild Turkey | F347: WTK | G347: Wild Turkey Rye Whiskey 700ml | H347: 700ml | I347: 12 | P347: 0 | R347: =IF(K347>0,K347*N347,L347*1.07*N347) -> 0 | S347: =ROUND(R347/1.07,2) -> 0 | T347: =IF(U347="Input Price only 1 column","",P347*S347) -> 0 | U347: =IF(AND(K347>0,L347>0),"Input Price only 1 column","OK") -> OK | V347: ='CASH REBATE'!$P$22 -> FALSE | W347: ALCHEMY
B348: 40-SPRUM-07501400 | C348: Campari | D348: Rum | E348: Appleton | F348: APT | G348: Appleton Estate Rare Blend 12 Years | H348: 750ml | I348: 12 | P348: 0 | R348: =IF(K348>0,K348*N348,L348*1.07*N348) -> 0 | S348: =ROUND(R348/1.07,2) -> 0 | T348: =IF(U348="Input Price only 1 column","",P348*S348) -> 0 | U348: =IF(AND(K348>0,L348>0),"Input Price only 1 column","OK") -> OK | V348: ='CASH REBATE'!$P$22 -> FALSE | W348: ALCHEMY
B349: 46-ABRGP-07000051 | C349: Campari | D349: Whisky | E349: Glen Grant | F349: GGT | G349: Glen Grant Single Malt Scotch Whisky Arboralis (Gift Pack) | H349: 700ml | I349: 6 | P349: 0 | R349: =IF(K349>0,K349*N349,L349*1.07*N349) -> 0 | S349: =ROUND(R349/1.07,2) -> 0 | T349: =IF(U349="Input Price only 1 column","",P349*S349) -> 0 | U349: =IF(AND(K349>0,L349>0),"Input Price only 1 column","OK") -> OK | V349: ='CASH REBATE'!$P$22 -> FALSE | W349: ALCHEMY
B350: 51-WISPA-07505015 | C350: Luc Belaire | D350: Sparkling Wine | E350: Luc Belaire | F350: LUC | G350: Luc Belaire Rare Luxe | H350: 750ml | I350: 6 | P350: 0 | R350: =IF(K350>0,K350*N350,L350*1.07*N350) -> 0 | S350: =ROUND(R350/1.07,2) -> 0 | T350: =IF(U350="Input Price only 1 column","",P350*S350) -> 0 | U350: =IF(AND(K350>0,L350>0),"Input Price only 1 column","OK") -> OK | V350: ='CASH REBATE'!$P$22 -> FALSE | W350: ALCHEMY
... B368: 75-06WHI-07007038 | C368: Vok | D368: Whisky | E368: Real Mccoy | F368: RMC | G368: Real Mccoy Bourbon Whiskey | H368: 700ml | I368: 6 | P368: 0 | R368: =IF(K368>0,K368*N368,L368*1.07*N368) -> 0 | S368: =ROUND(R368/1.07,2) -> 0 | T368: =IF(U368="Input Price only 1 column","",P368*S368) -> 0 | U368: =IF(AND(K368>0,L368>0),"Input Price only 1 column","OK") -> OK | V368: ='CASH REBATE'!$P$22 -> FALSE | W368: ALCHEMY
B369: 76-SPSHE-05001041 | C369: Edrington | D369: Wine | E369: Valdespino | G369: Valdespino Don Gonzalo Oloroso Sherry Wine | H369: 500ml | I369: 6 | P369: 0 | R369: =IF(K369>0,K369*N369,L369*1.07*N369) -> 0 | S369: =ROUND(R369/1.07,2) -> 0 | T369: =IF(U369="Input Price only 1 column","",P369*S369) -> 0 | U369: =IF(AND(K369>0,L369>0),"Input Price only 1 column","OK") -> OK | V369: ='CASH REBATE'!$P$22 -> FALSE | W369: ALCHEMY
B370: 76-SPSHE-07500938 | C370: Edrington | D370: Wine | E370: Valdespino | G370: Valdespino El Candado PX Sherry Wine | H370: 700ml | I370: 6 | P370: 0 | R370: =IF(K370>0,K370*N370,L370*1.07*N370) -> 0 | S370: =ROUND(R370/1.07,2) -> 0 | T370: =IF(U370="Input Price only 1 column","",P370*S370) -> 0 | U370: =IF(AND(K370>0,L370>0),"Input Price only 1 column","OK") -> OK | V370: ='CASH REBATE'!$P$22 -> FALSE | W370: ALCHEMY
B371: 76-SPVER-07500174 | C371: Edrington | D371: Vermouth | E371: Valdespino | G371: Valdespino Vermouth | H371: 700ml | I371: 6 | P371: 0 | R371: =IF(K371>0,K371*N371,L371*1.07*N371) -> 0 | S371: =ROUND(R371/1.07,2) -> 0 | T371: =IF(U371="Input Price only 1 column","",P371*S371) -> 0 | U371: =IF(AND(K371>0,L371>0),"Input Price only 1 column","OK") -> OK | V371: ='CASH REBATE'!$P$22 -> FALSE | W371: ALCHEMY
B372: 42-SPVER-10000853 | C372: Campari | D372: Vermouth | E372: Cinzano | F372: CZV | G372: CINZANO VERMOUTH EXTRA DRY 1L | H372: 1000ml | I372: 12 | P372: 0 | R372: =IF(K372>0,K372*N372,L372*1.07*N372) -> 0 | S372: =ROUND(R372/1.07,2) -> 0 | T372: =IF(U372="Input Price only 1 column","",P372*S372) -> 0 | U372: =IF(AND(K372>0,L372>0),"Input Price only 1 column","OK") -> OK | V372: ='CASH REBATE'!$P$22 -> FALSE | W372: ALCHEMY
B373: 52-WISPB-07503811 | C373: Pommery | D373: Champagne | E373: Pommery | F373: POM | G373: Champagne Heidsieck Monopole Blue Top Brut | H373: 750ml | I373: 6 | P373: 0 | R373: =IF(K373>0,K373*N373,L373*1.07*N373) -> 0 | S373: =ROUND(R373/1.07,2) -> 0 | T373: =IF(U373="Input Price only 1 column","",P373*S373) -> 0 | U373: =IF(AND(K373>0,L373>0),"Input Price only 1 column","OK") -> OK | V373: ='CASH REBATE'!$P$22 -> FALSE | W373: ALCHEMY
B374: 24-26CNY-07000401 | C374: Remy Cointreau | D374: Cognac | E374: Remy | F374: RMM | G374: Louis XIII CNY26 | H374: 700ml | I374: 1 | P374: 0 | R374: =IF(K374>0,K374*N374,L374*1.07*N374) -> 0 | S374: =ROUND(R374/1.07,2) -> 0 | T374: =IF(U374="Input Price only 1 column","",P374*S374) -> 0 | U374: =IF(AND(K374>0,L374>0),"Input Price only 1 column","OK") -> OK | V374: ='CASH REBATE'!$P$22 -> FALSE | W374: ALCHEMY
B375: 42-SPVER-10000822 | C375: Campari | D375: Vermouth | E375: Cinzano | F375: CZV | G375: Cinzano Bianco Vermouth | H375: 1000ml | I375: 12 | P375: 0 | R375: =IF(K375>0,K375*N375,L375*1.07*N375) -> 0 | S375: =ROUND(R375/1.07,2) -> 0 | T375: =IF(U375="Input Price only 1 column","",P375*S375) -> 0 | U375: =IF(AND(K375>0,L375>0),"Input Price only 1 column","OK") -> OK | V375: ='CASH REBATE'!$P$22 -> FALSE | W375: ALCHEMY
B376: 76-SPVER-07502857 | C376: Edrington | D376: Vermouth | E376: Valdespino | G376: VALDESPINO ORIGEN VERMOUTH 15% 0.75L | H376: 750ml | I376: 6 | P376: 0 | R376: =IF(K376>0,K376*N376,L376*1.07*N376) -> 0 | S376: =ROUND(R376/1.07,2) -> 0 | T376: =IF(U376="Input Price only 1 column","",P376*S376) -> 0 | U376: =IF(AND(K376>0,L376>0),"Input Price only 1 column","OK") -> OK | V376: ='CASH REBATE'!$P$22 -> FALSE | W376: ALCHEMY
B377: 103LOWHI-10000617 | C377: LOCH LOMOND GROUP | D377: WHISKY | E377: HIGH COMMISSIONER | G377: HIGH COMMISSIONER BLENDED 40% 12x1L | H377: 1000ml | I377: 12 | P377: 0 | R377: =IF(K377>0,K377*N377,L377*1.07*N377) -> 0 | S377: =ROUND(R377/1.07,2) -> 0 | T377: =IF(U377="Input Price only 1 column","",P377*S377) -> 0 | U377: =IF(AND(K377>0,L377>0),"Input Price only 1 column","OK") -> OK | V377: ='CASH REBATE'!$P$22 -> FALSE | W377: ALCHEMY
B378: 103LOWHI-07000211 | C378: LOCH LOMOND GROUP | D378: WHISKY | E378: HIGH COMMISSIONER | G378: HIGH COMMISSIONER BLENDED 40% 12x0.7L | H378: 700ml | I378: 12 | P378: 0 | R378: =IF(K378>0,K378*N378,L378*1.07*N378) -> 0 | S378: =ROUND(R378/1.07,2) -> 0 | T378: =IF(U378="Input Price only 1 column","",P378*S378) -> 0 | U378: =IF(AND(K378>0,L378>0),"Input Price only 1 column","OK") -> OK | V378: ='CASH REBATE'!$P$22 -> FALSE | W378: ALCHEMY
B379: 103LOWHI-03500129 | C379: LOCH LOMOND GROUP | D379: WHISKY | E379: HIGH COMMISSIONER | G379: HIGH COMMISSIONER BLENDED 40% 24x0.35L | H379: 350ml | I379: 24 | P379: 0 | R379: =IF(K379>0,K379*N379,L379*1.07*N379) -> 0 | S379: =ROUND(R379/1.07,2) -> 0 | T379: =IF(U379="Input Price only 1 column","",P379*S379) -> 0 | U379: =IF(AND(K379>0,L379>0),"Input Price only 1 column","OK") -> OK | V379: ='CASH REBATE'!$P$22 -> FALSE | W379: ALCHEMY
B380: 103LOWHI-02000068 | C380: LOCH LOMOND GROUP | D380: WHISKY | E380: HIGH COMMISSIONER | G380: HIGH COMMISSIONER BLENDED 40% 48x0.2L | H380: 200ml | I380: 48 | P380: 0 | R380: =IF(K380>0,K380*N380,L380*1.07*N380) -> 0 | S380: =ROUND(R380/1.07,2) -> 0 | T380: =IF(U380="Input Price only 1 column","",P380*S380) -> 0 | U380: =IF(AND(K380>0,L380>0),"Input Price only 1 column","OK") -> OK | V380: ='CASH REBATE'!$P$22 -> FALSE | W380: ALCHEMY
B381: 106LOWHI-07003219 | C381: LOCH LOMOND GROUP | D381: WHISKY | E381: LOCH LOMOND | G381: LOCH LOMOND ORIGINAL SCOTCH WHISKY | H381: 700ml | I381: 6 | P381: 0 | R381: =IF(K381>0,K381*N381,L381*1.07*N381) -> 0 | S381: =ROUND(R381/1.07,2) -> 0 | T381: =IF(U381="Input Price only 1 column","",P381*S381) -> 0 | U381: =IF(AND(K381>0,L381>0),"Input Price only 1 column","OK") -> OK | V381: ='CASH REBATE'!$P$22 -> FALSE | W381: ALCHEMY
B382: 106LOWHI-07007216 | C382: LOCH LOMOND GROUP | D382: WHISKY | E382: LOCH LOMOND | G382: LOCH LOMOND AGED 12 YEARS SCOTCH WHISKY | H382: 700ml | I382: 6 | P382: 0 | R382: =IF(K382>0,K382*N382,L382*1.07*N382) -> 0 | S382: =ROUND(R382/1.07,2) -> 0 | T382: =IF(U382="Input Price only 1 column","",P382*S382) -> 0 | U382: =IF(AND(K382>0,L382>0),"Input Price only 1 column","OK") -> OK | V382: ='CASH REBATE'!$P$22 -> FALSE
B383: 106LOWHI-07009215 | C383: LOCH LOMOND GROUP | D383: WHISKY | E383: LOCH LOMOND | G383: LOCH LOMOND AGED 18 YEARS SCOTCH WHISKY | H383: 700ml | I383: 6 | P383: 0 | R383: =IF(K383>0,K383*N383,L383*1.07*N383) -> 0 | S383: =ROUND(R383/1.07,2) -> 0 | T383: =IF(U383="Input Price only 1 column","",P383*S383) -> 0 | U383: =IF(AND(K383>0,L383>0),"Input Price only 1 column","OK") -> OK | V383: ='CASH REBATE'!$P$22 -> FALSE
B384: 04-SPWHI-07001257 | C384: Edrington | D384: WHISKY | E384: The Macallan | F384: MAC | G384: THE MACALLAN LITHA WHISKY | H384: 700ml | I384: 6 | P384: 0 | R384: =IF(K384>0,K384*N384,L384*1.07*N384) -> 0 | S384: =ROUND(R384/1.07,2) -> 0 | T384: =IF(U384="Input Price only 1 column","",P384*S384) -> 0 | U384: =IF(AND(K384>0,L384>0),"Input Price only 1 column","OK") -> OK | V384: ='CASH REBATE'!$P$22 -> FALSE
B385: 42-SPVER-10000061 | C385: Campari Group | D385: Vermouth | E385: Del Professore | G385: Del Professore Rosso Vermouth | H385: 1000ml | I385: 6 | P385: 0 | R385: =IF(K385>0,K385*N385,L385*1.07*N385) -> 0 | S385: =ROUND(R385/1.07,2) -> 0 | T385: =IF(U385="Input Price only 1 column","",P385*S385) -> 0 | U385: =IF(AND(K385>0,L385>0),"Input Price only 1 column","OK") -> OK | V385: ='CASH REBATE'!$P$22 -> FALSE
B386: 42-WISPA-07503171 | C386: Campari Group | D386: Sparkling Wine | E386: Riccadonna | G386: Riccadonna To Spritz | H386: 750ml | I386: 6 | P386: 0 | R386: =IF(K386>0,K386*N386,L386*1.07*N386) -> 0 | S386: =ROUND(R386/1.07,2) -> 0 | T386: =IF(U386="Input Price only 1 column","",P386*S386) -> 0 | U386: =IF(AND(K386>0,L386>0),"Input Price only 1 column","OK") -> OK | V386: ='CASH REBATE'!$P$22 -> FALSE
B387: 57-SPLIQ-07000707 | C387: Campari | D387: Liqueur | E387: Ouzo | F387: OUZ | G387: Ouzo 12 Liqueur | H387: 700ml | I387: 6 | P387: 0 | R387: =IF(K387>0,K387*N387,L387*1.07*N387) -> 0 | S387: =ROUND(R387/1.07,2) -> 0 | T387: =IF(U387="Input Price only 1 column","",P387*S387) -> 0 | U387: =IF(AND(K387>0,L387>0),"Input Price only 1 column","OK") -> OK | V387: ='CASH REBATE'!$P$22 -> FALSE
B388: 58-SPLIQ-07009164 | C388: Ancho | D388: Liqueur | E388: Ancho | F388: BRC | G388: Ancho Reyes Verde Liqueur | H388: 700ml | I388: 6 | P388: 0 | R388: =IF(K388>0,K388*N388,L388*1.07*N388) -> 0 | S388: =ROUND(R388/1.07,2) -> 0 | T388: =IF(U388="Input Price only 1 column","",P388*S388) -> 0 | U388: =IF(AND(K388>0,L388>0),"Input Price only 1 column","OK") -> OK | V388: ='CASH REBATE'!$P$22 -> FALSE
B389: 66-SPGIN-07000064 | C389: Bareksten | D389: Gin | E389: Bareksten | F389: BAR | G389: Bareksten Botanical Gin | H389: 700ml | I389: 6 | P389: 0 | R389: =IF(K389>0,K389*N389,L389*1.07*N389) -> 0 | S389: =ROUND(R389/1.07,2) -> 0 | T389: =IF(U389="Input Price only 1 column","",P389*S389) -> 0 | U389: =IF(AND(K389>0,L389>0),"Input Price only 1 column","OK") -> OK | V389: ='CASH REBATE'!$P$22 -> FALSE
B390: 84-SPLIQ-07500002 | C390: BIGGAR & LEITH | D390: Liqueur | E390: BIGGAR & LEITH | F390: BGL | G390: Hotel Starlino Aperitivo Orange | H390: 750ml | I390: 6 | P390: 0 | R390: =IF(K390>0,K390*N390,L390*1.07*N390) -> 0 | S390: =ROUND(R390/1.07,2) -> 0 | T390: =IF(U390="Input Price only 1 column","",P390*S390) -> 0 | U390: =IF(AND(K390>0,L390>0),"Input Price only 1 column","OK") -> OK | V390: ='CASH REBATE'!$P$22 -> FALSE
B391: 84-SPLIQ-07500003 | C391: BIGGAR & LEITH | D391: Liqueur | E391: BIGGAR & LEITH | F391: BGL | G391: Hotel Starlino Aperitivo Rose | H391: 750ml | I391: 6 | P391: 0 | R391: =IF(K391>0,K391*N391,L391*1.07*N391) -> 0 | S391: =ROUND(R391/1.07,2) -> 0 | T391: =IF(U391="Input Price only 1 column","",P391*S391) -> 0 | U391: =IF(AND(K391>0,L391>0),"Input Price only 1 column","OK") -> OK | V391: ='CASH REBATE'!$P$22 -> FALSE
B392: 84-SPVER-07500001 | C392: BIGGAR & LEITH | D392: Vermouth | E392: BIGGAR & LEITH | F392: BGL | G392: Hotel Starlino Vermouth Rosso | H392: 750ml | I392: 6 | P392: 0 | R392: =IF(K392>0,K392*N392,L392*1.07*N392) -> 0 | S392: =ROUND(R392/1.07,2) -> 0 | T392: =IF(U392="Input Price only 1 column","",P392*S392) -> 0 | U392: =IF(AND(K392>0,L392>0),"Input Price only 1 column","OK") -> OK | V392: ='CASH REBATE'!$P$22 -> FALSE
B393: 85-SPLIQ-07000001 | C393: BIGGAR & LEITH | D393: Liqueur | E393: BIGGAR & LEITH | F393: BGL | G393: Shanky'S Whip Liqueur And Whisky Blend | H393: 700ml | I393: 6 | P393: 0 | R393: =IF(K393>0,K393*N393,L393*1.07*N393) -> 0 | S393: =ROUND(R393/1.07,2) -> 0 | T393: =IF(U393="Input Price only 1 column","",P393*S393) -> 0 | U393: =IF(AND(K393>0,L393>0),"Input Price only 1 column","OK") -> OK | V393: ='CASH REBATE'!$P$22 -> FALSE
B394: 86-SPLIQ-07000001 | C394: BIGGAR & LEITH | D394: Liqueur | E394: BIGGAR & LEITH | F394: BGL | G394: Stambecco Amaro Maraschino Liqueur | H394: 700ml | I394: 6 | P394: 0 | R394: =IF(K394>0,K394*N394,L394*1.07*N394) -> 0 | S394: =ROUND(R394/1.07,2) -> 0 | T394: =IF(U394="Input Price only 1 column","",P394*S394) -> 0 | U394: =IF(AND(K394>0,L394>0),"Input Price only 1 column","OK") -> OK | V394: ='CASH REBATE'!$P$22 -> FALSE
B395: 84-SPLIQ-07500852 | C395: BIGGAR & LEITH | D395: Liqueur | E395: BIGGAR & LEITH | F395: BGL | G395: Hotel Starlino Aperitivo Elderflower | H395: 750ml | I395: 6 | P395: 0
B396: GL-01WHI-07000203 | C396: BIGGAR & LEITH | D396: Whisky | E396: BIGGAR & LEITH | F396: BGL | G396: The Gladstone Axe American Oak Whisky | H396: 700ml | I396: 6 | P396: 0
B397: BU-03TEQ-05000371 | C397: BIGGAR & LEITH | D397: Tequila | E397: BIGGAR & LEITH | F397: BGL | G397: Butterfly Cannon Rosa Tequila 0.5L | H397: 500ml | I397: 6 | P397: 0
B398: BU-02TEQ-05000296 | C398: BIGGAR & LEITH | D398: Tequila | E398: BIGGAR & LEITH | F398: BGL | G398: Butterfly Cannon Cristalino Tequila 0.5L | H398: 500ml | I398: 6 | P398: 0
B399: SP-01RUM-07006059 | C399: Biggar & Leith | D399: Rum | E399: Biggar & Leith | F399: BGL | G399: Spytail Ginger Rum 0.7L | H399: 700ml | I399: 6 | P399: 0
B400: ST-01LIQ-07001224 | C400: BIGGAR & LEITH | D400: Liqueur | E400: BIGGAR & LEITH | F400: BGL | G400: Stambecco Tiramisu Liqueur 0.7L | H400: 700ml | I400: 6 | P400: 0
B401: BU-01TEQ-05000333 | C401: BIGGAR & LEITH | D401: Tequila | E401: BIGGAR & LEITH | F401: BGL | G401: Butterfly Cannon Blue Tequila 0.5L | H401: 500ml | I401: 6 | P401: 0
B402: 77-SPLIQ-10001617 | C402: Branca | D402: Liqueur | E402: Branca | F402: BRC | G402: Borghetti Espresso Liqueur | H402: 1000ml | I402: 6 | P402: 0
B403: 58-SPLIQ-07009065 | C403: Campari | D403: Liqueur | E403: Campari | F403: CAM | G403: Ancho Reyes Liqueur | H403: 700ml | I403: 6 | P403: 0
B404: 60-SPGIN-07000522 | C404: Campari | D404: Gin | E404: Campari | F404: CAM | G404: Ondina Gin | H404: 700ml | I404: 6 | P404: 0
B405: 55-SPMEZ-07502893 | C405: Clase Azul | D405: Mezcal | E405: Clase Azul | F405: CAZ | G405: Mezcal Clase Azul Durango | H405: 750ml | I405: 3 | P405: 0
B406: 55-SPTEQ-07504724 | C406: Clase Azul | D406: Tequila | E406: Clase Azul | F406: CAZ | G406: Tequila Clase Azul Anejo | H406: 750ml | I406: 3 | P406: 0
... B488: 99-SL001-07000013 | C488: BRANCA | D488: BITTER | E488: Fernet | F488: BRC | G488: Fernet Branca Bitters 700ml | H488: 700ml | I488: 6 | P488: 0
B489: GL-02WHI-07000241 | C489: BIGGAR & LEITH | D489: WHISKY | E489: The Gladstone | G489: The Gladstone Axe The Black Axe Whisky | H489: 700ml | I489: 6 | P489: 0
B490: SP-02RUM-07006523 | C490: Biggar & Leith | D490: Rum | E490: Spytail | G490: Spytail Cognac Barrel Rum | H490: 700ml | I490: 6 | P490: 0
B491: 80-SPWHI-07001488 | C491: GLENTURRET | D491: WHISKY | E491: Glenturret | F491: GTR | G491: The Glenturret Triple Wood Whisky (2024) | H491: 700ml | I491: 6 | P491: 0
B492: 79-SPGIN-07000392 | C492: LARK | D492: GIN | E492: Forty Spotted | G492: Forty Spotted Pinot Noir | H492: 700ml | I492: 6 | P492: 0
B493: 79-SPWHI-07003577 | C493: LARK | D493: WHISKY | E493: Lark | F493: LRK | G493: LARK NO. 151 FIRE TRAIL WHISKY | H493: 700ml | I493: 6 | P493: 0
B494: 79-SPWHI-07003584 | C494: LARK | D494: WHISKY | E494: Lark | F494: LRK | G494: LARK NO. 183 DEVIL'S STORM WHISKY | H494: 700ml | I494: 6 | P494: 0
B495: 79-SPWHI-07003607 | C495: LARK | D495: WHISKY | E495: Lark | F495: LRK | G495: LARK NO. 285 RUBY ABYSS WHISKY | H495: 700ml | I495: 6 | P495: 0
B496: 106PEWHI-07003015 | C496: PENDULUM | D496: WHISKY | E496: FABLE | G496: FABLE PALE HORSE 8 YEARS SCOTCH WHISKY | H496: 700ml | I496: 6 | P496: 0
B497: 106PEWHI-07002919 | C497: PENDULUM | D497: WHISKY | E497: FABLE | G497: FABLE CHAPTER 8 CANARY 11 YEARS SCOTCH WHISKY | H497: 700ml | I497: 6 | P497: 0
B498: 101SESPA-07500680 | C498: SERENA | D498: Sparkling Wine | E498: PIU | G498: Piu Brioso Vino Spumante Bianco | H498: 750ml | I498: 6 | P498: 0
B499: 101SESPA-07500703 | C499: SERENA | D499: Sparkling Wine | E499: PIU | G499: Piu Brioso Prosecco Valdobbiadene | H499: 750ml | I499: 6 | P499: 0
B500: 101SESPA-07500727 | C500: SERENA | D500: Sparkling Wine | E500: PIU | G500: Piu Brioso Prosecco Rose | H500: 750ml | I500: 6 | P500: 0

Sheet 03
B1: Outlet Rebate Calculation Form
B2: Outlet Name : | C2: =IF(INDEX!C3="","",INDEX!C3) -> Outlet Name | E2: Area : | F2: =IF(INDEX!C9="","",INDEX!C9) -> Area | N2: Vol. (Btls.) | P2: Rebate (%) | R2: Price inc. VAT | S2: Price ex. VAT | T2: Rebate
B3: Legal Name : | C3: =IF(INDEX!C5="","",INDEX!C5) -> Outlet Company Limited | E3: Agent : | F3: =IF(INDEX!C11="","",INDEX!C11) -> Agent name | L3: ALL PRINCIPLE | N3: =SUM(N12:N394) -> 0 | P3: =IFERROR(T3/S3,"") | R3: =SUM(R12:R394) -> 0 | S3: =SUM(S12:S394) -> 0 | T3: =SUM(T12:T394) -> 0
B5: BDE : | C5: =IF(INDEX!C7="","",INDEX!C7) -> Name of BDE | E5: Manager : | F5: =IF(INDEX!C13="","",INDEX!C13) -> Manager Name | L5: Campari | N5: =SUMIFS(N$12:N$394,$C$12:$C$394,$L$5) -> 0 | P5: =IFERROR(T5/S5,"") | R5: =SUMIFS(R$12:R$394,$C$12:$C$394,$L$5) -> 0 | S5: =SUMIFS(S$12:S$394,$C$12:$C$394,$L$5) -> 0 | T5: =SUMIFS(T$12:T$394,$C$12:$C$394,$L$5) -> 0
B7: Type of Contract : | C7: =INDEX!C21 -> Marketing Contract & Yearly Contract | L7: ATT | N7: =SUMIFS($N$12:N394,$W$12:$W$394,"ALCHEMY") -> 0 | P7: =IFERROR(T7/S7,"") | R7: =SUMIFS($R$12:R394,$W$12:$W$394,"ALCHEMY") -> 0 | S7: =SUMIFS($S$12:S394,$W$12:$W$394,"ALCHEMY") -> 0 | T7: =SUMIFS($T$12:T394,$W$12:$W$394,"ALCHEMY") -> 0
B9: Contract Period : | C9: =INDEX!C19 -> 01 Jan 26 - 31 Dec 26 | L9: BBC | N9: =SUMIFS($N$12:N394,$W$12:$W$394,"BBC") -> 0 | P9: =IFERROR(T9/S9,"") | R9: =SUMIFS($R$12:R394,$W$12:$W$394,"BBC") -> 0 | S9: =SUMIFS($S$12:S394,$W$12:$W$394,"BBC") -> 0 | T9: =SUMIFS($T$12:T394,$W$12:$W$394,"BBC") -> 0
B10: Period : | C10: MAR (change if needed)
K11: Input column J or K | N11: Input | R11: =SUBTOTAL(9,R13:R394) -> 0 | S11: =SUBTOTAL(9,S13:S394) -> 0 | T11: =SUBTOTAL(9,T13:T394) -> 0
B12: Code | C12: Principle | D12: Category | E12: Brand | F12: Brand Code | G12: Product | H12: Size | I12: Packing | J12: Wholesaler | K12: Price Inc. VAT | L12: Price Ex. VAT | M12: x | N12: Vol. (Btls.) | O12: x | P12: Rebate (%) | Q12: x | R12: Total Price Inc. VAT | S12: Total Price ex. VAT | T12: Total Rebate | U12: Check | V12: Pay
B13: {=MAPPING!$B$3:$I$490} -> 04-SPWHI-07007491 | C13: TEG | D13: Single Malt Scotch | E13: The Macallan | F13: MAC | G13: The Macallan Sherry Oak 12YO | H13: 700ml | I13: 12 | P13: {=MAPPING!J3:J490} -> 0 | R13: =IF(K13>0,K13*N13,L13*1.07*N13) -> 0 | S13: =ROUND(R13/1.07,2) -> 0 | T13: =IF(U13="Input Price only 1 column","",P13*S13) -> 0 | U13: =IF(AND(K13>0,L13>0),"Input Price only 1 column","OK") -> OK | V13: ='CASH REBATE'!$P$22 -> FALSE | W13: {=MAPPING!$A$3:$A$371} -> ALCHEMY
B14: 04-SPWHI-07017065 | C14: TEG | D14: Single Malt Scotch | E14: The Macallan | F14: MAC | G14: The Macallan Sherry Oak 18YO | H14: 700ml | I14: 6 | P14: 0 | R14: =IF(K14>0,K14*N14,L14*1.07*N14) -> 0 | S14: =ROUND(R14/1.07,2) -> 0 | T14: =IF(U14="Input Price only 1 column","",P14*S14) -> 0 | U14: =IF(AND(K14>0,L14>0),"Input Price only 1 column","OK") -> OK | V14: ='CASH REBATE'!$P$22 -> FALSE | W14: ALCHEMY
B15: 04-SPWHI-07006031 | C15: TEG | D15: Single Malt Scotch | E15: The Macallan | F15: MAC | G15: The Macallan Sherry Oak 25YO | H15: 700ml | I15: 3 | P15: 0 | R15: =IF(K15>0,K15*N15,L15*1.07*N15) -> 0 | S15: =ROUND(R15/1.07,2) -> 0 | T15: =IF(U15="Input Price only 1 column","",P15*S15) -> 0 | U15: =IF(AND(K15>0,L15>0),"Input Price only 1 column","OK") -> OK | V15: ='CASH REBATE'!$P$22 -> FALSE | W15: ALCHEMY
B16: 04-SPWHI-07006048 | C16: TEG | D16: Single Malt Scotch | E16: The Macallan | F16: MAC | G16: The Macallan Sherry Oak 30YO | H16: 700ml | I16: 3 | P16: 0 | R16: =IF(K16>0,K16*N16,L16*1.07*N16) -> 0 | S16: =ROUND(R16/1.07,2) -> 0 | T16: =IF(U16="Input Price only 1 column","",P16*S16) -> 0 | U16: =IF(AND(K16>0,L16>0),"Input Price only 1 column","OK") -> OK | V16: ='CASH REBATE'!$P$22 -> FALSE | W16: ALCHEMY
B17: 04-SPWHI-07003009 | C17: TEG | D17: Single Malt Scotch | E17: The Macallan | F17: MAC | G17: The Macallan Double Cask 12YO | H17: 700ml | I17: 12 | P17: 0 | R17: =IF(K17>0,K17*N17,L17*1.07*N17) -> 0 | S17: =ROUND(R17/1.07,2) -> 0 | T17: =IF(U17="Input Price only 1 column","",P17*S17) -> 0 | U17: =IF(AND(K17>0,L17>0),"Input Price only 1 column","OK") -> OK | V17: ='CASH REBATE'!$P$22 -> FALSE | W17: ALCHEMY
B18: 04-SPWHI-07007700 | C18: TEG | D18: Single Malt Scotch | E18: The Macallan | F18: MAC | G18: The Macallan Double Cask 15YO | H18: 700ml | I18: 6 | P18: 0 | R18: =IF(K18>0,K18*N18,L18*1.07*N18) -> 0 | S18: =ROUND(R18/1.07,2) -> 0 | T18: =IF(U18="Input Price only 1 column","",P18*S18) -> 0 | U18: =IF(AND(K18>0,L18>0),"Input Price only 1 column","OK") -> OK | V18: ='CASH REBATE'!$P$22 -> FALSE | W18: ALCHEMY
B19: 04-SPWHI-07009254 | C19: TEG | D19: Single Malt Scotch | E19: The Macallan | F19: MAC | G19: The Macallan Double Cask 18YO | H19: 700ml | I19: 6 | P19: 0 | R19: =IF(K19>0,K19*N19,L19*1.07*N19) -> 0 | S19: =ROUND(R19/1.07,2) -> 0 | T19: =IF(U19="Input Price only 1 column","",P19*S19) -> 0 | U19: =IF(AND(K19>0,L19>0),"Input Price only 1 column","OK") -> OK | V19: ='CASH REBATE'!$P$22 -> FALSE | W19: ALCHEMY
B20: 04-SPWHI-07000311 | C20: TEG | D20: Single Malt Scotch | E20: The Macallan | F20: MAC | G20: The Macallan Double Cask 30YO | H20: 700ml | I20: 3 | P20: 0 | R20: =IF(K20>0,K20*N20,L20*1.07*N20) -> 0 | S20: =ROUND(R20/1.07,2) -> 0 | T20: =IF(U20="Input Price only 1 column","",P20*S20) -> 0 | U20: =IF(AND(K20>0,L20>0),"Input Price only 1 column","OK") -> OK | V20: ='CASH REBATE'!$P$22 -> FALSE | W20: ALCHEMY
B21: 04-SPWHI-07000796 | C21: TEG | D21: Single Malt Scotch | E21: The Macallan | F21: MAC | G21: The Macallan Triple Cask 12YO | H21: 700ml | I21: 12 | P21: 0 | R21: =IF(K21>0,K21*N21,L21*1.07*N21) -> 0 | S21: =ROUND(R21/1.07,2) -> 0 | T21: =IF(U21="Input Price only 1 column","",P21*S21) -> 0 | U21: =IF(AND(K21>0,L21>0),"Input Price only 1 column","OK") -> OK | V21: ='CASH REBATE'!$P$22 -> FALSE | W21: ALCHEMY
B22: 04-24HMN-07002650 | C22: TEG | D22: Single Malt Scotch | E22: The Macallan | F22: MAC | G22: The Macallan Harmony Vibrant Oak | H22: 700ml | I22: 6 | P22: 0 | R22: =IF(K22>0,K22*N22,L22*1.07*N22) -> 0 | S22: =ROUND(R22/1.07,2) -> 0 | T22: =IF(U22="Input Price only 1 column","",P22*S22) -> 0 | U22: =IF(AND(K22>0,L22>0),"Input Price only 1 column","OK") -> OK | V22: ='CASH REBATE'!$P$22 -> FALSE | W22: ALCHEMY
B23: 04-23WHI-07002322 | C23: TEG | D23: Single Malt Scotch | E23: The Macallan | F23: MAC | G23: The Macallan Harmony Collection Amber Meadow | H23: 700ml | I23: 12 | P23: 0 | R23: =IF(K23>0,K23*N23,L23*1.07*N23) -> 0 | S23: =ROUND(R23/1.07,2) -> 0 | T23: =IF(U23="Input Price only 1 column","",P23*S23) -> 0 | U23: =IF(AND(K23>0,L23>0),"Input Price only 1 column","OK") -> OK | V23: ='CASH REBATE'!$P$22 -> FALSE | W23: ALCHEMY
B24: 04-SPWHI-07000557 | C24: TEG | D24: Single Malt Scotch | E24: The Macallan | F24: MAC | G24: The Macallan Harmony Collection | H24: 700ml | I24: 6 | P24: 0 | R24: =IF(K24>0,K24*N24,L24*1.07*N24) -> 0 | S24: =ROUND(R24/1.07,2) -> 0 | T24: =IF(U24="Input Price only 1 column","",P24*S24) -> 0 | U24: =IF(AND(K24>0,L24>0),"Input Price only 1 column","OK") -> OK | V24: ='CASH REBATE'!$P$22 -> FALSE | W24: ALCHEMY
B25: 04-SPWHI-07001226 | C25: TEG | D25: Single Malt Scotch | E25: The Macallan | F25: MAC | G25: The Macallan Harmony Collection Intense Arabica | H25: 700ml | I25: 6 | P25: 0 | R25: =IF(K25>0,K25*N25,L25*1.07*N25) -> 0 | S25: =ROUND(R25/1.07,2) -> 0 | T25: =IF(U25="Input Price only 1 column","",P25*S25) -> 0 | U25: =IF(AND(K25>0,L25>0),"Input Price only 1 column","OK") -> OK | V25: ='CASH REBATE'!$P$22 -> FALSE | W25: ALCHEMY
... B337: 29-SPGIN-07006351 | C337: Remy Cointreau | D337: Gin | E337: Botanist | F337: BOT | G337: The Botanist Islay Dry Gin (Gift Box) | H337: 700ml | I337: 4 | P337: 0 | R337: =IF(K337>0,K337*N337,L337*1.07*N337) -> 0 | S337: =ROUND(R337/1.07,2) -> 0 | T337: =IF(U337="Input Price only 1 column","",P337*S337) -> 0 | U337: =IF(AND(K337>0,L337>0),"Input Price only 1 column","OK") -> OK | V337: ='CASH REBATE'!$P$22 -> FALSE | W337: ALCHEMY
B338: 31-SPMIX-1450PACK | C338: Campari | D338: Liqueur | E338: Aperol/Cinzano | G338: Aperol + Cinzano Prosecco | H338: 1450ml | I338: 3 | P338: 0 | R338: =IF(K338>0,K338*N338,L338*1.07*N338) -> 0 | S338: =ROUND(R338/1.07,2) -> 0 | T338: =IF(U338="Input Price only 1 column","",P338*S338) -> 0 | U338: =IF(AND(K338>0,L338>0),"Input Price only 1 column","OK") -> OK | V338: ='CASH REBATE'!$P$22 -> FALSE | W338: ALCHEMY
B339: 31-SPPAC-07000575 | C339: Campari | D339: Liqueur | E339: Aperol | F339: APR | G339: Aperol Glass Set | H339: 700ml | I339: 5 | P339: 0 | R339: =IF(K339>0,K339*N339,L339*1.07*N339) -> 0 | S339: =ROUND(R339/1.07,2) -> 0 | T339: =IF(U339="Input Price only 1 column","",P339*S339) -> 0 | U339: =IF(AND(K339>0,L339>0),"Input Price only 1 column","OK") -> OK | V339: ='CASH REBATE'!$P$22 -> FALSE | W339: ALCHEMY
B340: 32-06LIQ-05001051 | C340: Campari | D340: Liqueur | E340: Campari | F340: CAM | G340: Campari Negroni Liqueur | H340: 500ml | I340: 6 | P340: 0 | R340: =IF(K340>0,K340*N340,L340*1.07*N340) -> 0 | S340: =ROUND(R340/1.07,2) -> 0 | T340: =IF(U340="Input Price only 1 column","",P340*S340) -> 0 | U340: =IF(AND(K340>0,L340>0),"Input Price only 1 column","OK") -> OK | V340: ='CASH REBATE'!$P$22 -> FALSE | W340: ALCHEMY
B341: 32-06LIQ-07501402 | C341: Campari | D341: Liqueur | E341: Campari | F341: CAM | G341: Campari Bitter 750 ml | H341: 750ml | I341: 6 | P341: 0 | R341: =IF(K341>0,K341*N341,L341*1.07*N341) -> 0 | S341: =ROUND(R341/1.07,2) -> 0 | T341: =IF(U341="Input Price only 1 column","",P341*S341) -> 0 | U341: =IF(AND(K341>0,L341>0),"Input Price only 1 column","OK") -> OK | V341: ='CASH REBATE'!$P$22 -> FALSE | W341: ALCHEMY
B342: 32-SPPAC-07509002 | C342: Campari | D342: Liqueur | E342: Campari | F342: CAM | G342: Campari Negroni Set | H342: 2250ml | I342: 4 | P342: 0 | R342: =IF(K342>0,K342*N342,L342*1.07*N342) -> 0 | S342: =ROUND(R342/1.07,2) -> 0 | T342: =IF(U342="Input Price only 1 column","",P342*S342) -> 0 | U342: =IF(AND(K342>0,L342>0),"Input Price only 1 column","OK") -> OK | V342: ='CASH REBATE'!$P$22 -> FALSE | W342: ALCHEMY
